Workbook

Sheet Rate Card
AD1: Source rate inputs below (hidden) - every price on this sheet is a formula pointing at these cells. Unhide columns to edit.
B2: THE COURIER GUY — RATE CARD
B3: Effective 1 September 2026 | Version 14 | All figures in ZAR
B5: GLOBAL SETTINGS (edit only the blue cells — everything below updates automatically)
B6: VAT rate | C6: 0.15 | D6: Fuel levy % | E6: 0.165 | F6: Apply fuel levy? | G6: YES | H6: 30-day surcharge % | I6: 0.2 | J6: Apply 30-day surcharge? | K6: NO
B7: Apply insurance? | C7: YES | D7: Free cover threshold | E7: 1000 | F7: Insurance rate (% of value above) | G7: 0.02 | H7: Min charge (incl VAT) | I7: 57.5 | J7: <- calculator is on the Volumetric Calculator sheet
B8: Apply airfreight surcharge? | C8: NO | D8: Airfreight surcharge (R/kg) | E8: 6.88 | F8: Applies to PRI only (PRIR matched Ship Logic exactly with no surcharge in testing) on specific inter-zone routes (confirmed so far: Limpopo<->Eastern Cape, Limpopo<->Western Cape, Mpumalanga<->Eastern Cape, Mpumalanga<->Western Cape - list may not be exhaustive). Switch on manually only when quoting a route you know qualifies.
B9: FUEL SURCHARGE FINDER (match a live quote)
B10: Base rate on quote (incl VAT, excl fuel) | E10: 119.6
B11: Fuel surcharge amount shown on quote | E11: 19.73
B12: Base rate excl VAT (informational only) | E12: =IFERROR($E$10/(1+$C$6),"")
B13: Fuel levy % implied by this quote | E13: =IFERROR($E$11/$E$10,"")
B14: If this doesn't match the Fuel levy % above, the system quote and this sheet have drifted — update whichever is out of date.
B16: Legend: | D16: editable input | G16: priced off another service's rate (see note)
B18: 1. National / Default Rate — Default Group card
B19: Service | C19: Description | D19: Min charge (excl VAT) | E19: Up to (kg) | F19: Rate/kg thereafter (excl) | G19: Min charge (incl VAT) | H19: Rate/kg thereafter (incl) | I19: Notes
B20: LPF | C20: Local Priority Flyer | D20: =$AD$20 | E20: 5 | F20: =$AE$20 | G20: =ROUND($AD$20*(1+$C$6),2)+ROUND(ROUND($AD$20*(1+$C$6),2)*(IF($G$6="YES",$E$6,0)+IF($K$6="YES",$I$6,0)),2) | H20: =ROUND($AE$20*(1+$C$6),2)+ROUND(ROUND($AE$20*(1+$C$6),2)*(IF($G$6="YES",$E$6,0)+IF($K$6="YES",$I$6,0)),2) | I20: Local service — beyond 35kg, priced at the ECO/R rate above. | AD20: 94.96 | AE20: 13.04
B21: LPP | C21: Local Priority Parcel | D21: =$AD$21 | E21: 15 | F21: =$AE$21 | G21: =ROUND($AD$21*(1+$C$6),2)+ROUND(ROUND($AD$21*(1+$C$6),2)*(IF($G$6="YES",$E$6,0)+IF($K$6="YES",$I$6,0)),2) | H21: =ROUND($AE$21*(1+$C$6),2)+ROUND(ROUND($AE$21*(1+$C$6),2)*(IF($G$6="YES",$E$6,0)+IF($K$6="YES",$I$6,0)),2) | I21: Local service — beyond 35kg, priced at the ECO/R rate above. | AD21: 109.2 | AE21: 13.04
B22: ECO | C22: Economy Road — National | D22: =$AD$22 | E22: 2 | F22: =$AI$22 | G22: =ROUND($AD$22*(1+$C$6),2)+ROUND(ROUND($AD$22*(1+$C$6),2)*(IF($G$6="YES",$E$6,0)+IF($K$6="YES",$I$6,0)),2) | H22: =ROUND($AI$22*(1+$C$6),2)+ROUND(ROUND($AI$22*(1+$C$6),2)*(IF($G$6="YES",$E$6,0)+IF($K$6="YES",$I$6,0)),2) | AD22: 94.96 | AE22: 104 | AF22: 149.22 | AG22: 180.87 | AH22: 257.74 | AI22: 13.04 | AJ22: 17.39 | AK22: 453.39
B23: ECOR | C23: Economy Road — Regional | D23: =$AD$23 | E23: 2 | F23: =$AI$23 | G23: =ROUND($AD$23*(1+$C$6),2)+ROUND(ROUND($AD$23*(1+$C$6),2)*(IF($G$6="YES",$E$6,0)+IF($K$6="YES",$I$6,0)),2) | H23: =ROUND($AI$23*(1+$C$6),2)+ROUND(ROUND($AI$23*(1+$C$6),2)*(IF($G$6="YES",$E$6,0)+IF($K$6="YES",$I$6,0)),2) | AD23: 104.09 | AE23: 106 | AF23: 152.8 | AG23: 185.22 | AH23: 263.93 | AI23: 13.04 | AJ23: 17.39 | AK23: 459.59
B24: ECORR | C24: Economy Road — Regional to Regional | D24: =$AD$24 | E24: 2 | F24: =$AI$24 | G24: =ROUND($AD$24*(1+$C$6),2)+ROUND(ROUND($AD$24*(1+$C$6),2)*(IF($G$6="YES",$E$6,0)+IF($K$6="YES",$I$6,0)),2) | H24: =ROUND($AI$24*(1+$C$6),2)+ROUND(ROUND($AI$24*(1+$C$6),2)*(IF($G$6="YES",$E$6,0)+IF($K$6="YES",$I$6,0)),2) | AD24: 108.65 | AE24: 110.57 | AF24: 157.37 | AG24: 189.78 | AH24: 268.5 | AI24: 13.04 | AJ24: 17.39 | AK24: 464.15
B25: PRI | C25: Priority Courier — National | D25: =$AD$25 | E25: 2 | F25: =$AE$25 | G25: =ROUND($AD$25*(1+$C$6),2)+ROUND(ROUND($AD$25*(1+$C$6),2)*(IF($G$6="YES",$E$6,0)+IF($K$6="YES",$I$6,0)),2) | H25: =ROUND($AE$25*(1+$C$6),2)+ROUND(ROUND($AE$25*(1+$C$6),2)*(IF($G$6="YES",$E$6,0)+IF($K$6="YES",$I$6,0)),2) | I25: May carry an additional R/kg airfreight surcharge on certain inter-zone routes - see Global Settings above. | AD25: 151.93 | AE25: 48
B26: PRIR | C26: Priority Courier — Regional | D26: =$AD$26 | E26: 2 | F26: =$AE$26 | G26: =ROUND($AD$26*(1+$C$6),2)+ROUND(ROUND($AD$26*(1+$C$6),2)*(IF($G$6="YES",$E$6,0)+IF($K$6="YES",$I$6,0)),2) | H26: =ROUND($AE$26*(1+$C$6),2)+ROUND(ROUND($AE$26*(1+$C$6),2)*(IF($G$6="YES",$E$6,0)+IF($K$6="YES",$I$6,0)),2) | I26: May carry an additional R/kg airfreight surcharge on certain inter-zone routes - see Global Settings above. | AD26: 166.54 | AE26: 48
B28: Weight-based price — VAT & fuel levy EXCLUDED
B29: Kg | C29: LPF | D29: LPP | E29: ECO | F29: ECOR | G29: ECORR | H29: PRI | I29: PRIR
B30: 1 | C30: =IF(1<=5,$AD$20,$AD$20+(1-5)*$AE$20) | D30: =IF(1<=15,$AD$21,$AD$21+(1-15)*$AE$21) | E30: =IF(1<=2,$AD$22,IF(1<=5,$AE$22,IF(1<=10,$AF$22,IF(1<=15,$AG$22,IF(1<=20,$AH$22,IF(1<=35,$AH$22+(1-20)*$AI$22,$AK$22+(1-35)*$AJ$22)))))) | F30: =IF(1<=2,$AD$23,IF(1<=5,$AE$23,IF(1<=10,$AF$23,IF(1<=15,$AG$23,IF(1<=20,$AH$23,IF(1<=35,$AH$23+(1-20)*$AI$23,$AK$23+(1-35)*$AJ$23)))))) | G30: =IF(1<=2,$AD$24,IF(1<=5,$AE$24,IF(1<=10,$AF$24,IF(1<=15,$AG$24,IF(1<=20,$AH$24,IF(1<=35,$AH$24+(1-20)*$AI$24,$AK$24+(1-35)*$AJ$24)))))) | H30: =IF(1<=2,$AD$25,$AD$25+(1-2)*$AE$25) | I30: =IF(1<=2,$AD$26,$AD$26+(1-2)*$AE$26)
B31: 2 | C31: =IF(2<=5,$AD$20,$AD$20+(2-5)*$AE$20) | D31: =IF(2<=15,$AD$21,$AD$21+(2-15)*$AE$21) | E31: =IF(2<=2,$AD$22,IF(2<=5,$AE$22,IF(2<=10,$AF$22,IF(2<=15,$AG$22,IF(2<=20,$AH$22,IF(2<=35,$AH$22+(2-20)*$AI$22,$AK$22+(2-35)*$AJ$22)))))) | F31: =IF(2<=2,$AD$23,IF(2<=5,$AE$23,IF(2<=10,$AF$23,IF(2<=15,$AG$23,IF(2<=20,$AH$23,IF(2<=35,$AH$23+(2-20)*$AI$23,$AK$23+(2-35)*$AJ$23)))))) | G31: =IF(2<=2,$AD$24,IF(2<=5,$AE$24,IF(2<=10,$AF$24,IF(2<=15,$AG$24,IF(2<=20,$AH$24,IF(2<=35,$AH$24+(2-20)*$AI$24,$AK$24+(2-35)*$AJ$24)))))) | H31: =IF(2<=2,$AD$25,$AD$25+(2-2)*$AE$25) | I31: =IF(2<=2,$AD$26,$AD$26+(2-2)*$AE$26)
B32: 3 | C32: =IF(3<=5,$AD$20,$AD$20+(3-5)*$AE$20) | D32: =IF(3<=15,$AD$21,$AD$21+(3-15)*$AE$21) | E32: =IF(3<=2,$AD$22,IF(3<=5,$AE$22,IF(3<=10,$AF$22,IF(3<=15,$AG$22,IF(3<=20,$AH$22,IF(3<=35,$AH$22+(3-20)*$AI$22,$AK$22+(3-35)*$AJ$22)))))) | F32: =IF(3<=2,$AD$23,IF(3<=5,$AE$23,IF(3<=10,$AF$23,IF(3<=15,$AG$23,IF(3<=20,$AH$23,IF(3<=35,$AH$23+(3-20)*$AI$23,$AK$23+(3-35)*$AJ$23)))))) | G32: =IF(3<=2,$AD$24,IF(3<=5,$AE$24,IF(3<=10,$AF$24,IF(3<=15,$AG$24,IF(3<=20,$AH$24,IF(3<=35,$AH$24+(3-20)*$AI$24,$AK$24+(3-35)*$AJ$24)))))) | H32: =IF(3<=2,$AD$25,$AD$25+(3-2)*$AE$25) | I32: =IF(3<=2,$AD$26,$AD$26+(3-2)*$AE$26)
B33: 4 | C33: =IF(4<=5,$AD$20,$AD$20+(4-5)*$AE$20) | D33: =IF(4<=15,$AD$21,$AD$21+(4-15)*$AE$21) | E33: =IF(4<=2,$AD$22,IF(4<=5,$AE$22,IF(4<=10,$AF$22,IF(4<=15,$AG$22,IF(4<=20,$AH$22,IF(4<=35,$AH$22+(4-20)*$AI$22,$AK$22+(4-35)*$AJ$22)))))) | F33: =IF(4<=2,$AD$23,IF(4<=5,$AE$23,IF(4<=10,$AF$23,IF(4<=15,$AG$23,IF(4<=20,$AH$23,IF(4<=35,$AH$23+(4-20)*$AI$23,$AK$23+(4-35)*$AJ$23)))))) | G33: =IF(4<=2,$AD$24,IF(4<=5,$AE$24,IF(4<=10,$AF$24,IF(4<=15,$AG$24,IF(4<=20,$AH$24,IF(4<=35,$AH$24+(4-20)*$AI$24,$AK$24+(4-35)*$AJ$24)))))) | H33: =IF(4<=2,$AD$25,$AD$25+(4-2)*$AE$25) | I33: =IF(4<=2,$AD$26,$AD$26+(4-2)*$AE$26)
B34: 5 | C34: =IF(5<=5,$AD$20,$AD$20+(5-5)*$AE$20) | D34: =IF(5<=15,$AD$21,$AD$21+(5-15)*$AE$21) | E34: =IF(5<=2,$AD$22,IF(5<=5,$AE$22,IF(5<=10,$AF$22,IF(5<=15,$AG$22,IF(5<=20,$AH$22,IF(5<=35,$AH$22+(5-20)*$AI$22,$AK$22+(5-35)*$AJ$22)))))) | F34: =IF(5<=2,$AD$23,IF(5<=5,$AE$23,IF(5<=10,$AF$23,IF(5<=15,$AG$23,IF(5<=20,$AH$23,IF(5<=35,$AH$23+(5-20)*$AI$23,$AK$23+(5-35)*$AJ$23)))))) | G34: =IF(5<=2,$AD$24,IF(5<=5,$AE$24,IF(5<=10,$AF$24,IF(5<=15,$AG$24,IF(5<=20,$AH$24,IF(5<=35,$AH$24+(5-20)*$AI$24,$AK$24+(5-35)*$AJ$24)))))) | H34: =IF(5<=2,$AD$25,$AD$25+(5-2)*$AE$25) | I34: =IF(5<=2,$AD$26,$AD$26+(5-2)*$AE$26)
B35: 6 | C35: =IF(6<=5,$AD$20,$AD$20+(6-5)*$AE$20) | D35: =IF(6<=15,$AD$21,$AD$21+(6-15)*$AE$21) | E35: =IF(6<=2,$AD$22,IF(6<=5,$AE$22,IF(6<=10,$AF$22,IF(6<=15,$AG$22,IF(6<=20,$AH$22,IF(6<=35,$AH$22+(6-20)*$AI$22,$AK$22+(6-35)*$AJ$22)))))) | F35: =IF(6<=2,$AD$23,IF(6<=5,$AE$23,IF(6<=10,$AF$23,IF(6<=15,$AG$23,IF(6<=20,$AH$23,IF(6<=35,$AH$23+(6-20)*$AI$23,$AK$23+(6-35)*$AJ$23)))))) | G35: =IF(6<=2,$AD$24,IF(6<=5,$AE$24,IF(6<=10,$AF$24,IF(6<=15,$AG$24,IF(6<=20,$AH$24,IF(6<=35,$AH$24+(6-20)*$AI$24,$AK$24+(6-35)*$AJ$24)))))) | H35: =IF(6<=2,$AD$25,$AD$25+(6-2)*$AE$25) | I35: =IF(6<=2,$AD$26,$AD$26+(6-2)*$AE$26)
B36: 7 | C36: =IF(7<=5,$AD$20,$AD$20+(7-5)*$AE$20) | D36: =IF(7<=15,$AD$21,$AD$21+(7-15)*$AE$21) | E36: =IF(7<=2,$AD$22,IF(7<=5,$AE$22,IF(7<=10,$AF$22,IF(7<=15,$AG$22,IF(7<=20,$AH$22,IF(7<=35,$AH$22+(7-20)*$AI$22,$AK$22+(7-35)*$AJ$22)))))) | F36: =IF(7<=2,$AD$23,IF(7<=5,$AE$23,IF(7<=10,$AF$23,IF(7<=15,$AG$23,IF(7<=20,$AH$23,IF(7<=35,$AH$23+(7-20)*$AI$23,$AK$23+(7-35)*$AJ$23)))))) | G36: =IF(7<=2,$AD$24,IF(7<=5,$AE$24,IF(7<=10,$AF$24,IF(7<=15,$AG$24,IF(7<=20,$AH$24,IF(7<=35,$AH$24+(7-20)*$AI$24,$AK$24+(7-35)*$AJ$24)))))) | H36: =IF(7<=2,$AD$25,$AD$25+(7-2)*$AE$25) | I36: =IF(7<=2,$AD$26,$AD$26+(7-2)*$AE$26)
B37: 8 | C37: =IF(8<=5,$AD$20,$AD$20+(8-5)*$AE$20) | D37: =IF(8<=15,$AD$21,$AD$21+(8-15)*$AE$21) | E37: =IF(8<=2,$AD$22,IF(8<=5,$AE$22,IF(8<=10,$AF$22,IF(8<=15,$AG$22,IF(8<=20,$AH$22,IF(8<=35,$AH$22+(8-20)*$AI$22,$AK$22+(8-35)*$AJ$22)))))) | F37: =IF(8<=2,$AD$23,IF(8<=5,$AE$23,IF(8<=10,$AF$23,IF(8<=15,$AG$23,IF(8<=20,$AH$23,IF(8<=35,$AH$23+(8-20)*$AI$23,$AK$23+(8-35)*$AJ$23)))))) | G37: =IF(8<=2,$AD$24,IF(8<=5,$AE$24,IF(8<=10,$AF$24,IF(8<=15,$AG$24,IF(8<=20,$AH$24,IF(8<=35,$AH$24+(8-20)*$AI$24,$AK$24+(8-35)*$AJ$24)))))) | H37: =IF(8<=2,$AD$25,$AD$25+(8-2)*$AE$25) | I37: =IF(8<=2,$AD$26,$AD$26+(8-2)*$AE$26)
B38: 9 | C38: =IF(9<=5,$AD$20,$AD$20+(9-5)*$AE$20) | D38: =IF(9<=15,$AD$21,$AD$21+(9-15)*$AE$21) | E38: =IF(9<=2,$AD$22,IF(9<=5,$AE$22,IF(9<=10,$AF$22,IF(9<=15,$AG$22,IF(9<=20,$AH$22,IF(9<=35,$AH$22+(9-20)*$AI$22,$AK$22+(9-35)*$AJ$22)))))) | F38: =IF(9<=2,$AD$23,IF(9<=5,$AE$23,IF(9<=10,$AF$23,IF(9<=15,$AG$23,IF(9<=20,$AH$23,IF(9<=35,$AH$23+(9-20)*$AI$23,$AK$23+(9-35)*$AJ$23)))))) | G38: =IF(9<=2,$AD$24,IF(9<=5,$AE$24,IF(9<=10,$AF$24,IF(9<=15,$AG$24,IF(9<=20,$AH$24,IF(9<=35,$AH$24+(9-20)*$AI$24,$AK$24+(9-35)*$AJ$24)))))) | H38: =IF(9<=2,$AD$25,$AD$25+(9-2)*$AE$25) | I38: =IF(9<=2,$AD$26,$AD$26+(9-2)*$AE$26)
B39: 10 | C39: =IF(10<=5,$AD$20,$AD$20+(10-5)*$AE$20) | D39: =IF(10<=15,$AD$21,$AD$21+(10-15)*$AE$21) | E39: =IF(10<=2,$AD$22,IF(10<=5,$AE$22,IF(10<=10,$AF$22,IF(10<=15,$AG$22,IF(10<=20,$AH$22,IF(10<=35,$AH$22+(10-20)*$AI$22,$AK$22+(10-35)*$AJ$22)))))) | F39: =IF(10<=2,$AD$23,IF(10<=5,$AE$23,IF(10<=10,$AF$23,IF(10<=15,$AG$23,IF(10<=20,$AH$23,IF(10<=35,$AH$23+(10-20)*$AI$23,$AK$23+(10-35)*$AJ$23)))))) | G39: =IF(10<=2,$AD$24,IF(10<=5,$AE$24,IF(10<=10,$AF$24,IF(10<=15,$AG$24,IF(10<=20,$AH$24,IF(10<=35,$AH$24+(10-20)*$AI$24,$AK$24+(10-35)*$AJ$24)))))) | H39: =IF(10<=2,$AD$25,$AD$25+(10-2)*$AE$25) | I39: =IF(10<=2,$AD$26,$AD$26+(10-2)*$AE$26)
B40: 11 | C40: =IF(11<=5,$AD$20,$AD$20+(11-5)*$AE$20) | D40: =IF(11<=15,$AD$21,$AD$21+(11-15)*$AE$21) | E40: =IF(11<=2,$AD$22,IF(11<=5,$AE$22,IF(11<=10,$AF$22,IF(11<=15,$AG$22,IF(11<=20,$AH$22,IF(11<=35,$AH$22+(11-20)*$AI$22,$AK$22+(11-35)*$AJ$22)))))) | F40: =IF(11<=2,$AD$23,IF(11<=5,$AE$23,IF(11<=10,$AF$23,IF(11<=15,$AG$23,IF(11<=20,$AH$23,IF(11<=35,$AH$23+(11-20)*$AI$23,$AK$23+(11-35)*$AJ$23)))))) | G40: =IF(11<=2,$AD$24,IF(11<=5,$AE$24,IF(11<=10,$AF$24,IF(11<=15,$AG$24,IF(11<=20,$AH$24,IF(11<=35,$AH$24+(11-20)*$AI$24,$AK$24+(11-35)*$AJ$24)))))) | H40: =IF(11<=2,$AD$25,$AD$25+(11-2)*$AE$25) | I40: =IF(11<=2,$AD$26,$AD$26+(11-2)*$AE$26)
B41: 12 | C41: =IF(12<=5,$AD$20,$AD$20+(12-5)*$AE$20) | D41: =IF(12<=15,$AD$21,$AD$21+(12-15)*$AE$21) | E41: =IF(12<=2,$AD$22,IF(12<=5,$AE$22,IF(12<=10,$AF$22,IF(12<=15,$AG$22,IF(12<=20,$AH$22,IF(12<=35,$AH$22+(12-20)*$AI$22,$AK$22+(12-35)*$AJ$22)))))) | F41: =IF(12<=2,$AD$23,IF(12<=5,$AE$23,IF(12<=10,$AF$23,IF(12<=15,$AG$23,IF(12<=20,$AH$23,IF(12<=35,$AH$23+(12-20)*$AI$23,$AK$23+(12-35)*$AJ$23)))))) | G41: =IF(12<=2,$AD$24,IF(12<=5,$AE$24,IF(12<=10,$AF$24,IF(12<=15,$AG$24,IF(12<=20,$AH$24,IF(12<=35,$AH$24+(12-20)*$AI$24,$AK$24+(12-35)*$AJ$24)))))) | H41: =IF(12<=2,$AD$25,$AD$25+(12-2)*$AE$25) | I41: =IF(12<=2,$AD$26,$AD$26+(12-2)*$AE$26)
B42: 13 | C42: =IF(13<=5,$AD$20,$AD$20+(13-5)*$AE$20) | D42: =IF(13<=15,$AD$21,$AD$21+(13-15)*$AE$21) | E42: =IF(13<=2,$AD$22,IF(13<=5,$AE$22,IF(13<=10,$AF$22,IF(13<=15,$AG$22,IF(13<=20,$AH$22,IF(13<=35,$AH$22+(13-20)*$AI$22,$AK$22+(13-35)*$AJ$22)))))) | F42: =IF(13<=2,$AD$23,IF(13<=5,$AE$23,IF(13<=10,$AF$23,IF(13<=15,$AG$23,IF(13<=20,$AH$23,IF(13<=35,$AH$23+(13-20)*$AI$23,$AK$23+(13-35)*$AJ$23)))))) | G42: =IF(13<=2,$AD$24,IF(13<=5,$AE$24,IF(13<=10,$AF$24,IF(13<=15,$AG$24,IF(13<=20,$AH$24,IF(13<=35,$AH$24+(13-20)*$AI$24,$AK$24+(13-35)*$AJ$24)))))) | H42: =IF(13<=2,$AD$25,$AD$25+(13-2)*$AE$25) | I42: =IF(13<=2,$AD$26,$AD$26+(13-2)*$AE$26)
B43: 14 | C43: =IF(14<=5,$AD$20,$AD$20+(14-5)*$AE$20) | D43: =IF(14<=15,$AD$21,$AD$21+(14-15)*$AE$21) | E43: =IF(14<=2,$AD$22,IF(14<=5,$AE$22,IF(14<=10,$AF$22,IF(14<=15,$AG$22,IF(14<=20,$AH$22,IF(14<=35,$AH$22+(14-20)*$AI$22,$AK$22+(14-35)*$AJ$22)))))) | F43: =IF(14<=2,$AD$23,IF(14<=5,$AE$23,IF(14<=10,$AF$23,IF(14<=15,$AG$23,IF(14<=20,$AH$23,IF(14<=35,$AH$23+(14-20)*$AI$23,$AK$23+(14-35)*$AJ$23)))))) | G43: =IF(14<=2,$AD$24,IF(14<=5,$AE$24,IF(14<=10,$AF$24,IF(14<=15,$AG$24,IF(14<=20,$AH$24,IF(14<=35,$AH$24+(14-20)*$AI$24,$AK$24+(14-35)*$AJ$24)))))) | H43: =IF(14<=2,$AD$25,$AD$25+(14-2)*$AE$25) | I43: =IF(14<=2,$AD$26,$AD$26+(14-2)*$AE$26)
B44: 15 | C44: =IF(15<=5,$AD$20,$AD$20+(15-5)*$AE$20) | D44: =IF(15<=15,$AD$21,$AD$21+(15-15)*$AE$21) | E44: =IF(15<=2,$AD$22,IF(15<=5,$AE$22,IF(15<=10,$AF$22,IF(15<=15,$AG$22,IF(15<=20,$AH$22,IF(15<=35,$AH$22+(15-20)*$AI$22,$AK$22+(15-35)*$AJ$22)))))) | F44: =IF(15<=2,$AD$23,IF(15<=5,$AE$23,IF(15<=10,$AF$23,IF(15<=15,$AG$23,IF(15<=20,$AH$23,IF(15<=35,$AH$23+(15-20)*$AI$23,$AK$23+(15-35)*$AJ$23)))))) | G44: =IF(15<=2,$AD$24,IF(15<=5,$AE$24,IF(15<=10,$AF$24,IF(15<=15,$AG$24,IF(15<=20,$AH$24,IF(15<=35,$AH$24+(15-20)*$AI$24,$AK$24+(15-35)*$AJ$24)))))) | H44: =IF(15<=2,$AD$25,$AD$25+(15-2)*$AE$25) | I44: =IF(15<=2,$AD$26,$AD$26+(15-2)*$AE$26)
B45: 16 | C45: =IF(16<=5,$AD$20,$AD$20+(16-5)*$AE$20) | D45: =IF(16<=15,$AD$21,$AD$21+(16-15)*$AE$21) | E45: =IF(16<=2,$AD$22,IF(16<=5,$AE$22,IF(16<=10,$AF$22,IF(16<=15,$AG$22,IF(16<=20,$AH$22,IF(16<=35,$AH$22+(16-20)*$AI$22,$AK$22+(16-35)*$AJ$22)))))) | F45: =IF(16<=2,$AD$23,IF(16<=5,$AE$23,IF(16<=10,$AF$23,IF(16<=15,$AG$23,IF(16<=20,$AH$23,IF(16<=35,$AH$23+(16-20)*$AI$23,$AK$23+(16-35)*$AJ$23)))))) | G45: =IF(16<=2,$AD$24,IF(16<=5,$AE$24,IF(16<=10,$AF$24,IF(16<=15,$AG$24,IF(16<=20,$AH$24,IF(16<=35,$AH$24+(16-20)*$AI$24,$AK$24+(16-35)*$AJ$24)))))) | H45: =IF(16<=2,$AD$25,$AD$25+(16-2)*$AE$25) | I45: =IF(16<=2,$AD$26,$AD$26+(16-2)*$AE$26)
B46: 17 | C46: =IF(17<=5,$AD$20,$AD$20+(17-5)*$AE$20) | D46: =IF(17<=15,$AD$21,$AD$21+(17-15)*$AE$21) | E46: =IF(17<=2,$AD$22,IF(17<=5,$AE$22,IF(17<=10,$AF$22,IF(17<=15,$AG$22,IF(17<=20,$AH$22,IF(17<=35,$AH$22+(17-20)*$AI$22,$AK$22+(17-35)*$AJ$22)))))) | F46: =IF(17<=2,$AD$23,IF(17<=5,$AE$23,IF(17<=10,$AF$23,IF(17<=15,$AG$23,IF(17<=20,$AH$23,IF(17<=35,$AH$23+(17-20)*$AI$23,$AK$23+(17-35)*$AJ$23)))))) | G46: =IF(17<=2,$AD$24,IF(17<=5,$AE$24,IF(17<=10,$AF$24,IF(17<=15,$AG$24,IF(17<=20,$AH$24,IF(17<=35,$AH$24+(17-20)*$AI$24,$AK$24+(17-35)*$AJ$24)))))) | H46: =IF(17<=2,$AD$25,$AD$25+(17-2)*$AE$25) | I46: =IF(17<=2,$AD$26,$AD$26+(17-2)*$AE$26)
B47: 18 | C47: =IF(18<=5,$AD$20,$AD$20+(18-5)*$AE$20) | D47: =IF(18<=15,$AD$21,$AD$21+(18-15)*$AE$21) | E47: =IF(18<=2,$AD$22,IF(18<=5,$AE$22,IF(18<=10,$AF$22,IF(18<=15,$AG$22,IF(18<=20,$AH$22,IF(18<=35,$AH$22+(18-20)*$AI$22,$AK$22+(18-35)*$AJ$22)))))) | F47: =IF(18<=2,$AD$23,IF(18<=5,$AE$23,IF(18<=10,$AF$23,IF(18<=15,$AG$23,IF(18<=20,$AH$23,IF(18<=35,$AH$23+(18-20)*$AI$23,$AK$23+(18-35)*$AJ$23)))))) | G47: =IF(18<=2,$AD$24,IF(18<=5,$AE$24,IF(18<=10,$AF$24,IF(18<=15,$AG$24,IF(18<=20,$AH$24,IF(18<=35,$AH$24+(18-20)*$AI$24,$AK$24+(18-35)*$AJ$24)))))) | H47: =IF(18<=2,$AD$25,$AD$25+(18-2)*$AE$25) | I47: =IF(18<=2,$AD$26,$AD$26+(18-2)*$AE$26)
B48: 19 | C48: =IF(19<=5,$AD$20,$AD$20+(19-5)*$AE$20) | D48: =IF(19<=15,$AD$21,$AD$21+(19-15)*$AE$21) | E48: =IF(19<=2,$AD$22,IF(19<=5,$AE$22,IF(19<=10,$AF$22,IF(19<=15,$AG$22,IF(19<=20,$AH$22,IF(19<=35,$AH$22+(19-20)*$AI$22,$AK$22+(19-35)*$AJ$22)))))) | F48: =IF(19<=2,$AD$23,IF(19<=5,$AE$23,IF(19<=10,$AF$23,IF(19<=15,$AG$23,IF(19<=20,$AH$23,IF(19<=35,$AH$23+(19-20)*$AI$23,$AK$23+(19-35)*$AJ$23)))))) | G48: =IF(19<=2,$AD$24,IF(19<=5,$AE$24,IF(19<=10,$AF$24,IF(19<=15,$AG$24,IF(19<=20,$AH$24,IF(19<=35,$AH$24+(19-20)*$AI$24,$AK$24+(19-35)*$AJ$24)))))) | H48: =IF(19<=2,$AD$25,$AD$25+(19-2)*$AE$25) | I48: =IF(19<=2,$AD$26,$AD$26+(19-2)*$AE$26)
B49: 20 | C49: =IF(20<=5,$AD$20,$AD$20+(20-5)*$AE$20) | D49: =IF(20<=15,$AD$21,$AD$21+(20-15)*$AE$21) | E49: =IF(20<=2,$AD$22,IF(20<=5,$AE$22,IF(20<=10,$AF$22,IF(20<=15,$AG$22,IF(20<=20,$AH$22,IF(20<=35,$AH$22+(20-20)*$AI$22,$AK$22+(20-35)*$AJ$22)))))) | F49: =IF(20<=2,$AD$23,IF(20<=5,$AE$23,IF(20<=10,$AF$23,IF(20<=15,$AG$23,IF(20<=20,$AH$23,IF(20<=35,$AH$23+(20-20)*$AI$23,$AK$23+(20-35)*$AJ$23)))))) | G49: =IF(20<=2,$AD$24,IF(20<=5,$AE$24,IF(20<=10,$AF$24,IF(20<=15,$AG$24,IF(20<=20,$AH$24,IF(20<=35,$AH$24+(20-20)*$AI$24,$AK$24+(20-35)*$AJ$24)))))) | H49: =IF(20<=2,$AD$25,$AD$25+(20-2)*$AE$25) | I49: =IF(20<=2,$AD$26,$AD$26+(20-2)*$AE$26)
B50: 21 | C50: =IF(21<=5,$AD$20,$AD$20+(21-5)*$AE$20) | D50: =IF(21<=15,$AD$21,$AD$21+(21-15)*$AE$21) | E50: =IF(21<=2,$AD$22,IF(21<=5,$AE$22,IF(21<=10,$AF$22,IF(21<=15,$AG$22,IF(21<=20,$AH$22,IF(21<=35,$AH$22+(21-20)*$AI$22,$AK$22+(21-35)*$AJ$22)))))) | F50: =IF(21<=2,$AD$23,IF(21<=5,$AE$23,IF(21<=10,$AF$23,IF(21<=15,$AG$23,IF(21<=20,$AH$23,IF(21<=35,$AH$23+(21-20)*$AI$23,$AK$23+(21-35)*$AJ$23)))))) | G50: =IF(21<=2,$AD$24,IF(21<=5,$AE$24,IF(21<=10,$AF$24,IF(21<=15,$AG$24,IF(21<=20,$AH$24,IF(21<=35,$AH$24+(21-20)*$AI$24,$AK$24+(21-35)*$AJ$24)))))) | H50: =IF(21<=2,$AD$25,$AD$25+(21-2)*$AE$25) | I50: =IF(21<=2,$AD$26,$AD$26+(21-2)*$AE$26)
B51: 22 | C51: =IF(22<=5,$AD$20,$AD$20+(22-5)*$AE$20) | D51: =IF(22<=15,$AD$21,$AD$21+(22-15)*$AE$21) | E51: =IF(22<=2,$AD$22,IF(22<=5,$AE$22,IF(22<=10,$AF$22,IF(22<=15,$AG$22,IF(22<=20,$AH$22,IF(22<=35,$AH$22+(22-20)*$AI$22,$AK$22+(22-35)*$AJ$22)))))) | F51: =IF(22<=2,$AD$23,IF(22<=5,$AE$23,IF(22<=10,$AF$23,IF(22<=15,$AG$23,IF(22<=20,$AH$23,IF(22<=35,$AH$23+(22-20)*$AI$23,$AK$23+(22-35)*$AJ$23)))))) | G51: =IF(22<=2,$AD$24,IF(22<=5,$AE$24,IF(22<=10,$AF$24,IF(22<=15,$AG$24,IF(22<=20,$AH$24,IF(22<=35,$AH$24+(22-20)*$AI$24,$AK$24+(22-35)*$AJ$24)))))) | H51: =IF(22<=2,$AD$25,$AD$25+(22-2)*$AE$25) | I51: =IF(22<=2,$AD$26,$AD$26+(22-2)*$AE$26)
B52: 23 | C52: =IF(23<=5,$AD$20,$AD$20+(23-5)*$AE$20) | D52: =IF(23<=15,$AD$21,$AD$21+(23-15)*$AE$21) | E52: =IF(23<=2,$AD$22,IF(23<=5,$AE$22,IF(23<=10,$AF$22,IF(23<=15,$AG$22,IF(23<=20,$AH$22,IF(23<=35,$AH$22+(23-20)*$AI$22,$AK$22+(23-35)*$AJ$22)))))) | F52: =IF(23<=2,$AD$23,IF(23<=5,$AE$23,IF(23<=10,$AF$23,IF(23<=15,$AG$23,IF(23<=20,$AH$23,IF(23<=35,$AH$23+(23-20)*$AI$23,$AK$23+(23-35)*$AJ$23)))))) | G52: =IF(23<=2,$AD$24,IF(23<=5,$AE$24,IF(23<=10,$AF$24,IF(23<=15,$AG$24,IF(23<=20,$AH$24,IF(23<=35,$AH$24+(23-20)*$AI$24,$AK$24+(23-35)*$AJ$24)))))) | H52: =IF(23<=2,$AD$25,$AD$25+(23-2)*$AE$25) | I52: =IF(23<=2,$AD$26,$AD$26+(23-2)*$AE$26)
B53: 24 | C53: =IF(24<=5,$AD$20,$AD$20+(24-5)*$AE$20) | D53: =IF(24<=15,$AD$21,$AD$21+(24-15)*$AE$21) | E53: =IF(24<=2,$AD$22,IF(24<=5,$AE$22,IF(24<=10,$AF$22,IF(24<=15,$AG$22,IF(24<=20,$AH$22,IF(24<=35,$AH$22+(24-20)*$AI$22,$AK$22+(24-35)*$AJ$22)))))) | F53: =IF(24<=2,$AD$23,IF(24<=5,$AE$23,IF(24<=10,$AF$23,IF(24<=15,$AG$23,IF(24<=20,$AH$23,IF(24<=35,$AH$23+(24-20)*$AI$23,$AK$23+(24-35)*$AJ$23)))))) | G53: =IF(24<=2,$AD$24,IF(24<=5,$AE$24,IF(24<=10,$AF$24,IF(24<=15,$AG$24,IF(24<=20,$AH$24,IF(24<=35,$AH$24+(24-20)*$AI$24,$AK$24+(24-35)*$AJ$24)))))) | H53: =IF(24<=2,$AD$25,$AD$25+(24-2)*$AE$25) | I53: =IF(24<=2,$AD$26,$AD$26+(24-2)*$AE$26)
B54: 25 | C54: =IF(25<=5,$AD$20,$AD$20+(25-5)*$AE$20) | D54: =IF(25<=15,$AD$21,$AD$21+(25-15)*$AE$21) | E54: =IF(25<=2,$AD$22,IF(25<=5,$AE$22,IF(25<=10,$AF$22,IF(25<=15,$AG$22,IF(25<=20,$AH$22,IF(25<=35,$AH$22+(25-20)*$AI$22,$AK$22+(25-35)*$AJ$22)))))) | F54: =IF(25<=2,$AD$23,IF(25<=5,$AE$23,IF(25<=10,$AF$23,IF(25<=15,$AG$23,IF(25<=20,$AH$23,IF(25<=35,$AH$23+(25-20)*$AI$23,$AK$23+(25-35)*$AJ$23)))))) | G54: =IF(25<=2,$AD$24,IF(25<=5,$AE$24,IF(25<=10,$AF$24,IF(25<=15,$AG$24,IF(25<=20,$AH$24,IF(25<=35,$AH$24+(25-20)*$AI$24,$AK$24+(25-35)*$AJ$24)))))) | H54: =IF(25<=2,$AD$25,$AD$25+(25-2)*$AE$25) | I54: =IF(25<=2,$AD$26,$AD$26+(25-2)*$AE$26)
B55: 26 | C55: =IF(26<=5,$AD$20,$AD$20+(26-5)*$AE$20) | D55: =IF(26<=15,$AD$21,$AD$21+(26-15)*$AE$21) | E55: =IF(26<=2,$AD$22,IF(26<=5,$AE$22,IF(26<=10,$AF$22,IF(26<=15,$AG$22,IF(26<=20,$AH$22,IF(26<=35,$AH$22+(26-20)*$AI$22,$AK$22+(26-35)*$AJ$22)))))) | F55: =IF(26<=2,$AD$23,IF(26<=5,$AE$23,IF(26<=10,$AF$23,IF(26<=15,$AG$23,IF(26<=20,$AH$23,IF(26<=35,$AH$23+(26-20)*$AI$23,$AK$23+(26-35)*$AJ$23)))))) | G55: =IF(26<=2,$AD$24,IF(26<=5,$AE$24,IF(26<=10,$AF$24,IF(26<=15,$AG$24,IF(26<=20,$AH$24,IF(26<=35,$AH$24+(26-20)*$AI$24,$AK$24+(26-35)*$AJ$24)))))) | H55: =IF(26<=2,$AD$25,$AD$25+(26-2)*$AE$25) | I55: =IF(26<=2,$AD$26,$AD$26+(26-2)*$AE$26)
B56: 27 | C56: =IF(27<=5,$AD$20,$AD$20+(27-5)*$AE$20) | D56: =IF(27<=15,$AD$21,$AD$21+(27-15)*$AE$21) | E56: =IF(27<=2,$AD$22,IF(27<=5,$AE$22,IF(27<=10,$AF$22,IF(27<=15,$AG$22,IF(27<=20,$AH$22,IF(27<=35,$AH$22+(27-20)*$AI$22,$AK$22+(27-35)*$AJ$22)))))) | F56: =IF(27<=2,$AD$23,IF(27<=5,$AE$23,IF(27<=10,$AF$23,IF(27<=15,$AG$23,IF(27<=20,$AH$23,IF(27<=35,$AH$23+(27-20)*$AI$23,$AK$23+(27-35)*$AJ$23)))))) | G56: =IF(27<=2,$AD$24,IF(27<=5,$AE$24,IF(27<=10,$AF$24,IF(27<=15,$AG$24,IF(27<=20,$AH$24,IF(27<=35,$AH$24+(27-20)*$AI$24,$AK$24+(27-35)*$AJ$24)))))) | H56: =IF(27<=2,$AD$25,$AD$25+(27-2)*$AE$25) | I56: =IF(27<=2,$AD$26,$AD$26+(27-2)*$AE$26)
B57: 28 | C57: =IF(28<=5,$AD$20,$AD$20+(28-5)*$AE$20) | D57: =IF(28<=15,$AD$21,$AD$21+(28-15)*$AE$21) | E57: =IF(28<=2,$AD$22,IF(28<=5,$AE$22,IF(28<=10,$AF$22,IF(28<=15,$AG$22,IF(28<=20,$AH$22,IF(28<=35,$AH$22+(28-20)*$AI$22,$AK$22+(28-35)*$AJ$22)))))) | F57: =IF(28<=2,$AD$23,IF(28<=5,$AE$23,IF(28<=10,$AF$23,IF(28<=15,$AG$23,IF(28<=20,$AH$23,IF(28<=35,$AH$23+(28-20)*$AI$23,$AK$23+(28-35)*$AJ$23)))))) | G57: =IF(28<=2,$AD$24,IF(28<=5,$AE$24,IF(28<=10,$AF$24,IF(28<=15,$AG$24,IF(28<=20,$AH$24,IF(28<=35,$AH$24+(28-20)*$AI$24,$AK$24+(28-35)*$AJ$24)))))) | H57: =IF(28<=2,$AD$25,$AD$25+(28-2)*$AE$25) | I57: =IF(28<=2,$AD$26,$AD$26+(28-2)*$AE$26)
B58: 29 | C58: =IF(29<=5,$AD$20,$AD$20+(29-5)*$AE$20) | D58: =IF(29<=15,$AD$21,$AD$21+(29-15)*$AE$21) | E58: =IF(29<=2,$AD$22,IF(29<=5,$AE$22,IF(29<=10,$AF$22,IF(29<=15,$AG$22,IF(29<=20,$AH$22,IF(29<=35,$AH$22+(29-20)*$AI$22,$AK$22+(29-35)*$AJ$22)))))) | F58: =IF(29<=2,$AD$23,IF(29<=5,$AE$23,IF(29<=10,$AF$23,IF(29<=15,$AG$23,IF(29<=20,$AH$23,IF(29<=35,$AH$23+(29-20)*$AI$23,$AK$23+(29-35)*$AJ$23)))))) | G58: =IF(29<=2,$AD$24,IF(29<=5,$AE$24,IF(29<=10,$AF$24,IF(29<=15,$AG$24,IF(29<=20,$AH$24,IF(29<=35,$AH$24+(29-20)*$AI$24,$AK$24+(29-35)*$AJ$24)))))) | H58: =IF(29<=2,$AD$25,$AD$25+(29-2)*$AE$25) | I58: =IF(29<=2,$AD$26,$AD$26+(29-2)*$AE$26)
B59: 30 | C59: =IF(30<=5,$AD$20,$AD$20+(30-5)*$AE$20) | D59: =IF(30<=15,$AD$21,$AD$21+(30-15)*$AE$21) | E59: =IF(30<=2,$AD$22,IF(30<=5,$AE$22,IF(30<=10,$AF$22,IF(30<=15,$AG$22,IF(30<=20,$AH$22,IF(30<=35,$AH$22+(30-20)*$AI$22,$AK$22+(30-35)*$AJ$22)))))) | F59: =IF(30<=2,$AD$23,IF(30<=5,$AE$23,IF(30<=10,$AF$23,IF(30<=15,$AG$23,IF(30<=20,$AH$23,IF(30<=35,$AH$23+(30-20)*$AI$23,$AK$23+(30-35)*$AJ$23)))))) | G59: =IF(30<=2,$AD$24,IF(30<=5,$AE$24,IF(30<=10,$AF$24,IF(30<=15,$AG$24,IF(30<=20,$AH$24,IF(30<=35,$AH$24+(30-20)*$AI$24,$AK$24+(30-35)*$AJ$24)))))) | H59: =IF(30<=2,$AD$25,$AD$25+(30-2)*$AE$25) | I59: =IF(30<=2,$AD$26,$AD$26+(30-2)*$AE$26)
B60: 31 | C60: =IF(31<=5,$AD$20,$AD$20+(31-5)*$AE$20) | D60: =IF(31<=15,$AD$21,$AD$21+(31-15)*$AE$21) | E60: =IF(31<=2,$AD$22,IF(31<=5,$AE$22,IF(31<=10,$AF$22,IF(31<=15,$AG$22,IF(31<=20,$AH$22,IF(31<=35,$AH$22+(31-20)*$AI$22,$AK$22+(31-35)*$AJ$22)))))) | F60: =IF(31<=2,$AD$23,IF(31<=5,$AE$23,IF(31<=10,$AF$23,IF(31<=15,$AG$23,IF(31<=20,$AH$23,IF(31<=35,$AH$23+(31-20)*$AI$23,$AK$23+(31-35)*$AJ$23)))))) | G60: =IF(31<=2,$AD$24,IF(31<=5,$AE$24,IF(31<=10,$AF$24,IF(31<=15,$AG$24,IF(31<=20,$AH$24,IF(31<=35,$AH$24+(31-20)*$AI$24,$AK$24+(31-35)*$AJ$24)))))) | H60: =IF(31<=2,$AD$25,$AD$25+(31-2)*$AE$25) | I60: =IF(31<=2,$AD$26,$AD$26+(31-2)*$AE$26)
B61: 32 | C61: =IF(32<=5,$AD$20,$AD$20+(32-5)*$AE$20) | D61: =IF(32<=15,$AD$21,$AD$21+(32-15)*$AE$21) | E61: =IF(32<=2,$AD$22,IF(32<=5,$AE$22,IF(32<=10,$AF$22,IF(32<=15,$AG$22,IF(32<=20,$AH$22,IF(32<=35,$AH$22+(32-20)*$AI$22,$AK$22+(32-35)*$AJ$22)))))) | F61: =IF(32<=2,$AD$23,IF(32<=5,$AE$23,IF(32<=10,$AF$23,IF(32<=15,$AG$23,IF(32<=20,$AH$23,IF(32<=35,$AH$23+(32-20)*$AI$23,$AK$23+(32-35)*$AJ$23)))))) | G61: =IF(32<=2,$AD$24,IF(32<=5,$AE$24,IF(32<=10,$AF$24,IF(32<=15,$AG$24,IF(32<=20,$AH$24,IF(32<=35,$AH$24+(32-20)*$AI$24,$AK$24+(32-35)*$AJ$24)))))) | H61: =IF(32<=2,$AD$25,$AD$25+(32-2)*$AE$25) | I61: =IF(32<=2,$AD$26,$AD$26+(32-2)*$AE$26)
B62: 33 | C62: =IF(33<=5,$AD$20,$AD$20+(33-5)*$AE$20) | D62: =IF(33<=15,$AD$21,$AD$21+(33-15)*$AE$21) | E62: =IF(33<=2,$AD$22,IF(33<=5,$AE$22,IF(33<=10,$AF$22,IF(33<=15,$AG$22,IF(33<=20,$AH$22,IF(33<=35,$AH$22+(33-20)*$AI$22,$AK$22+(33-35)*$AJ$22)))))) | F62: =IF(33<=2,$AD$23,IF(33<=5,$AE$23,IF(33<=10,$AF$23,IF(33<=15,$AG$23,IF(33<=20,$AH$23,IF(33<=35,$AH$23+(33-20)*$AI$23,$AK$23+(33-35)*$AJ$23)))))) | G62: =IF(33<=2,$AD$24,IF(33<=5,$AE$24,IF(33<=10,$AF$24,IF(33<=15,$AG$24,IF(33<=20,$AH$24,IF(33<=35,$AH$24+(33-20)*$AI$24,$AK$24+(33-35)*$AJ$24)))))) | H62: =IF(33<=2,$AD$25,$AD$25+(33-2)*$AE$25) | I62: =IF(33<=2,$AD$26,$AD$26+(33-2)*$AE$26)
B63: 34 | C63: =IF(34<=5,$AD$20,$AD$20+(34-5)*$AE$20) | D63: =IF(34<=15,$AD$21,$AD$21+(34-15)*$AE$21) | E63: =IF(34<=2,$AD$22,IF(34<=5,$AE$22,IF(34<=10,$AF$22,IF(34<=15,$AG$22,IF(34<=20,$AH$22,IF(34<=35,$AH$22+(34-20)*$AI$22,$AK$22+(34-35)*$AJ$22)))))) | F63: =IF(34<=2,$AD$23,IF(34<=5,$AE$23,IF(34<=10,$AF$23,IF(34<=15,$AG$23,IF(34<=20,$AH$23,IF(34<=35,$AH$23+(34-20)*$AI$23,$AK$23+(34-35)*$AJ$23)))))) | G63: =IF(34<=2,$AD$24,IF(34<=5,$AE$24,IF(34<=10,$AF$24,IF(34<=15,$AG$24,IF(34<=20,$AH$24,IF(34<=35,$AH$24+(34-20)*$AI$24,$AK$24+(34-35)*$AJ$24)))))) | H63: =IF(34<=2,$AD$25,$AD$25+(34-2)*$AE$25) | I63: =IF(34<=2,$AD$26,$AD$26+(34-2)*$AE$26)
B64: 35 | C64: =IF(35<=5,$AD$20,$AD$20+(35-5)*$AE$20) | D64: =IF(35<=15,$AD$21,$AD$21+(35-15)*$AE$21) | E64: =IF(35<=2,$AD$22,IF(35<=5,$AE$22,IF(35<=10,$AF$22,IF(35<=15,$AG$22,IF(35<=20,$AH$22,IF(35<=35,$AH$22+(35-20)*$AI$22,$AK$22+(35-35)*$AJ$22)))))) | F64: =IF(35<=2,$AD$23,IF(35<=5,$AE$23,IF(35<=10,$AF$23,IF(35<=15,$AG$23,IF(35<=20,$AH$23,IF(35<=35,$AH$23+(35-20)*$AI$23,$AK$23+(35-35)*$AJ$23)))))) | G64: =IF(35<=2,$AD$24,IF(35<=5,$AE$24,IF(35<=10,$AF$24,IF(35<=15,$AG$24,IF(35<=20,$AH$24,IF(35<=35,$AH$24+(35-20)*$AI$24,$AK$24+(35-35)*$AJ$24)))))) | H64: =IF(35<=2,$AD$25,$AD$25+(35-2)*$AE$25) | I64: =IF(35<=2,$AD$26,$AD$26+(35-2)*$AE$26)
B65: 36 | C65: see ECO/R | D65: see ECO/R | E65: =IF(36<=2,$AD$22,IF(36<=5,$AE$22,IF(36<=10,$AF$22,IF(36<=15,$AG$22,IF(36<=20,$AH$22,IF(36<=35,$AH$22+(36-20)*$AI$22,$AK$22+(36-35)*$AJ$22)))))) | F65: =IF(36<=2,$AD$23,IF(36<=5,$AE$23,IF(36<=10,$AF$23,IF(36<=15,$AG$23,IF(36<=20,$AH$23,IF(36<=35,$AH$23+(36-20)*$AI$23,$AK$23+(36-35)*$AJ$23)))))) | G65: =IF(36<=2,$AD$24,IF(36<=5,$AE$24,IF(36<=10,$AF$24,IF(36<=15,$AG$24,IF(36<=20,$AH$24,IF(36<=35,$AH$24+(36-20)*$AI$24,$AK$24+(36-35)*$AJ$24)))))) | H65: =IF(36<=2,$AD$25,$AD$25+(36-2)*$AE$25) | I65: =IF(36<=2,$AD$26,$AD$26+(36-2)*$AE$26)
B66: 37 | C66: see ECO/R | D66: see ECO/R | E66: =IF(37<=2,$AD$22,IF(37<=5,$AE$22,IF(37<=10,$AF$22,IF(37<=15,$AG$22,IF(37<=20,$AH$22,IF(37<=35,$AH$22+(37-20)*$AI$22,$AK$22+(37-35)*$AJ$22)))))) | F66: =IF(37<=2,$AD$23,IF(37<=5,$AE$23,IF(37<=10,$AF$23,IF(37<=15,$AG$23,IF(37<=20,$AH$23,IF(37<=35,$AH$23+(37-20)*$AI$23,$AK$23+(37-35)*$AJ$23)))))) | G66: =IF(37<=2,$AD$24,IF(37<=5,$AE$24,IF(37<=10,$AF$24,IF(37<=15,$AG$24,IF(37<=20,$AH$24,IF(37<=35,$AH$24+(37-20)*$AI$24,$AK$24+(37-35)*$AJ$24)))))) | H66: =IF(37<=2,$AD$25,$AD$25+(37-2)*$AE$25) | I66: =IF(37<=2,$AD$26,$AD$26+(37-2)*$AE$26)
B67: 38 | C67: see ECO/R | D67: see ECO/R | E67: =IF(38<=2,$AD$22,IF(38<=5,$AE$22,IF(38<=10,$AF$22,IF(38<=15,$AG$22,IF(38<=20,$AH$22,IF(38<=35,$AH$22+(38-20)*$AI$22,$AK$22+(38-35)*$AJ$22)))))) | F67: =IF(38<=2,$AD$23,IF(38<=5,$AE$23,IF(38<=10,$AF$23,IF(38<=15,$AG$23,IF(38<=20,$AH$23,IF(38<=35,$AH$23+(38-20)*$AI$23,$AK$23+(38-35)*$AJ$23)))))) | G67: =IF(38<=2,$AD$24,IF(38<=5,$AE$24,IF(38<=10,$AF$24,IF(38<=15,$AG$24,IF(38<=20,$AH$24,IF(38<=35,$AH$24+(38-20)*$AI$24,$AK$24+(38-35)*$AJ$24)))))) | H67: =IF(38<=2,$AD$25,$AD$25+(38-2)*$AE$25) | I67: =IF(38<=2,$AD$26,$AD$26+(38-2)*$AE$26)
B68: 39 | C68: see ECO/R | D68: see ECO/R | E68: =IF(39<=2,$AD$22,IF(39<=5,$AE$22,IF(39<=10,$AF$22,IF(39<=15,$AG$22,IF(39<=20,$AH$22,IF(39<=35,$AH$22+(39-20)*$AI$22,$AK$22+(39-35)*$AJ$22)))))) | F68: =IF(39<=2,$AD$23,IF(39<=5,$AE$23,IF(39<=10,$AF$23,IF(39<=15,$AG$23,IF(39<=20,$AH$23,IF(39<=35,$AH$23+(39-20)*$AI$23,$AK$23+(39-35)*$AJ$23)))))) | G68: =IF(39<=2,$AD$24,IF(39<=5,$AE$24,IF(39<=10,$AF$24,IF(39<=15,$AG$24,IF(39<=20,$AH$24,IF(39<=35,$AH$24+(39-20)*$AI$24,$AK$24+(39-35)*$AJ$24)))))) | H68: =IF(39<=2,$AD$25,$AD$25+(39-2)*$AE$25) | I68: =IF(39<=2,$AD$26,$AD$26+(39-2)*$AE$26)
B69: 40 | C69: see ECO/R | D69: see ECO/R | E69: =IF(40<=2,$AD$22,IF(40<=5,$AE$22,IF(40<=10,$AF$22,IF(40<=15,$AG$22,IF(40<=20,$AH$22,IF(40<=35,$AH$22+(40-20)*$AI$22,$AK$22+(40-35)*$AJ$22)))))) | F69: =IF(40<=2,$AD$23,IF(40<=5,$AE$23,IF(40<=10,$AF$23,IF(40<=15,$AG$23,IF(40<=20,$AH$23,IF(40<=35,$AH$23+(40-20)*$AI$23,$AK$23+(40-35)*$AJ$23)))))) | G69: =IF(40<=2,$AD$24,IF(40<=5,$AE$24,IF(40<=10,$AF$24,IF(40<=15,$AG$24,IF(40<=20,$AH$24,IF(40<=35,$AH$24+(40-20)*$AI$24,$AK$24+(40-35)*$AJ$24)))))) | H69: =IF(40<=2,$AD$25,$AD$25+(40-2)*$AE$25) | I69: =IF(40<=2,$AD$26,$AD$26+(40-2)*$AE$26)
B71: Weight-based price — VAT & fuel levy INCLUDED
B72: Kg | C72: LPF | D72: LPP | E72: ECO | F72: ECOR | G72: ECORR | H72: PRI | I72: PRIR
B73: 1 | C73: =ROUND((IF(1<=5,$AD$20,$AD$20+(1-5)*$AE$20))*(1+$C$6),2)+ROUND(ROUND((IF(1<=5,$AD$20,$AD$20+(1-5)*$AE$20))*(1+$C$6),2)*(IF($G$6="YES",$E$6,0)+IF($K$6="YES",$I$6,0)),2) | D73: =ROUND((IF(1<=15,$AD$21,$AD$21+(1-15)*$AE$21))*(1+$C$6),2)+ROUND(ROUND((IF(1<=15,$AD$21,$AD$21+(1-15)*$AE$21))*(1+$C$6),2)*(IF($G$6="YES",$E$6,0)+IF($K$6="YES",$I$6,0)),2) | E73: =ROUND((IF(1<=2,$AD$22,IF(1<=5,$AE$22,IF(1<=10,$AF$22,IF(1<=15,$AG$22,IF(1<=20,$AH$22,IF(1<=35,$AH$22+(1-20)*$AI$22,$AK$22+(1-35)*$AJ$22)))))))*(1+$C$6),2)+ROUND(ROUND((IF(1<=2,$AD$22,IF(1<=5,$AE$22,IF(1<=10,$AF$22,IF(1<=15,$AG$22,IF(1<=20,$AH$22,IF(1<=35,$AH$22+(1-20)*$AI$22,$AK$22+(1-35)*$AJ$22)))))))*(1+$C$6),2)*(IF($G$6="YES",$E$6,0)+IF($K$6="YES",$I$6,0)),2) | F73: =ROUND((IF(1<=2,$AD$23,IF(1<=5,$AE$23,IF(1<=10,$AF$23,IF(1<=15,$AG$23,IF(1<=20,$AH$23,IF(1<=35,$AH$23+(1-20)*$AI$23,$AK$23+(1-35)*$AJ$23)))))))*(1+$C$6),2)+ROUND(ROUND((IF(1<=2,$AD$23,IF(1<=5,$AE$23,IF(1<=10,$AF$23,IF(1<=15,$AG$23,IF(1<=20,$AH$23,IF(1<=35,$AH$23+(1-20)*$AI$23,$AK$23+(1-35)*$AJ$23)))))))*(1+$C$6),2)*(IF($G$6="YES",$E$6,0)+IF($K$6="YES",$I$6,0)),2) | G73: =ROUND((IF(1<=2,$AD$24,IF(1<=5,$AE$24,IF(1<=10,$AF$24,IF(1<=15,$AG$24,IF(1<=20,$AH$24,IF(1<=35,$AH$24+(1-20)*$AI$24,$AK$24+(1-35)*$AJ$24)))))))*(1+$C$6),2)+ROUND(ROUND((IF(1<=2,$AD$24,IF(1<=5,$AE$24,IF(1<=10,$AF$24,IF(1<=15,$AG$24,IF(1<=20,$AH$24,IF(1<=35,$AH$24+(1-20)*$AI$24,$AK$24+(1-35)*$AJ$24)))))))*(1+$C$6),2)*(IF($G$6="YES",$E$6,0)+IF($K$6="YES",$I$6,0)),2) | H73: =ROUND((IF(1<=2,$AD$25,$AD$25+(1-2)*$AE$25))*(1+$C$6),2)+ROUND(ROUND((IF(1<=2,$AD$25,$AD$25+(1-2)*$AE$25))*(1+$C$6),2)*(IF($G$6="YES",$E$6,0)+IF($K$6="YES",$I$6,0)),2)+(1*$E$8*IF($C$8="YES",1,0)) | I73: =ROUND((IF(1<=2,$AD$26,$AD$26+(1-2)*$AE$26))*(1+$C$6),2)+ROUND(ROUND((IF(1<=2,$AD$26,$AD$26+(1-2)*$AE$26))*(1+$C$6),2)*(IF($G$6="YES",$E$6,0)+IF($K$6="YES",$I$6,0)),2)
B74: 2 | C74: =ROUND((IF(2<=5,$AD$20,$AD$20+(2-5)*$AE$20))*(1+$C$6),2)+ROUND(ROUND((IF(2<=5,$AD$20,$AD$20+(2-5)*$AE$20))*(1+$C$6),2)*(IF($G$6="YES",$E$6,0)+IF($K$6="YES",$I$6,0)),2) | D74: =ROUND((IF(2<=15,$AD$21,$AD$21+(2-15)*$AE$21))*(1+$C$6),2)+ROUND(ROUND((IF(2<=15,$AD$21,$AD$21+(2-15)*$AE$21))*(1+$C$6),2)*(IF($G$6="YES",$E$6,0)+IF($K$6="YES",$I$6,0)),2) | E74: =ROUND((IF(2<=2,$AD$22,IF(2<=5,$AE$22,IF(2<=10,$AF$22,IF(2<=15,$AG$22,IF(2<=20,$AH$22,IF(2<=35,$AH$22+(2-20)*$AI$22,$AK$22+(2-35)*$AJ$22)))))))*(1+$C$6),2)+ROUND(ROUND((IF(2<=2,$AD$22,IF(2<=5,$AE$22,IF(2<=10,$AF$22,IF(2<=15,$AG$22,IF(2<=20,$AH$22,IF(2<=35,$AH$22+(2-20)*$AI$22,$AK$22+(2-35)*$AJ$22)))))))*(1+$C$6),2)*(IF($G$6="YES",$E$6,0)+IF($K$6="YES",$I$6,0)),2) | F74: =ROUND((IF(2<=2,$AD$23,IF(2<=5,$AE$23,IF(2<=10,$AF$23,IF(2<=15,$AG$23,IF(2<=20,$AH$23,IF(2<=35,$AH$23+(2-20)*$AI$23,$AK$23+(2-35)*$AJ$23)))))))*(1+$C$6),2)+ROUND(ROUND((IF(2<=2,$AD$23,IF(2<=5,$AE$23,IF(2<=10,$AF$23,IF(2<=15,$AG$23,IF(2<=20,$AH$23,IF(2<=35,$AH$23+(2-20)*$AI$23,$AK$23+(2-35)*$AJ$23)))))))*(1+$C$6),2)*(IF($G$6="YES",$E$6,0)+IF($K$6="YES",$I$6,0)),2) | G74: =ROUND((IF(2<=2,$AD$24,IF(2<=5,$AE$24,IF(2<=10,$AF$24,IF(2<=15,$AG$24,IF(2<=20,$AH$24,IF(2<=35,$AH$24+(2-20)*$AI$24,$AK$24+(2-35)*$AJ$24)))))))*(1+$C$6),2)+ROUND(ROUND((IF(2<=2,$AD$24,IF(2<=5,$AE$24,IF(2<=10,$AF$24,IF(2<=15,$AG$24,IF(2<=20,$AH$24,IF(2<=35,$AH$24+(2-20)*$AI$24,$AK$24+(2-35)*$AJ$24)))))))*(1+$C$6),2)*(IF($G$6="YES",$E$6,0)+IF($K$6="YES",$I$6,0)),2) | H74: =ROUND((IF(2<=2,$AD$25,$AD$25+(2-2)*$AE$25))*(1+$C$6),2)+ROUND(ROUND((IF(2<=2,$AD$25,$AD$25+(2-2)*$AE$25))*(1+$C$6),2)*(IF($G$6="YES",$E$6,0)+IF($K$6="YES",$I$6,0)),2)+(2*$E$8*IF($C$8="YES",1,0)) | I74: =ROUND((IF(2<=2,$AD$26,$AD$26+(2-2)*$AE$26))*(1+$C$6),2)+ROUND(ROUND((IF(2<=2,$AD$26,$AD$26+(2-2)*$AE$26))*(1+$C$6),2)*(IF($G$6="YES",$E$6,0)+IF($K$6="YES",$I$6,0)),2)
B75: 3 | C75: =ROUND((IF(3<=5,$AD$20,$AD$20+(3-5)*$AE$20))*(1+$C$6),2)+ROUND(ROUND((IF(3<=5,$AD$20,$AD$20+(3-5)*$AE$20))*(1+$C$6),2)*(IF($G$6="YES",$E$6,0)+IF($K$6="YES",$I$6,0)),2) | D75: =ROUND((IF(3<=15,$AD$21,$AD$21+(3-15)*$AE$21))*(1+$C$6),2)+ROUND(ROUND((IF(3<=15,$AD$21,$AD$21+(3-15)*$AE$21))*(1+$C$6),2)*(IF($G$6="YES",$E$6,0)+IF($K$6="YES",$I$6,0)),2) | E75: =ROUND((IF(3<=2,$AD$22,IF(3<=5,$AE$22,IF(3<=10,$AF$22,IF(3<=15,$AG$22,IF(3<=20,$AH$22,IF(3<=35,$AH$22+(3-20)*$AI$22,$AK$22+(3-35)*$AJ$22)))))))*(1+$C$6),2)+ROUND(ROUND((IF(3<=2,$AD$22,IF(3<=5,$AE$22,IF(3<=10,$AF$22,IF(3<=15,$AG$22,IF(3<=20,$AH$22,IF(3<=35,$AH$22+(3-20)*$AI$22,$AK$22+(3-35)*$AJ$22)))))))*(1+$C$6),2)*(IF($G$6="YES",$E$6,0)+IF($K$6="YES",$I$6,0)),2) | F75: =ROUND((IF(3<=2,$AD$23,IF(3<=5,$AE$23,IF(3<=10,$AF$23,IF(3<=15,$AG$23,IF(3<=20,$AH$23,IF(3<=35,$AH$23+(3-20)*$AI$23,$AK$23+(3-35)*$AJ$23)))))))*(1+$C$6),2)+ROUND(ROUND((IF(3<=2,$AD$23,IF(3<=5,$AE$23,IF(3<=10,$AF$23,IF(3<=15,$AG$23,IF(3<=20,$AH$23,IF(3<=35,$AH$23+(3-20)*$AI$23,$AK$23+(3-35)*$AJ$23)))))))*(1+$C$6),2)*(IF($G$6="YES",$E$6,0)+IF($K$6="YES",$I$6,0)),2) | G75: =ROUND((IF(3<=2,$AD$24,IF(3<=5,$AE$24,IF(3<=10,$AF$24,IF(3<=15,$AG$24,IF(3<=20,$AH$24,IF(3<=35,$AH$24+(3-20)*$AI$24,$AK$24+(3-35)*$AJ$24)))))))*(1+$C$6),2)+ROUND(ROUND((IF(3<=2,$AD$24,IF(3<=5,$AE$24,IF(3<=10,$AF$24,IF(3<=15,$AG$24,IF(3<=20,$AH$24,IF(3<=35,$AH$24+(3-20)*$AI$24,$AK$24+(3-35)*$AJ$24)))))))*(1+$C$6),2)*(IF($G$6="YES",$E$6,0)+IF($K$6="YES",$I$6,0)),2) | H75: =ROUND((IF(3<=2,$AD$25,$AD$25+(3-2)*$AE$25))*(1+$C$6),2)+ROUND(ROUND((IF(3<=2,$AD$25,$AD$25+(3-2)*$AE$25))*(1+$C$6),2)*(IF($G$6="YES",$E$6,0)+IF($K$6="YES",$I$6,0)),2)+(3*$E$8*IF($C$8="YES",1,0)) | I75: =ROUND((IF(3<=2,$AD$26,$AD$26+(3-2)*$AE$26))*(1+$C$6),2)+ROUND(ROUND((IF(3<=2,$AD$26,$AD$26+(3-2)*$AE$26))*(1+$C$6),2)*(IF($G$6="YES",$E$6,0)+IF($K$6="YES",$I$6,0)),2)
B76: 4 | C76: =ROUND((IF(4<=5,$AD$20,$AD$20+(4-5)*$AE$20))*(1+$C$6),2)+ROUND(ROUND((IF(4<=5,$AD$20,$AD$20+(4-5)*$AE$20))*(1+$C$6),2)*(IF($G$6="YES",$E$6,0)+IF($K$6="YES",$I$6,0)),2) | D76: =ROUND((IF(4<=15,$AD$21,$AD$21+(4-15)*$AE$21))*(1+$C$6),2)+ROUND(ROUND((IF(4<=15,$AD$21,$AD$21+(4-15)*$AE$21))*(1+$C$6),2)*(IF($G$6="YES",$E$6,0)+IF($K$6="YES",$I$6,0)),2) | E76: =ROUND((IF(4<=2,$AD$22,IF(4<=5,$AE$22,IF(4<=10,$AF$22,IF(4<=15,$AG$22,IF(4<=20,$AH$22,IF(4<=35,$AH$22+(4-20)*$AI$22,$AK$22+(4-35)*$AJ$22)))))))*(1+$C$6),2)+ROUND(ROUND((IF(4<=2,$AD$22,IF(4<=5,$AE$22,IF(4<=10,$AF$22,IF(4<=15,$AG$22,IF(4<=20,$AH$22,IF(4<=35,$AH$22+(4-20)*$AI$22,$AK$22+(4-35)*$AJ$22)))))))*(1+$C$6),2)*(IF($G$6="YES",$E$6,0)+IF($K$6="YES",$I$6,0)),2) | F76: =ROUND((IF(4<=2,$AD$23,IF(4<=5,$AE$23,IF(4<=10,$AF$23,IF(4<=15,$AG$23,IF(4<=20,$AH$23,IF(4<=35,$AH$23+(4-20)*$AI$23,$AK$23+(4-35)*$AJ$23)))))))*(1+$C$6),2)+ROUND(ROUND((IF(4<=2,$AD$23,IF(4<=5,$AE$23,IF(4<=10,$AF$23,IF(4<=15,$AG$23,IF(4<=20,$AH$23,IF(4<=35,$AH$23+(4-20)*$AI$23,$AK$23+(4-35)*$AJ$23)))))))*(1+$C$6),2)*(IF($G$6="YES",$E$6,0)+IF($K$6="YES",$I$6,0)),2) | G76: =ROUND((IF(4<=2,$AD$24,IF(4<=5,$AE$24,IF(4<=10,$AF$24,IF(4<=15,$AG$24,IF(4<=20,$AH$24,IF(4<=35,$AH$24+(4-20)*$AI$24,$AK$24+(4-35)*$AJ$24)))))))*(1+$C$6),2)+ROUND(ROUND((IF(4<=2,$AD$24,IF(4<=5,$AE$24,IF(4<=10,$AF$24,IF(4<=15,$AG$24,IF(4<=20,$AH$24,IF(4<=35,$AH$24+(4-20)*$AI$24,$AK$24+(4-35)*$AJ$24)))))))*(1+$C$6),2)*(IF($G$6="YES",$E$6,0)+IF($K$6="YES",$I$6,0)),2) | H76: =ROUND((IF(4<=2,$AD$25,$AD$25+(4-2)*$AE$25))*(1+$C$6),2)+ROUND(ROUND((IF(4<=2,$AD$25,$AD$25+(4-2)*$AE$25))*(1+$C$6),2)*(IF($G$6="YES",$E$6,0)+IF($K$6="YES",$I$6,0)),2)+(4*$E$8*IF($C$8="YES",1,0)) | I76: =ROUND((IF(4<=2,$AD$26,$AD$26+(4-2)*$AE$26))*(1+$C$6),2)+ROUND(ROUND((IF(4<=2,$AD$26,$AD$26+(4-2)*$AE$26))*(1+$C$6),2)*(IF($G$6="YES",$E$6,0)+IF($K$6="YES",$I$6,0)),2)
B77: 5 | C77: =ROUND((IF(5<=5,$AD$20,$AD$20+(5-5)*$AE$20))*(1+$C$6),2)+ROUND(ROUND((IF(5<=5,$AD$20,$AD$20+(5-5)*$AE$20))*(1+$C$6),2)*(IF($G$6="YES",$E$6,0)+IF($K$6="YES",$I$6,0)),2) | D77: =ROUND((IF(5<=15,$AD$21,$AD$21+(5-15)*$AE$21))*(1+$C$6),2)+ROUND(ROUND((IF(5<=15,$AD$21,$AD$21+(5-15)*$AE$21))*(1+$C$6),2)*(IF($G$6="YES",$E$6,0)+IF($K$6="YES",$I$6,0)),2) | E77: =ROUND((IF(5<=2,$AD$22,IF(5<=5,$AE$22,IF(5<=10,$AF$22,IF(5<=15,$AG$22,IF(5<=20,$AH$22,IF(5<=35,$AH$22+(5-20)*$AI$22,$AK$22+(5-35)*$AJ$22)))))))*(1+$C$6),2)+ROUND(ROUND((IF(5<=2,$AD$22,IF(5<=5,$AE$22,IF(5<=10,$AF$22,IF(5<=15,$AG$22,IF(5<=20,$AH$22,IF(5<=35,$AH$22+(5-20)*$AI$22,$AK$22+(5-35)*$AJ$22)))))))*(1+$C$6),2)*(IF($G$6="YES",$E$6,0)+IF($K$6="YES",$I$6,0)),2) | F77: =ROUND((IF(5<=2,$AD$23,IF(5<=5,$AE$23,IF(5<=10,$AF$23,IF(5<=15,$AG$23,IF(5<=20,$AH$23,IF(5<=35,$AH$23+(5-20)*$AI$23,$AK$23+(5-35)*$AJ$23)))))))*(1+$C$6),2)+ROUND(ROUND((IF(5<=2,$AD$23,IF(5<=5,$AE$23,IF(5<=10,$AF$23,IF(5<=15,$AG$23,IF(5<=20,$AH$23,IF(5<=35,$AH$23+(5-20)*$AI$23,$AK$23+(5-35)*$AJ$23)))))))*(1+$C$6),2)*(IF($G$6="YES",$E$6,0)+IF($K$6="YES",$I$6,0)),2) | G77: =ROUND((IF(5<=2,$AD$24,IF(5<=5,$AE$24,IF(5<=10,$AF$24,IF(5<=15,$AG$24,IF(5<=20,$AH$24,IF(5<=35,$AH$24+(5-20)*$AI$24,$AK$24+(5-35)*$AJ$24)))))))*(1+$C$6),2)+ROUND(ROUND((IF(5<=2,$AD$24,IF(5<=5,$AE$24,IF(5<=10,$AF$24,IF(5<=15,$AG$24,IF(5<=20,$AH$24,IF(5<=35,$AH$24+(5-20)*$AI$24,$AK$24+(5-35)*$AJ$24)))))))*(1+$C$6),2)*(IF($G$6="YES",$E$6,0)+IF($K$6="YES",$I$6,0)),2) | H77: =ROUND((IF(5<=2,$AD$25,$AD$25+(5-2)*$AE$25))*(1+$C$6),2)+ROUND(ROUND((IF(5<=2,$AD$25,$AD$25+(5-2)*$AE$25))*(1+$C$6),2)*(IF($G$6="YES",$E$6,0)+IF($K$6="YES",$I$6,0)),2)+(5*$E$8*IF($C$8="YES",1,0)) | I77: =ROUND((IF(5<=2,$AD$26,$AD$26+(5-2)*$AE$26))*(1+$C$6),2)+ROUND(ROUND((IF(5<=2,$AD$26,$AD$26+(5-2)*$AE$26))*(1+$C$6),2)*(IF($G$6="YES",$E$6,0)+IF($K$6="YES",$I$6,0)),2)
B78: 6 | C78: =ROUND((IF(6<=5,$AD$20,$AD$20+(6-5)*$AE$20))*(1+$C$6),2)+ROUND(ROUND((IF(6<=5,$AD$20,$AD$20+(6-5)*$AE$20))*(1+$C$6),2)*(IF($G$6="YES",$E$6,0)+IF($K$6="YES",$I$6,0)),2) | D78: =ROUND((IF(6<=15,$AD$21,$AD$21+(6-15)*$AE$21))*(1+$C$6),2)+ROUND(ROUND((IF(6<=15,$AD$21,$AD$21+(6-15)*$AE$21))*(1+$C$6),2)*(IF($G$6="YES",$E$6,0)+IF($K$6="YES",$I$6,0)),2) | E78: =ROUND((IF(6<=2,$AD$22,IF(6<=5,$AE$22,IF(6<=10,$AF$22,IF(6<=15,$AG$22,IF(6<=20,$AH$22,IF(6<=35,$AH$22+(6-20)*$AI$22,$AK$22+(6-35)*$AJ$22)))))))*(1+$C$6),2)+ROUND(ROUND((IF(6<=2,$AD$22,IF(6<=5,$AE$22,IF(6<=10,$AF$22,IF(6<=15,$AG$22,IF(6<=20,$AH$22,IF(6<=35,$AH$22+(6-20)*$AI$22,$AK$22+(6-35)*$AJ$22)))))))*(1+$C$6),2)*(IF($G$6="YES",$E$6,0)+IF($K$6="YES",$I$6,0)),2) | F78: =ROUND((IF(6<=2,$AD$23,IF(6<=5,$AE$23,IF(6<=10,$AF$23,IF(6<=15,$AG$23,IF(6<=20,$AH$23,IF(6<=35,$AH$23+(6-20)*$AI$23,$AK$23+(6-35)*$AJ$23)))))))*(1+$C$6),2)+ROUND(ROUND((IF(6<=2,$AD$23,IF(6<=5,$AE$23,IF(6<=10,$AF$23,IF(6<=15,$AG$23,IF(6<=20,$AH$23,IF(6<=35,$AH$23+(6-20)*$AI$23,$AK$23+(6-35)*$AJ$23)))))))*(1+$C$6),2)*(IF($G$6="YES",$E$6,0)+IF($K$6="YES",$I$6,0)),2) | G78: =ROUND((IF(6<=2,$AD$24,IF(6<=5,$AE$24,IF(6<=10,$AF$24,IF(6<=15,$AG$24,IF(6<=20,$AH$24,IF(6<=35,$AH$24+(6-20)*$AI$24,$AK$24+(6-35)*$AJ$24)))))))*(1+$C$6),2)+ROUND(ROUND((IF(6<=2,$AD$24,IF(6<=5,$AE$24,IF(6<=10,$AF$24,IF(6<=15,$AG$24,IF(6<=20,$AH$24,IF(6<=35,$AH$24+(6-20)*$AI$24,$AK$24+(6-35)*$AJ$24)))))))*(1+$C$6),2)*(IF($G$6="YES",$E$6,0)+IF($K$6="YES",$I$6,0)),2) | H78: =ROUND((IF(6<=2,$AD$25,$AD$25+(6-2)*$AE$25))*(1+$C$6),2)+ROUND(ROUND((IF(6<=2,$AD$25,$AD$25+(6-2)*$AE$25))*(1+$C$6),2)*(IF($G$6="YES",$E$6,0)+IF($K$6="YES",$I$6,0)),2)+(6*$E$8*IF($C$8="YES",1,0)) | I78: =ROUND((IF(6<=2,$AD$26,$AD$26+(6-2)*$AE$26))*(1+$C$6),2)+ROUND(ROUND((IF(6<=2,$AD$26,$AD$26+(6-2)*$AE$26))*(1+$C$6),2)*(IF($G$6="YES",$E$6,0)+IF($K$6="YES",$I$6,0)),2)
B79: 7 | C79: =ROUND((IF(7<=5,$AD$20,$AD$20+(7-5)*$AE$20))*(1+$C$6),2)+ROUND(ROUND((IF(7<=5,$AD$20,$AD$20+(7-5)*$AE$20))*(1+$C$6),2)*(IF($G$6="YES",$E$6,0)+IF($K$6="YES",$I$6,0)),2) | D79: =ROUND((IF(7<=15,$AD$21,$AD$21+(7-15)*$AE$21))*(1+$C$6),2)+ROUND(ROUND((IF(7<=15,$AD$21,$AD$21+(7-15)*$AE$21))*(1+$C$6),2)*(IF($G$6="YES",$E$6,0)+IF($K$6="YES",$I$6,0)),2) | E79: =ROUND((IF(7<=2,$AD$22,IF(7<=5,$AE$22,IF(7<=10,$AF$22,IF(7<=15,$AG$22,IF(7<=20,$AH$22,IF(7<=35,$AH$22+(7-20)*$AI$22,$AK$22+(7-35)*$AJ$22)))))))*(1+$C$6),2)+ROUND(ROUND((IF(7<=2,$AD$22,IF(7<=5,$AE$22,IF(7<=10,$AF$22,IF(7<=15,$AG$22,IF(7<=20,$AH$22,IF(7<=35,$AH$22+(7-20)*$AI$22,$AK$22+(7-35)*$AJ$22)))))))*(1+$C$6),2)*(IF($G$6="YES",$E$6,0)+IF($K$6="YES",$I$6,0)),2) | F79: =ROUND((IF(7<=2,$AD$23,IF(7<=5,$AE$23,IF(7<=10,$AF$23,IF(7<=15,$AG$23,IF(7<=20,$AH$23,IF(7<=35,$AH$23+(7-20)*$AI$23,$AK$23+(7-35)*$AJ$23)))))))*(1+$C$6),2)+ROUND(ROUND((IF(7<=2,$AD$23,IF(7<=5,$AE$23,IF(7<=10,$AF$23,IF(7<=15,$AG$23,IF(7<=20,$AH$23,IF(7<=35,$AH$23+(7-20)*$AI$23,$AK$23+(7-35)*$AJ$23)))))))*(1+$C$6),2)*(IF($G$6="YES",$E$6,0)+IF($K$6="YES",$I$6,0)),2) | G79: =ROUND((IF(7<=2,$AD$24,IF(7<=5,$AE$24,IF(7<=10,$AF$24,IF(7<=15,$AG$24,IF(7<=20,$AH$24,IF(7<=35,$AH$24+(7-20)*$AI$24,$AK$24+(7-35)*$AJ$24)))))))*(1+$C$6),2)+ROUND(ROUND((IF(7<=2,$AD$24,IF(7<=5,$AE$24,IF(7<=10,$AF$24,IF(7<=15,$AG$24,IF(7<=20,$AH$24,IF(7<=35,$AH$24+(7-20)*$AI$24,$AK$24+(7-35)*$AJ$24)))))))*(1+$C$6),2)*(IF($G$6="YES",$E$6,0)+IF($K$6="YES",$I$6,0)),2) | H79: =ROUND((IF(7<=2,$AD$25,$AD$25+(7-2)*$AE$25))*(1+$C$6),2)+ROUND(ROUND((IF(7<=2,$AD$25,$AD$25+(7-2)*$AE$25))*(1+$C$6),2)*(IF($G$6="YES",$E$6,0)+IF($K$6="YES",$I$6,0)),2)+(7*$E$8*IF($C$8="YES",1,0)) | I79: =ROUND((IF(7<=2,$AD$26,$AD$26+(7-2)*$AE$26))*(1+$C$6),2)+ROUND(ROUND((IF(7<=2,$AD$26,$AD$26+(7-2)*$AE$26))*(1+$C$6),2)*(IF($G$6="YES",$E$6,0)+IF($K$6="YES",$I$6,0)),2)
B80: 8 | C80: =ROUND((IF(8<=5,$AD$20,$AD$20+(8-5)*$AE$20))*(1+$C$6),2)+ROUND(ROUND((IF(8<=5,$AD$20,$AD$20+(8-5)*$AE$20))*(1+$C$6),2)*(IF($G$6="YES",$E$6,0)+IF($K$6="YES",$I$6,0)),2) | D80: =ROUND((IF(8<=15,$AD$21,$AD$21+(8-15)*$AE$21))*(1+$C$6),2)+ROUND(ROUND((IF(8<=15,$AD$21,$AD$21+(8-15)*$AE$21))*(1+$C$6),2)*(IF($G$6="YES",$E$6,0)+IF($K$6="YES",$I$6,0)),2) | E80: =ROUND((IF(8<=2,$AD$22,IF(8<=5,$AE$22,IF(8<=10,$AF$22,IF(8<=15,$AG$22,IF(8<=20,$AH$22,IF(8<=35,$AH$22+(8-20)*$AI$22,$AK$22+(8-35)*$AJ$22)))))))*(1+$C$6),2)+ROUND(ROUND((IF(8<=2,$AD$22,IF(8<=5,$AE$22,IF(8<=10,$AF$22,IF(8<=15,$AG$22,IF(8<=20,$AH$22,IF(8<=35,$AH$22+(8-20)*$AI$22,$AK$22+(8-35)*$AJ$22)))))))*(1+$C$6),2)*(IF($G$6="YES",$E$6,0)+IF($K$6="YES",$I$6,0)),2) | F80: =ROUND((IF(8<=2,$AD$23,IF(8<=5,$AE$23,IF(8<=10,$AF$23,IF(8<=15,$AG$23,IF(8<=20,$AH$23,IF(8<=35,$AH$23+(8-20)*$AI$23,$AK$23+(8-35)*$AJ$23)))))))*(1+$C$6),2)+ROUND(ROUND((IF(8<=2,$AD$23,IF(8<=5,$AE$23,IF(8<=10,$AF$23,IF(8<=15,$AG$23,IF(8<=20,$AH$23,IF(8<=35,$AH$23+(8-20)*$AI$23,$AK$23+(8-35)*$AJ$23)))))))*(1+$C$6),2)*(IF($G$6="YES",$E$6,0)+IF($K$6="YES",$I$6,0)),2) | G80: =ROUND((IF(8<=2,$AD$24,IF(8<=5,$AE$24,IF(8<=10,$AF$24,IF(8<=15,$AG$24,IF(8<=20,$AH$24,IF(8<=35,$AH$24+(8-20)*$AI$24,$AK$24+(8-35)*$AJ$24)))))))*(1+$C$6),2)+ROUND(ROUND((IF(8<=2,$AD$24,IF(8<=5,$AE$24,IF(8<=10,$AF$24,IF(8<=15,$AG$24,IF(8<=20,$AH$24,IF(8<=35,$AH$24+(8-20)*$AI$24,$AK$24+(8-35)*$AJ$24)))))))*(1+$C$6),2)*(IF($G$6="YES",$E$6,0)+IF($K$6="YES",$I$6,0)),2) | H80: =ROUND((IF(8<=2,$AD$25,$AD$25+(8-2)*$AE$25))*(1+$C$6),2)+ROUND(ROUND((IF(8<=2,$AD$25,$AD$25+(8-2)*$AE$25))*(1+$C$6),2)*(IF($G$6="YES",$E$6,0)+IF($K$6="YES",$I$6,0)),2)+(8*$E$8*IF($C$8="YES",1,0)) | I80: =ROUND((IF(8<=2,$AD$26,$AD$26+(8-2)*$AE$26))*(1+$C$6),2)+ROUND(ROUND((IF(8<=2,$AD$26,$AD$26+(8-2)*$AE$26))*(1+$C$6),2)*(IF($G$6="YES",$E$6,0)+IF($K$6="YES",$I$6,0)),2)
B81: 9 | C81: =ROUND((IF(9<=5,$AD$20,$AD$20+(9-5)*$AE$20))*(1+$C$6),2)+ROUND(ROUND((IF(9<=5,$AD$20,$AD$20+(9-5)*$AE$20))*(1+$C$6),2)*(IF($G$6="YES",$E$6,0)+IF($K$6="YES",$I$6,0)),2) | D81: =ROUND((IF(9<=15,$AD$21,$AD$21+(9-15)*$AE$21))*(1+$C$6),2)+ROUND(ROUND((IF(9<=15,$AD$21,$AD$21+(9-15)*$AE$21))*(1+$C$6),2)*(IF($G$6="YES",$E$6,0)+IF($K$6="YES",$I$6,0)),2) | E81: =ROUND((IF(9<=2,$AD$22,IF(9<=5,$AE$22,IF(9<=10,$AF$22,IF(9<=15,$AG$22,IF(9<=20,$AH$22,IF(9<=35,$AH$22+(9-20)*$AI$22,$AK$22+(9-35)*$AJ$22)))))))*(1+$C$6),2)+ROUND(ROUND((IF(9<=2,$AD$22,IF(9<=5,$AE$22,IF(9<=10,$AF$22,IF(9<=15,$AG$22,IF(9<=20,$AH$22,IF(9<=35,$AH$22+(9-20)*$AI$22,$AK$22+(9-35)*$AJ$22)))))))*(1+$C$6),2)*(IF($G$6="YES",$E$6,0)+IF($K$6="YES",$I$6,0)),2) | F81: =ROUND((IF(9<=2,$AD$23,IF(9<=5,$AE$23,IF(9<=10,$AF$23,IF(9<=15,$AG$23,IF(9<=20,$AH$23,IF(9<=35,$AH$23+(9-20)*$AI$23,$AK$23+(9-35)*$AJ$23)))))))*(1+$C$6),2)+ROUND(ROUND((IF(9<=2,$AD$23,IF(9<=5,$AE$23,IF(9<=10,$AF$23,IF(9<=15,$AG$23,IF(9<=20,$AH$23,IF(9<=35,$AH$23+(9-20)*$AI$23,$AK$23+(9-35)*$AJ$23)))))))*(1+$C$6),2)*(IF($G$6="YES",$E$6,0)+IF($K$6="YES",$I$6,0)),2) | G81: =ROUND((IF(9<=2,$AD$24,IF(9<=5,$AE$24,IF(9<=10,$AF$24,IF(9<=15,$AG$24,IF(9<=20,$AH$24,IF(9<=35,$AH$24+(9-20)*$AI$24,$AK$24+(9-35)*$AJ$24)))))))*(1+$C$6),2)+ROUND(ROUND((IF(9<=2,$AD$24,IF(9<=5,$AE$24,IF(9<=10,$AF$24,IF(9<=15,$AG$24,IF(9<=20,$AH$24,IF(9<=35,$AH$24+(9-20)*$AI$24,$AK$24+(9-35)*$AJ$24)))))))*(1+$C$6),2)*(IF($G$6="YES",$E$6,0)+IF($K$6="YES",$I$6,0)),2) | H81: =ROUND((IF(9<=2,$AD$25,$AD$25+(9-2)*$AE$25))*(1+$C$6),2)+ROUND(ROUND((IF(9<=2,$AD$25,$AD$25+(9-2)*$AE$25))*(1+$C$6),2)*(IF($G$6="YES",$E$6,0)+IF($K$6="YES",$I$6,0)),2)+(9*$E$8*IF($C$8="YES",1,0)) | I81: =ROUND((IF(9<=2,$AD$26,$AD$26+(9-2)*$AE$26))*(1+$C$6),2)+ROUND(ROUND((IF(9<=2,$AD$26,$AD$26+(9-2)*$AE$26))*(1+$C$6),2)*(IF($G$6="YES",$E$6,0)+IF($K$6="YES",$I$6,0)),2)
B82: 10 | C82: =ROUND((IF(10<=5,$AD$20,$AD$20+(10-5)*$AE$20))*(1+$C$6),2)+ROUND(ROUND((IF(10<=5,$AD$20,$AD$20+(10-5)*$AE$20))*(1+$C$6),2)*(IF($G$6="YES",$E$6,0)+IF($K$6="YES",$I$6,0)),2) | D82: =ROUND((IF(10<=15,$AD$21,$AD$21+(10-15)*$AE$21))*(1+$C$6),2)+ROUND(ROUND((IF(10<=15,$AD$21,$AD$21+(10-15)*$AE$21))*(1+$C$6),2)*(IF($G$6="YES",$E$6,0)+IF($K$6="YES",$I$6,0)),2) | E82: =ROUND((IF(10<=2,$AD$22,IF(10<=5,$AE$22,IF(10<=10,$AF$22,IF(10<=15,$AG$22,IF(10<=20,$AH$22,IF(10<=35,$AH$22+(10-20)*$AI$22,$AK$22+(10-35)*$AJ$22)))))))*(1+$C$6),2)+ROUND(ROUND((IF(10<=2,$AD$22,IF(10<=5,$AE$22,IF(10<=10,$AF$22,IF(10<=15,$AG$22,IF(10<=20,$AH$22,IF(10<=35,$AH$22+(10-20)*$AI$22,$AK$22+(10-35)*$AJ$22)))))))*(1+$C$6),2)*(IF($G$6="YES",$E$6,0)+IF($K$6="YES",$I$6,0)),2) | F82: =ROUND((IF(10<=2,$AD$23,IF(10<=5,$AE$23,IF(10<=10,$AF$23,IF(10<=15,$AG$23,IF(10<=20,$AH$23,IF(10<=35,$AH$23+(10-20)*$AI$23,$AK$23+(10-35)*$AJ$23)))))))*(1+$C$6),2)+ROUND(ROUND((IF(10<=2,$AD$23,IF(10<=5,$AE$23,IF(10<=10,$AF$23,IF(10<=15,$AG$23,IF(10<=20,$AH$23,IF(10<=35,$AH$23+(10-20)*$AI$23,$AK$23+(10-35)*$AJ$23)))))))*(1+$C$6),2)*(IF($G$6="YES",$E$6,0)+IF($K$6="YES",$I$6,0)),2) | G82: =ROUND((IF(10<=2,$AD$24,IF(10<=5,$AE$24,IF(10<=10,$AF$24,IF(10<=15,$AG$24,IF(10<=20,$AH$24,IF(10<=35,$AH$24+(10-20)*$AI$24,$AK$24+(10-35)*$AJ$24)))))))*(1+$C$6),2)+ROUND(ROUND((IF(10<=2,$AD$24,IF(10<=5,$AE$24,IF(10<=10,$AF$24,IF(10<=15,$AG$24,IF(10<=20,$AH$24,IF(10<=35,$AH$24+(10-20)*$AI$24,$AK$24+(10-35)*$AJ$24)))))))*(1+$C$6),2)*(IF($G$6="YES",$E$6,0)+IF($K$6="YES",$I$6,0)),2) | H82: =ROUND((IF(10<=2,$AD$25,$AD$25+(10-2)*$AE$25))*(1+$C$6),2)+ROUND(ROUND((IF(10<=2,$AD$25,$AD$25+(10-2)*$AE$25))*(1+$C$6),2)*(IF($G$6="YES",$E$6,0)+IF($K$6="YES",$I$6,0)),2)+(10*$E$8*IF($C$8="YES",1,0)) | I82: =ROUND((IF(10<=2,$AD$26,$AD$26+(10-2)*$AE$26))*(1+$C$6),2)+ROUND(ROUND((IF(10<=2,$AD$26,$AD$26+(10-2)*$AE$26))*(1+$C$6),2)*(IF($G$6="YES",$E$6,0)+IF($K$6="YES",$I$6,0)),2)
B83: 11 | C83: =ROUND((IF(11<=5,$AD$20,$AD$20+(11-5)*$AE$20))*(1+$C$6),2)+ROUND(ROUND((IF(11<=5,$AD$20,$AD$20+(11-5)*$AE$20))*(1+$C$6),2)*(IF($G$6="YES",$E$6,0)+IF($K$6="YES",$I$6,0)),2) | D83: =ROUND((IF(11<=15,$AD$21,$AD$21+(11-15)*$AE$21))*(1+$C$6),2)+ROUND(ROUND((IF(11<=15,$AD$21,$AD$21+(11-15)*$AE$21))*(1+$C$6),2)*(IF($G$6="YES",$E$6,0)+IF($K$6="YES",$I$6,0)),2) | E83: =ROUND((IF(11<=2,$AD$22,IF(11<=5,$AE$22,IF(11<=10,$AF$22,IF(11<=15,$AG$22,IF(11<=20,$AH$22,IF(11<=35,$AH$22+(11-20)*$AI$22,$AK$22+(11-35)*$AJ$22)))))))*(1+$C$6),2)+ROUND(ROUND((IF(11<=2,$AD$22,IF(11<=5,$AE$22,IF(11<=10,$AF$22,IF(11<=15,$AG$22,IF(11<=20,$AH$22,IF(11<=35,$AH$22+(11-20)*$AI$22,$AK$22+(11-35)*$AJ$22)))))))*(1+$C$6),2)*(IF($G$6="YES",$E$6,0)+IF($K$6="YES",$I$6,0)),2) | F83: =ROUND((IF(11<=2,$AD$23,IF(11<=5,$AE$23,IF(11<=10,$AF$23,IF(11<=15,$AG$23,IF(11<=20,$AH$23,IF(11<=35,$AH$23+(11-20)*$AI$23,$AK$23+(11-35)*$AJ$23)))))))*(1+$C$6),2)+ROUND(ROUND((IF(11<=2,$AD$23,IF(11<=5,$AE$23,IF(11<=10,$AF$23,IF(11<=15,$AG$23,IF(11<=20,$AH$23,IF(11<=35,$AH$23+(11-20)*$AI$23,$AK$23+(11-35)*$AJ$23)))))))*(1+$C$6),2)*(IF($G$6="YES",$E$6,0)+IF($K$6="YES",$I$6,0)),2) | G83: =ROUND((IF(11<=2,$AD$24,IF(11<=5,$AE$24,IF(11<=10,$AF$24,IF(11<=15,$AG$24,IF(11<=20,$AH$24,IF(11<=35,$AH$24+(11-20)*$AI$24,$AK$24+(11-35)*$AJ$24)))))))*(1+$C$6),2)+ROUND(ROUND((IF(11<=2,$AD$24,IF(11<=5,$AE$24,IF(11<=10,$AF$24,IF(11<=15,$AG$24,IF(11<=20,$AH$24,IF(11<=35,$AH$24+(11-20)*$AI$24,$AK$24+(11-35)*$AJ$24)))))))*(1+$C$6),2)*(IF($G$6="YES",$E$6,0)+IF($K$6="YES",$I$6,0)),2) | H83: =ROUND((IF(11<=2,$AD$25,$AD$25+(11-2)*$AE$25))*(1+$C$6),2)+ROUND(ROUND((IF(11<=2,$AD$25,$AD$25+(11-2)*$AE$25))*(1+$C$6),2)*(IF($G$6="YES",$E$6,0)+IF($K$6="YES",$I$6,0)),2)+(11*$E$8*IF($C$8="YES",1,0)) | I83: =ROUND((IF(11<=2,$AD$26,$AD$26+(11-2)*$AE$26))*(1+$C$6),2)+ROUND(ROUND((IF(11<=2,$AD$26,$AD$26+(11-2)*$AE$26))*(1+$C$6),2)*(IF($G$6="YES",$E$6,0)+IF($K$6="YES",$I$6,0)),2)
B84: 12 | C84: =ROUND((IF(12<=5,$AD$20,$AD$20+(12-5)*$AE$20))*(1+$C$6),2)+ROUND(ROUND((IF(12<=5,$AD$20,$AD$20+(12-5)*$AE$20))*(1+$C$6),2)*(IF($G$6="YES",$E$6,0)+IF($K$6="YES",$I$6,0)),2) | D84: =ROUND((IF(12<=15,$AD$21,$AD$21+(12-15)*$AE$21))*(1+$C$6),2)+ROUND(ROUND((IF(12<=15,$AD$21,$AD$21+(12-15)*$AE$21))*(1+$C$6),2)*(IF($G$6="YES",$E$6,0)+IF($K$6="YES",$I$6,0)),2) | E84: =ROUND((IF(12<=2,$AD$22,IF(12<=5,$AE$22,IF(12<=10,$AF$22,IF(12<=15,$AG$22,IF(12<=20,$AH$22,IF(12<=35,$AH$22+(12-20)*$AI$22,$AK$22+(12-35)*$AJ$22)))))))*(1+$C$6),2)+ROUND(ROUND((IF(12<=2,$AD$22,IF(12<=5,$AE$22,IF(12<=10,$AF$22,IF(12<=15,$AG$22,IF(12<=20,$AH$22,IF(12<=35,$AH$22+(12-20)*$AI$22,$AK$22+(12-35)*$AJ$22)))))))*(1+$C$6),2)*(IF($G$6="YES",$E$6,0)+IF($K$6="YES",$I$6,0)),2) | F84: =ROUND((IF(12<=2,$AD$23,IF(12<=5,$AE$23,IF(12<=10,$AF$23,IF(12<=15,$AG$23,IF(12<=20,$AH$23,IF(12<=35,$AH$23+(12-20)*$AI$23,$AK$23+(12-35)*$AJ$23)))))))*(1+$C$6),2)+ROUND(ROUND((IF(12<=2,$AD$23,IF(12<=5,$AE$23,IF(12<=10,$AF$23,IF(12<=15,$AG$23,IF(12<=20,$AH$23,IF(12<=35,$AH$23+(12-20)*$AI$23,$AK$23+(12-35)*$AJ$23)))))))*(1+$C$6),2)*(IF($G$6="YES",$E$6,0)+IF($K$6="YES",$I$6,0)),2) | G84: =ROUND((IF(12<=2,$AD$24,IF(12<=5,$AE$24,IF(12<=10,$AF$24,IF(12<=15,$AG$24,IF(12<=20,$AH$24,IF(12<=35,$AH$24+(12-20)*$AI$24,$AK$24+(12-35)*$AJ$24)))))))*(1+$C$6),2)+ROUND(ROUND((IF(12<=2,$AD$24,IF(12<=5,$AE$24,IF(12<=10,$AF$24,IF(12<=15,$AG$24,IF(12<=20,$AH$24,IF(12<=35,$AH$24+(12-20)*$AI$24,$AK$24+(12-35)*$AJ$24)))))))*(1+$C$6),2)*(IF($G$6="YES",$E$6,0)+IF($K$6="YES",$I$6,0)),2) | H84: =ROUND((IF(12<=2,$AD$25,$AD$25+(12-2)*$AE$25))*(1+$C$6),2)+ROUND(ROUND((IF(12<=2,$AD$25,$AD$25+(12-2)*$AE$25))*(1+$C$6),2)*(IF($G$6="YES",$E$6,0)+IF($K$6="YES",$I$6,0)),2)+(12*$E$8*IF($C$8="YES",1,0)) | I84: =ROUND((IF(12<=2,$AD$26,$AD$26+(12-2)*$AE$26))*(1+$C$6),2)+ROUND(ROUND((IF(12<=2,$AD$26,$AD$26+(12-2)*$AE$26))*(1+$C$6),2)*(IF($G$6="YES",$E$6,0)+IF($K$6="YES",$I$6,0)),2)
B85: 13 | C85: =ROUND((IF(13<=5,$AD$20,$AD$20+(13-5)*$AE$20))*(1+$C$6),2)+ROUND(ROUND((IF(13<=5,$AD$20,$AD$20+(13-5)*$AE$20))*(1+$C$6),2)*(IF($G$6="YES",$E$6,0)+IF($K$6="YES",$I$6,0)),2) | D85: =ROUND((IF(13<=15,$AD$21,$AD$21+(13-15)*$AE$21))*(1+$C$6),2)+ROUND(ROUND((IF(13<=15,$AD$21,$AD$21+(13-15)*$AE$21))*(1+$C$6),2)*(IF($G$6="YES",$E$6,0)+IF($K$6="YES",$I$6,0)),2) | E85: =ROUND((IF(13<=2,$AD$22,IF(13<=5,$AE$22,IF(13<=10,$AF$22,IF(13<=15,$AG$22,IF(13<=20,$AH$22,IF(13<=35,$AH$22+(13-20)*$AI$22,$AK$22+(13-35)*$AJ$22)))))))*(1+$C$6),2)+ROUND(ROUND((IF(13<=2,$AD$22,IF(13<=5,$AE$22,IF(13<=10,$AF$22,IF(13<=15,$AG$22,IF(13<=20,$AH$22,IF(13<=35,$AH$22+(13-20)*$AI$22,$AK$22+(13-35)*$AJ$22)))))))*(1+$C$6),2)*(IF($G$6="YES",$E$6,0)+IF($K$6="YES",$I$6,0)),2) | F85: =ROUND((IF(13<=2,$AD$23,IF(13<=5,$AE$23,IF(13<=10,$AF$23,IF(13<=15,$AG$23,IF(13<=20,$AH$23,IF(13<=35,$AH$23+(13-20)*$AI$23,$AK$23+(13-35)*$AJ$23)))))))*(1+$C$6),2)+ROUND(ROUND((IF(13<=2,$AD$23,IF(13<=5,$AE$23,IF(13<=10,$AF$23,IF(13<=15,$AG$23,IF(13<=20,$AH$23,IF(13<=35,$AH$23+(13-20)*$AI$23,$AK$23+(13-35)*$AJ$23)))))))*(1+$C$6),2)*(IF($G$6="YES",$E$6,0)+IF($K$6="YES",$I$6,0)),2) | G85: =ROUND((IF(13<=2,$AD$24,IF(13<=5,$AE$24,IF(13<=10,$AF$24,IF(13<=15,$AG$24,IF(13<=20,$AH$24,IF(13<=35,$AH$24+(13-20)*$AI$24,$AK$24+(13-35)*$AJ$24)))))))*(1+$C$6),2)+ROUND(ROUND((IF(13<=2,$AD$24,IF(13<=5,$AE$24,IF(13<=10,$AF$24,IF(13<=15,$AG$24,IF(13<=20,$AH$24,IF(13<=35,$AH$24+(13-20)*$AI$24,$AK$24+(13-35)*$AJ$24)))))))*(1+$C$6),2)*(IF($G$6="YES",$E$6,0)+IF($K$6="YES",$I$6,0)),2) | H85: =ROUND((IF(13<=2,$AD$25,$AD$25+(13-2)*$AE$25))*(1+$C$6),2)+ROUND(ROUND((IF(13<=2,$AD$25,$AD$25+(13-2)*$AE$25))*(1+$C$6),2)*(IF($G$6="YES",$E$6,0)+IF($K$6="YES",$I$6,0)),2)+(13*$E$8*IF($C$8="YES",1,0)) | I85: =ROUND((IF(13<=2,$AD$26,$AD$26+(13-2)*$AE$26))*(1+$C$6),2)+ROUND(ROUND((IF(13<=2,$AD$26,$AD$26+(13-2)*$AE$26))*(1+$C$6),2)*(IF($G$6="YES",$E$6,0)+IF($K$6="YES",$I$6,0)),2)
B86: 14 | C86: =ROUND((IF(14<=5,$AD$20,$AD$20+(14-5)*$AE$20))*(1+$C$6),2)+ROUND(ROUND((IF(14<=5,$AD$20,$AD$20+(14-5)*$AE$20))*(1+$C$6),2)*(IF($G$6="YES",$E$6,0)+IF($K$6="YES",$I$6,0)),2) | D86: =ROUND((IF(14<=15,$AD$21,$AD$21+(14-15)*$AE$21))*(1+$C$6),2)+ROUND(ROUND((IF(14<=15,$AD$21,$AD$21+(14-15)*$AE$21))*(1+$C$6),2)*(IF($G$6="YES",$E$6,0)+IF($K$6="YES",$I$6,0)),2) | E86: =ROUND((IF(14<=2,$AD$22,IF(14<=5,$AE$22,IF(14<=10,$AF$22,IF(14<=15,$AG$22,IF(14<=20,$AH$22,IF(14<=35,$AH$22+(14-20)*$AI$22,$AK$22+(14-35)*$AJ$22)))))))*(1+$C$6),2)+ROUND(ROUND((IF(14<=2,$AD$22,IF(14<=5,$AE$22,IF(14<=10,$AF$22,IF(14<=15,$AG$22,IF(14<=20,$AH$22,IF(14<=35,$AH$22+(14-20)*$AI$22,$AK$22+(14-35)*$AJ$22)))))))*(1+$C$6),2)*(IF($G$6="YES",$E$6,0)+IF($K$6="YES",$I$6,0)),2) | F86: =ROUND((IF(14<=2,$AD$23,IF(14<=5,$AE$23,IF(14<=10,$AF$23,IF(14<=15,$AG$23,IF(14<=20,$AH$23,IF(14<=35,$AH$23+(14-20)*$AI$23,$AK$23+(14-35)*$AJ$23)))))))*(1+$C$6),2)+ROUND(ROUND((IF(14<=2,$AD$23,IF(14<=5,$AE$23,IF(14<=10,$AF$23,IF(14<=15,$AG$23,IF(14<=20,$AH$23,IF(14<=35,$AH$23+(14-20)*$AI$23,$AK$23+(14-35)*$AJ$23)))))))*(1+$C$6),2)*(IF($G$6="YES",$E$6,0)+IF($K$6="YES",$I$6,0)),2) | G86: =ROUND((IF(14<=2,$AD$24,IF(14<=5,$AE$24,IF(14<=10,$AF$24,IF(14<=15,$AG$24,IF(14<=20,$AH$24,IF(14<=35,$AH$24+(14-20)*$AI$24,$AK$24+(14-35)*$AJ$24)))))))*(1+$C$6),2)+ROUND(ROUND((IF(14<=2,$AD$24,IF(14<=5,$AE$24,IF(14<=10,$AF$24,IF(14<=15,$AG$24,IF(14<=20,$AH$24,IF(14<=35,$AH$24+(14-20)*$AI$24,$AK$24+(14-35)*$AJ$24)))))))*(1+$C$6),2)*(IF($G$6="YES",$E$6,0)+IF($K$6="YES",$I$6,0)),2) | H86: =ROUND((IF(14<=2,$AD$25,$AD$25+(14-2)*$AE$25))*(1+$C$6),2)+ROUND(ROUND((IF(14<=2,$AD$25,$AD$25+(14-2)*$AE$25))*(1+$C$6),2)*(IF($G$6="YES",$E$6,0)+IF($K$6="YES",$I$6,0)),2)+(14*$E$8*IF($C$8="YES",1,0)) | I86: =ROUND((IF(14<=2,$AD$26,$AD$26+(14-2)*$AE$26))*(1+$C$6),2)+ROUND(ROUND((IF(14<=2,$AD$26,$AD$26+(14-2)*$AE$26))*(1+$C$6),2)*(IF($G$6="YES",$E$6,0)+IF($K$6="YES",$I$6,0)),2)
B87: 15 | C87: =ROUND((IF(15<=5,$AD$20,$AD$20+(15-5)*$AE$20))*(1+$C$6),2)+ROUND(ROUND((IF(15<=5,$AD$20,$AD$20+(15-5)*$AE$20))*(1+$C$6),2)*(IF($G$6="YES",$E$6,0)+IF($K$6="YES",$I$6,0)),2) | D87: =ROUND((IF(15<=15,$AD$21,$AD$21+(15-15)*$AE$21))*(1+$C$6),2)+ROUND(ROUND((IF(15<=15,$AD$21,$AD$21+(15-15)*$AE$21))*(1+$C$6),2)*(IF($G$6="YES",$E$6,0)+IF($K$6="YES",$I$6,0)),2) | E87: =ROUND((IF(15<=2,$AD$22,IF(15<=5,$AE$22,IF(15<=10,$AF$22,IF(15<=15,$AG$22,IF(15<=20,$AH$22,IF(15<=35,$AH$22+(15-20)*$AI$22,$AK$22+(15-35)*$AJ$22)))))))*(1+$C$6),2)+ROUND(ROUND((IF(15<=2,$AD$22,IF(15<=5,$AE$22,IF(15<=10,$AF$22,IF(15<=15,$AG$22,IF(15<=20,$AH$22,IF(15<=35,$AH$22+(15-20)*$AI$22,$AK$22+(15-35)*$AJ$22)))))))*(1+$C$6),2)*(IF($G$6="YES",$E$6,0)+IF($K$6="YES",$I$6,0)),2) | F87: =ROUND((IF(15<=2,$AD$23,IF(15<=5,$AE$23,IF(15<=10,$AF$23,IF(15<=15,$AG$23,IF(15<=20,$AH$23,IF(15<=35,$AH$23+(15-20)*$AI$23,$AK$23+(15-35)*$AJ$23)))))))*(1+$C$6),2)+ROUND(ROUND((IF(15<=2,$AD$23,IF(15<=5,$AE$23,IF(15<=10,$AF$23,IF(15<=15,$AG$23,IF(15<=20,$AH$23,IF(15<=35,$AH$23+(15-20)*$AI$23,$AK$23+(15-35)*$AJ$23)))))))*(1+$C$6),2)*(IF($G$6="YES",$E$6,0)+IF($K$6="YES",$I$6,0)),2) | G87: =ROUND((IF(15<=2,$AD$24,IF(15<=5,$AE$24,IF(15<=10,$AF$24,IF(15<=15,$AG$24,IF(15<=20,$AH$24,IF(15<=35,$AH$24+(15-20)*$AI$24,$AK$24+(15-35)*$AJ$24)))))))*(1+$C$6),2)+ROUND(ROUND((IF(15<=2,$AD$24,IF(15<=5,$AE$24,IF(15<=10,$AF$24,IF(15<=15,$AG$24,IF(15<=20,$AH$24,IF(15<=35,$AH$24+(15-20)*$AI$24,$AK$24+(15-35)*$AJ$24)))))))*(1+$C$6),2)*(IF($G$6="YES",$E$6,0)+IF($K$6="YES",$I$6,0)),2) | H87: =ROUND((IF(15<=2,$AD$25,$AD$25+(15-2)*$AE$25))*(1+$C$6),2)+ROUND(ROUND((IF(15<=2,$AD$25,$AD$25+(15-2)*$AE$25))*(1+$C$6),2)*(IF($G$6="YES",$E$6,0)+IF($K$6="YES",$I$6,0)),2)+(15*$E$8*IF($C$8="YES",1,0)) | I87: =ROUND((IF(15<=2,$AD$26,$AD$26+(15-2)*$AE$26))*(1+$C$6),2)+ROUND(ROUND((IF(15<=2,$AD$26,$AD$26+(15-2)*$AE$26))*(1+$C$6),2)*(IF($G$6="YES",$E$6,0)+IF($K$6="YES",$I$6,0)),2)
B88: 16 | C88: =ROUND((IF(16<=5,$AD$20,$AD$20+(16-5)*$AE$20))*(1+$C$6),2)+ROUND(ROUND((IF(16<=5,$AD$20,$AD$20+(16-5)*$AE$20))*(1+$C$6),2)*(IF($G$6="YES",$E$6,0)+IF($K$6="YES",$I$6,0)),2) | D88: =ROUND((IF(16<=15,$AD$21,$AD$21+(16-15)*$AE$21))*(1+$C$6),2)+ROUND(ROUND((IF(16<=15,$AD$21,$AD$21+(16-15)*$AE$21))*(1+$C$6),2)*(IF($G$6="YES",$E$6,0)+IF($K$6="YES",$I$6,0)),2) | E88: =ROUND((IF(16<=2,$AD$22,IF(16<=5,$AE$22,IF(16<=10,$AF$22,IF(16<=15,$AG$22,IF(16<=20,$AH$22,IF(16<=35,$AH$22+(16-20)*$AI$22,$AK$22+(16-35)*$AJ$22)))))))*(1+$C$6),2)+ROUND(ROUND((IF(16<=2,$AD$22,IF(16<=5,$AE$22,IF(16<=10,$AF$22,IF(16<=15,$AG$22,IF(16<=20,$AH$22,IF(16<=35,$AH$22+(16-20)*$AI$22,$AK$22+(16-35)*$AJ$22)))))))*(1+$C$6),2)*(IF($G$6="YES",$E$6,0)+IF($K$6="YES",$I$6,0)),2) | F88: =ROUND((IF(16<=2,$AD$23,IF(16<=5,$AE$23,IF(16<=10,$AF$23,IF(16<=15,$AG$23,IF(16<=20,$AH$23,IF(16<=35,$AH$23+(16-20)*$AI$23,$AK$23+(16-35)*$AJ$23)))))))*(1+$C$6),2)+ROUND(ROUND((IF(16<=2,$AD$23,IF(16<=5,$AE$23,IF(16<=10,$AF$23,IF(16<=15,$AG$23,IF(16<=20,$AH$23,IF(16<=35,$AH$23+(16-20)*$AI$23,$AK$23+(16-35)*$AJ$23)))))))*(1+$C$6),2)*(IF($G$6="YES",$E$6,0)+IF($K$6="YES",$I$6,0)),2) | G88: =ROUND((IF(16<=2,$AD$24,IF(16<=5,$AE$24,IF(16<=10,$AF$24,IF(16<=15,$AG$24,IF(16<=20,$AH$24,IF(16<=35,$AH$24+(16-20)*$AI$24,$AK$24+(16-35)*$AJ$24)))))))*(1+$C$6),2)+ROUND(ROUND((IF(16<=2,$AD$24,IF(16<=5,$AE$24,IF(16<=10,$AF$24,IF(16<=15,$AG$24,IF(16<=20,$AH$24,IF(16<=35,$AH$24+(16-20)*$AI$24,$AK$24+(16-35)*$AJ$24)))))))*(1+$C$6),2)*(IF($G$6="YES",$E$6,0)+IF($K$6="YES",$I$6,0)),2) | H88: =ROUND((IF(16<=2,$AD$25,$AD$25+(16-2)*$AE$25))*(1+$C$6),2)+ROUND(ROUND((IF(16<=2,$AD$25,$AD$25+(16-2)*$AE$25))*(1+$C$6),2)*(IF($G$6="YES",$E$6,0)+IF($K$6="YES",$I$6,0)),2)+(16*$E$8*IF($C$8="YES",1,0)) | I88: =ROUND((IF(16<=2,$AD$26,$AD$26+(16-2)*$AE$26))*(1+$C$6),2)+ROUND(ROUND((IF(16<=2,$AD$26,$AD$26+(16-2)*$AE$26))*(1+$C$6),2)*(IF($G$6="YES",$E$6,0)+IF($K$6="YES",$I$6,0)),2)
B89: 17 | C89: =ROUND((IF(17<=5,$AD$20,$AD$20+(17-5)*$AE$20))*(1+$C$6),2)+ROUND(ROUND((IF(17<=5,$AD$20,$AD$20+(17-5)*$AE$20))*(1+$C$6),2)*(IF($G$6="YES",$E$6,0)+IF($K$6="YES",$I$6,0)),2) | D89: =ROUND((IF(17<=15,$AD$21,$AD$21+(17-15)*$AE$21))*(1+$C$6),2)+ROUND(ROUND((IF(17<=15,$AD$21,$AD$21+(17-15)*$AE$21))*(1+$C$6),2)*(IF($G$6="YES",$E$6,0)+IF($K$6="YES",$I$6,0)),2) | E89: =ROUND((IF(17<=2,$AD$22,IF(17<=5,$AE$22,IF(17<=10,$AF$22,IF(17<=15,$AG$22,IF(17<=20,$AH$22,IF(17<=35,$AH$22+(17-20)*$AI$22,$AK$22+(17-35)*$AJ$22)))))))*(1+$C$6),2)+ROUND(ROUND((IF(17<=2,$AD$22,IF(17<=5,$AE$22,IF(17<=10,$AF$22,IF(17<=15,$AG$22,IF(17<=20,$AH$22,IF(17<=35,$AH$22+(17-20)*$AI$22,$AK$22+(17-35)*$AJ$22)))))))*(1+$C$6),2)*(IF($G$6="YES",$E$6,0)+IF($K$6="YES",$I$6,0)),2) | F89: =ROUND((IF(17<=2,$AD$23,IF(17<=5,$AE$23,IF(17<=10,$AF$23,IF(17<=15,$AG$23,IF(17<=20,$AH$23,IF(17<=35,$AH$23+(17-20)*$AI$23,$AK$23+(17-35)*$AJ$23)))))))*(1+$C$6),2)+ROUND(ROUND((IF(17<=2,$AD$23,IF(17<=5,$AE$23,IF(17<=10,$AF$23,IF(17<=15,$AG$23,IF(17<=20,$AH$23,IF(17<=35,$AH$23+(17-20)*$AI$23,$AK$23+(17-35)*$AJ$23)))))))*(1+$C$6),2)*(IF($G$6="YES",$E$6,0)+IF($K$6="YES",$I$6,0)),2) | G89: =ROUND((IF(17<=2,$AD$24,IF(17<=5,$AE$24,IF(17<=10,$AF$24,IF(17<=15,$AG$24,IF(17<=20,$AH$24,IF(17<=35,$AH$24+(17-20)*$AI$24,$AK$24+(17-35)*$AJ$24)))))))*(1+$C$6),2)+ROUND(ROUND((IF(17<=2,$AD$24,IF(17<=5,$AE$24,IF(17<=10,$AF$24,IF(17<=15,$AG$24,IF(17<=20,$AH$24,IF(17<=35,$AH$24+(17-20)*$AI$24,$AK$24+(17-35)*$AJ$24)))))))*(1+$C$6),2)*(IF($G$6="YES",$E$6,0)+IF($K$6="YES",$I$6,0)),2) | H89: =ROUND((IF(17<=2,$AD$25,$AD$25+(17-2)*$AE$25))*(1+$C$6),2)+ROUND(ROUND((IF(17<=2,$AD$25,$AD$25+(17-2)*$AE$25))*(1+$C$6),2)*(IF($G$6="YES",$E$6,0)+IF($K$6="YES",$I$6,0)),2)+(17*$E$8*IF($C$8="YES",1,0)) | I89: =ROUND((IF(17<=2,$AD$26,$AD$26+(17-2)*$AE$26))*(1+$C$6),2)+ROUND(ROUND((IF(17<=2,$AD$26,$AD$26+(17-2)*$AE$26))*(1+$C$6),2)*(IF($G$6="YES",$E$6,0)+IF($K$6="YES",$I$6,0)),2)
B90: 18 | C90: =ROUND((IF(18<=5,$AD$20,$AD$20+(18-5)*$AE$20))*(1+$C$6),2)+ROUND(ROUND((IF(18<=5,$AD$20,$AD$20+(18-5)*$AE$20))*(1+$C$6),2)*(IF($G$6="YES",$E$6,0)+IF($K$6="YES",$I$6,0)),2) | D90: =ROUND((IF(18<=15,$AD$21,$AD$21+(18-15)*$AE$21))*(1+$C$6),2)+ROUND(ROUND((IF(18<=15,$AD$21,$AD$21+(18-15)*$AE$21))*(1+$C$6),2)*(IF($G$6="YES",$E$6,0)+IF($K$6="YES",$I$6,0)),2) | E90: =ROUND((IF(18<=2,$AD$22,IF(18<=5,$AE$22,IF(18<=10,$AF$22,IF(18<=15,$AG$22,IF(18<=20,$AH$22,IF(18<=35,$AH$22+(18-20)*$AI$22,$AK$22+(18-35)*$AJ$22)))))))*(1+$C$6),2)+ROUND(ROUND((IF(18<=2,$AD$22,IF(18<=5,$AE$22,IF(18<=10,$AF$22,IF(18<=15,$AG$22,IF(18<=20,$AH$22,IF(18<=35,$AH$22+(18-20)*$AI$22,$AK$22+(18-35)*$AJ$22)))))))*(1+$C$6),2)*(IF($G$6="YES",$E$6,0)+IF($K$6="YES",$I$6,0)),2) | F90: =ROUND((IF(18<=2,$AD$23,IF(18<=5,$AE$23,IF(18<=10,$AF$23,IF(18<=15,$AG$23,IF(18<=20,$AH$23,IF(18<=35,$AH$23+(18-20)*$AI$23,$AK$23+(18-35)*$AJ$23)))))))*(1+$C$6),2)+ROUND(ROUND((IF(18<=2,$AD$23,IF(18<=5,$AE$23,IF(18<=10,$AF$23,IF(18<=15,$AG$23,IF(18<=20,$AH$23,IF(18<=35,$AH$23+(18-20)*$AI$23,$AK$23+(18-35)*$AJ$23)))))))*(1+$C$6),2)*(IF($G$6="YES",$E$6,0)+IF($K$6="YES",$I$6,0)),2) | G90: =ROUND((IF(18<=2,$AD$24,IF(18<=5,$AE$24,IF(18<=10,$AF$24,IF(18<=15,$AG$24,IF(18<=20,$AH$24,IF(18<=35,$AH$24+(18-20)*$AI$24,$AK$24+(18-35)*$AJ$24)))))))*(1+$C$6),2)+ROUND(ROUND((IF(18<=2,$AD$24,IF(18<=5,$AE$24,IF(18<=10,$AF$24,IF(18<=15,$AG$24,IF(18<=20,$AH$24,IF(18<=35,$AH$24+(18-20)*$AI$24,$AK$24+(18-35)*$AJ$24)))))))*(1+$C$6),2)*(IF($G$6="YES",$E$6,0)+IF($K$6="YES",$I$6,0)),2) | H90: =ROUND((IF(18<=2,$AD$25,$AD$25+(18-2)*$AE$25))*(1+$C$6),2)+ROUND(ROUND((IF(18<=2,$AD$25,$AD$25+(18-2)*$AE$25))*(1+$C$6),2)*(IF($G$6="YES",$E$6,0)+IF($K$6="YES",$I$6,0)),2)+(18*$E$8*IF($C$8="YES",1,0)) | I90: =ROUND((IF(18<=2,$AD$26,$AD$26+(18-2)*$AE$26))*(1+$C$6),2)+ROUND(ROUND((IF(18<=2,$AD$26,$AD$26+(18-2)*$AE$26))*(1+$C$6),2)*(IF($G$6="YES",$E$6,0)+IF($K$6="YES",$I$6,0)),2)
B91: 19 | C91: =ROUND((IF(19<=5,$AD$20,$AD$20+(19-5)*$AE$20))*(1+$C$6),2)+ROUND(ROUND((IF(19<=5,$AD$20,$AD$20+(19-5)*$AE$20))*(1+$C$6),2)*(IF($G$6="YES",$E$6,0)+IF($K$6="YES",$I$6,0)),2) | D91: =ROUND((IF(19<=15,$AD$21,$AD$21+(19-15)*$AE$21))*(1+$C$6),2)+ROUND(ROUND((IF(19<=15,$AD$21,$AD$21+(19-15)*$AE$21))*(1+$C$6),2)*(IF($G$6="YES",$E$6,0)+IF($K$6="YES",$I$6,0)),2) | E91: =ROUND((IF(19<=2,$AD$22,IF(19<=5,$AE$22,IF(19<=10,$AF$22,IF(19<=15,$AG$22,IF(19<=20,$AH$22,IF(19<=35,$AH$22+(19-20)*$AI$22,$AK$22+(19-35)*$AJ$22)))))))*(1+$C$6),2)+ROUND(ROUND((IF(19<=2,$AD$22,IF(19<=5,$AE$22,IF(19<=10,$AF$22,IF(19<=15,$AG$22,IF(19<=20,$AH$22,IF(19<=35,$AH$22+(19-20)*$AI$22,$AK$22+(19-35)*$AJ$22)))))))*(1+$C$6),2)*(IF($G$6="YES",$E$6,0)+IF($K$6="YES",$I$6,0)),2) | F91: =ROUND((IF(19<=2,$AD$23,IF(19<=5,$AE$23,IF(19<=10,$AF$23,IF(19<=15,$AG$23,IF(19<=20,$AH$23,IF(19<=35,$AH$23+(19-20)*$AI$23,$AK$23+(19-35)*$AJ$23)))))))*(1+$C$6),2)+ROUND(ROUND((IF(19<=2,$AD$23,IF(19<=5,$AE$23,IF(19<=10,$AF$23,IF(19<=15,$AG$23,IF(19<=20,$AH$23,IF(19<=35,$AH$23+(19-20)*$AI$23,$AK$23+(19-35)*$AJ$23)))))))*(1+$C$6),2)*(IF($G$6="YES",$E$6,0)+IF($K$6="YES",$I$6,0)),2) | G91: =ROUND((IF(19<=2,$AD$24,IF(19<=5,$AE$24,IF(19<=10,$AF$24,IF(19<=15,$AG$24,IF(19<=20,$AH$24,IF(19<=35,$AH$24+(19-20)*$AI$24,$AK$24+(19-35)*$AJ$24)))))))*(1+$C$6),2)+ROUND(ROUND((IF(19<=2,$AD$24,IF(19<=5,$AE$24,IF(19<=10,$AF$24,IF(19<=15,$AG$24,IF(19<=20,$AH$24,IF(19<=35,$AH$24+(19-20)*$AI$24,$AK$24+(19-35)*$AJ$24)))))))*(1+$C$6),2)*(IF($G$6="YES",$E$6,0)+IF($K$6="YES",$I$6,0)),2) | H91: =ROUND((IF(19<=2,$AD$25,$AD$25+(19-2)*$AE$25))*(1+$C$6),2)+ROUND(ROUND((IF(19<=2,$AD$25,$AD$25+(19-2)*$AE$25))*(1+$C$6),2)*(IF($G$6="YES",$E$6,0)+IF($K$6="YES",$I$6,0)),2)+(19*$E$8*IF($C$8="YES",1,0)) | I91: =ROUND((IF(19<=2,$AD$26,$AD$26+(19-2)*$AE$26))*(1+$C$6),2)+ROUND(ROUND((IF(19<=2,$AD$26,$AD$26+(19-2)*$AE$26))*(1+$C$6),2)*(IF($G$6="YES",$E$6,0)+IF($K$6="YES",$I$6,0)),2)
B92: 20 | C92: =ROUND((IF(20<=5,$AD$20,$AD$20+(20-5)*$AE$20))*(1+$C$6),2)+ROUND(ROUND((IF(20<=5,$AD$20,$AD$20+(20-5)*$AE$20))*(1+$C$6),2)*(IF($G$6="YES",$E$6,0)+IF($K$6="YES",$I$6,0)),2) | D92: =ROUND((IF(20<=15,$AD$21,$AD$21+(20-15)*$AE$21))*(1+$C$6),2)+ROUND(ROUND((IF(20<=15,$AD$21,$AD$21+(20-15)*$AE$21))*(1+$C$6),2)*(IF($G$6="YES",$E$6,0)+IF($K$6="YES",$I$6,0)),2) | E92: =ROUND((IF(20<=2,$AD$22,IF(20<=5,$AE$22,IF(20<=10,$AF$22,IF(20<=15,$AG$22,IF(20<=20,$AH$22,IF(20<=35,$AH$22+(20-20)*$AI$22,$AK$22+(20-35)*$AJ$22)))))))*(1+$C$6),2)+ROUND(ROUND((IF(20<=2,$AD$22,IF(20<=5,$AE$22,IF(20<=10,$AF$22,IF(20<=15,$AG$22,IF(20<=20,$AH$22,IF(20<=35,$AH$22+(20-20)*$AI$22,$AK$22+(20-35)*$AJ$22)))))))*(1+$C$6),2)*(IF($G$6="YES",$E$6,0)+IF($K$6="YES",$I$6,0)),2) | F92: =ROUND((IF(20<=2,$AD$23,IF(20<=5,$AE$23,IF(20<=10,$AF$23,IF(20<=15,$AG$23,IF(20<=20,$AH$23,IF(20<=35,$AH$23+(20-20)*$AI$23,$AK$23+(20-35)*$AJ$23)))))))*(1+$C$6),2)+ROUND(ROUND((IF(20<=2,$AD$23,IF(20<=5,$AE$23,IF(20<=10,$AF$23,IF(20<=15,$AG$23,IF(20<=20,$AH$23,IF(20<=35,$AH$23+(20-20)*$AI$23,$AK$23+(20-35)*$AJ$23)))))))*(1+$C$6),2)*(IF($G$6="YES",$E$6,0)+IF($K$6="YES",$I$6,0)),2) | G92: =ROUND((IF(20<=2,$AD$24,IF(20<=5,$AE$24,IF(20<=10,$AF$24,IF(20<=15,$AG$24,IF(20<=20,$AH$24,IF(20<=35,$AH$24+(20-20)*$AI$24,$AK$24+(20-35)*$AJ$24)))))))*(1+$C$6),2)+ROUND(ROUND((IF(20<=2,$AD$24,IF(20<=5,$AE$24,IF(20<=10,$AF$24,IF(20<=15,$AG$24,IF(20<=20,$AH$24,IF(20<=35,$AH$24+(20-20)*$AI$24,$AK$24+(20-35)*$AJ$24)))))))*(1+$C$6),2)*(IF($G$6="YES",$E$6,0)+IF($K$6="YES",$I$6,0)),2) | H92: =ROUND((IF(20<=2,$AD$25,$AD$25+(20-2)*$AE$25))*(1+$C$6),2)+ROUND(ROUND((IF(20<=2,$AD$25,$AD$25+(20-2)*$AE$25))*(1+$C$6),2)*(IF($G$6="YES",$E$6,0)+IF($K$6="YES",$I$6,0)),2)+(20*$E$8*IF($C$8="YES",1,0)) | I92: =ROUND((IF(20<=2,$AD$26,$AD$26+(20-2)*$AE$26))*(1+$C$6),2)+ROUND(ROUND((IF(20<=2,$AD$26,$AD$26+(20-2)*$AE$26))*(1+$C$6),2)*(IF($G$6="YES",$E$6,0)+IF($K$6="YES",$I$6,0)),2)
B93: 21 | C93: =ROUND((IF(21<=5,$AD$20,$AD$20+(21-5)*$AE$20))*(1+$C$6),2)+ROUND(ROUND((IF(21<=5,$AD$20,$AD$20+(21-5)*$AE$20))*(1+$C$6),2)*(IF($G$6="YES",$E$6,0)+IF($K$6="YES",$I$6,0)),2) | D93: =ROUND((IF(21<=15,$AD$21,$AD$21+(21-15)*$AE$21))*(1+$C$6),2)+ROUND(ROUND((IF(21<=15,$AD$21,$AD$21+(21-15)*$AE$21))*(1+$C$6),2)*(IF($G$6="YES",$E$6,0)+IF($K$6="YES",$I$6,0)),2) | E93: =ROUND((IF(21<=2,$AD$22,IF(21<=5,$AE$22,IF(21<=10,$AF$22,IF(21<=15,$AG$22,IF(21<=20,$AH$22,IF(21<=35,$AH$22+(21-20)*$AI$22,$AK$22+(21-35)*$AJ$22)))))))*(1+$C$6),2)+ROUND(ROUND((IF(21<=2,$AD$22,IF(21<=5,$AE$22,IF(21<=10,$AF$22,IF(21<=15,$AG$22,IF(21<=20,$AH$22,IF(21<=35,$AH$22+(21-20)*$AI$22,$AK$22+(21-35)*$AJ$22)))))))*(1+$C$6),2)*(IF($G$6="YES",$E$6,0)+IF($K$6="YES",$I$6,0)),2) | F93: =ROUND((IF(21<=2,$AD$23,IF(21<=5,$AE$23,IF(21<=10,$AF$23,IF(21<=15,$AG$23,IF(21<=20,$AH$23,IF(21<=35,$AH$23+(21-20)*$AI$23,$AK$23+(21-35)*$AJ$23)))))))*(1+$C$6),2)+ROUND(ROUND((IF(21<=2,$AD$23,IF(21<=5,$AE$23,IF(21<=10,$AF$23,IF(21<=15,$AG$23,IF(21<=20,$AH$23,IF(21<=35,$AH$23+(21-20)*$AI$23,$AK$23+(21-35)*$AJ$23)))))))*(1+$C$6),2)*(IF($G$6="YES",$E$6,0)+IF($K$6="YES",$I$6,0)),2) | G93: =ROUND((IF(21<=2,$AD$24,IF(21<=5,$AE$24,IF(21<=10,$AF$24,IF(21<=15,$AG$24,IF(21<=20,$AH$24,IF(21<=35,$AH$24+(21-20)*$AI$24,$AK$24+(21-35)*$AJ$24)))))))*(1+$C$6),2)+ROUND(ROUND((IF(21<=2,$AD$24,IF(21<=5,$AE$24,IF(21<=10,$AF$24,IF(21<=15,$AG$24,IF(21<=20,$AH$24,IF(21<=35,$AH$24+(21-20)*$AI$24,$AK$24+(21-35)*$AJ$24)))))))*(1+$C$6),2)*(IF($G$6="YES",$E$6,0)+IF($K$6="YES",$I$6,0)),2) | H93: =ROUND((IF(21<=2,$AD$25,$AD$25+(21-2)*$AE$25))*(1+$C$6),2)+ROUND(ROUND((IF(21<=2,$AD$25,$AD$25+(21-2)*$AE$25))*(1+$C$6),2)*(IF($G$6="YES",$E$6,0)+IF($K$6="YES",$I$6,0)),2)+(21*$E$8*IF($C$8="YES",1,0)) | I93: =ROUND((IF(21<=2,$AD$26,$AD$26+(21-2)*$AE$26))*(1+$C$6),2)+ROUND(ROUND((IF(21<=2,$AD$26,$AD$26+(21-2)*$AE$26))*(1+$C$6),2)*(IF($G$6="YES",$E$6,0)+IF($K$6="YES",$I$6,0)),2)
B94: 22 | C94: =ROUND((IF(22<=5,$AD$20,$AD$20+(22-5)*$AE$20))*(1+$C$6),2)+ROUND(ROUND((IF(22<=5,$AD$20,$AD$20+(22-5)*$AE$20))*(1+$C$6),2)*(IF($G$6="YES",$E$6,0)+IF($K$6="YES",$I$6,0)),2) | D94: =ROUND((IF(22<=15,$AD$21,$AD$21+(22-15)*$AE$21))*(1+$C$6),2)+ROUND(ROUND((IF(22<=15,$AD$21,$AD$21+(22-15)*$AE$21))*(1+$C$6),2)*(IF($G$6="YES",$E$6,0)+IF($K$6="YES",$I$6,0)),2) | E94: =ROUND((IF(22<=2,$AD$22,IF(22<=5,$AE$22,IF(22<=10,$AF$22,IF(22<=15,$AG$22,IF(22<=20,$AH$22,IF(22<=35,$AH$22+(22-20)*$AI$22,$AK$22+(22-35)*$AJ$22)))))))*(1+$C$6),2)+ROUND(ROUND((IF(22<=2,$AD$22,IF(22<=5,$AE$22,IF(22<=10,$AF$22,IF(22<=15,$AG$22,IF(22<=20,$AH$22,IF(22<=35,$AH$22+(22-20)*$AI$22,$AK$22+(22-35)*$AJ$22)))))))*(1+$C$6),2)*(IF($G$6="YES",$E$6,0)+IF($K$6="YES",$I$6,0)),2) | F94: =ROUND((IF(22<=2,$AD$23,IF(22<=5,$AE$23,IF(22<=10,$AF$23,IF(22<=15,$AG$23,IF(22<=20,$AH$23,IF(22<=35,$AH$23+(22-20)*$AI$23,$AK$23+(22-35)*$AJ$23)))))))*(1+$C$6),2)+ROUND(ROUND((IF(22<=2,$AD$23,IF(22<=5,$AE$23,IF(22<=10,$AF$23,IF(22<=15,$AG$23,IF(22<=20,$AH$23,IF(22<=35,$AH$23+(22-20)*$AI$23,$AK$23+(22-35)*$AJ$23)))))))*(1+$C$6),2)*(IF($G$6="YES",$E$6,0)+IF($K$6="YES",$I$6,0)),2) | G94: =ROUND((IF(22<=2,$AD$24,IF(22<=5,$AE$24,IF(22<=10,$AF$24,IF(22<=15,$AG$24,IF(22<=20,$AH$24,IF(22<=35,$AH$24+(22-20)*$AI$24,$AK$24+(22-35)*$AJ$24)))))))*(1+$C$6),2)+ROUND(ROUND((IF(22<=2,$AD$24,IF(22<=5,$AE$24,IF(22<=10,$AF$24,IF(22<=15,$AG$24,IF(22<=20,$AH$24,IF(22<=35,$AH$24+(22-20)*$AI$24,$AK$24+(22-35)*$AJ$24)))))))*(1+$C$6),2)*(IF($G$6="YES",$E$6,0)+IF($K$6="YES",$I$6,0)),2) | H94: =ROUND((IF(22<=2,$AD$25,$AD$25+(22-2)*$AE$25))*(1+$C$6),2)+ROUND(ROUND((IF(22<=2,$AD$25,$AD$25+(22-2)*$AE$25))*(1+$C$6),2)*(IF($G$6="YES",$E$6,0)+IF($K$6="YES",$I$6,0)),2)+(22*$E$8*IF($C$8="YES",1,0)) | I94: =ROUND((IF(22<=2,$AD$26,$AD$26+(22-2)*$AE$26))*(1+$C$6),2)+ROUND(ROUND((IF(22<=2,$AD$26,$AD$26+(22-2)*$AE$26))*(1+$C$6),2)*(IF($G$6="YES",$E$6,0)+IF($K$6="YES",$I$6,0)),2)
B95: 23 | C95: =ROUND((IF(23<=5,$AD$20,$AD$20+(23-5)*$AE$20))*(1+$C$6),2)+ROUND(ROUND((IF(23<=5,$AD$20,$AD$20+(23-5)*$AE$20))*(1+$C$6),2)*(IF($G$6="YES",$E$6,0)+IF($K$6="YES",$I$6,0)),2) | D95: =ROUND((IF(23<=15,$AD$21,$AD$21+(23-15)*$AE$21))*(1+$C$6),2)+ROUND(ROUND((IF(23<=15,$AD$21,$AD$21+(23-15)*$AE$21))*(1+$C$6),2)*(IF($G$6="YES",$E$6,0)+IF($K$6="YES",$I$6,0)),2) | E95: =ROUND((IF(23<=2,$AD$22,IF(23<=5,$AE$22,IF(23<=10,$AF$22,IF(23<=15,$AG$22,IF(23<=20,$AH$22,IF(23<=35,$AH$22+(23-20)*$AI$22,$AK$22+(23-35)*$AJ$22)))))))*(1+$C$6),2)+ROUND(ROUND((IF(23<=2,$AD$22,IF(23<=5,$AE$22,IF(23<=10,$AF$22,IF(23<=15,$AG$22,IF(23<=20,$AH$22,IF(23<=35,$AH$22+(23-20)*$AI$22,$AK$22+(23-35)*$AJ$22)))))))*(1+$C$6),2)*(IF($G$6="YES",$E$6,0)+IF($K$6="YES",$I$6,0)),2) | F95: =ROUND((IF(23<=2,$AD$23,IF(23<=5,$AE$23,IF(23<=10,$AF$23,IF(23<=15,$AG$23,IF(23<=20,$AH$23,IF(23<=35,$AH$23+(23-20)*$AI$23,$AK$23+(23-35)*$AJ$23)))))))*(1+$C$6),2)+ROUND(ROUND((IF(23<=2,$AD$23,IF(23<=5,$AE$23,IF(23<=10,$AF$23,IF(23<=15,$AG$23,IF(23<=20,$AH$23,IF(23<=35,$AH$23+(23-20)*$AI$23,$AK$23+(23-35)*$AJ$23)))))))*(1+$C$6),2)*(IF($G$6="YES",$E$6,0)+IF($K$6="YES",$I$6,0)),2) | G95: =ROUND((IF(23<=2,$AD$24,IF(23<=5,$AE$24,IF(23<=10,$AF$24,IF(23<=15,$AG$24,IF(23<=20,$AH$24,IF(23<=35,$AH$24+(23-20)*$AI$24,$AK$24+(23-35)*$AJ$24)))))))*(1+$C$6),2)+ROUND(ROUND((IF(23<=2,$AD$24,IF(23<=5,$AE$24,IF(23<=10,$AF$24,IF(23<=15,$AG$24,IF(23<=20,$AH$24,IF(23<=35,$AH$24+(23-20)*$AI$24,$AK$24+(23-35)*$AJ$24)))))))*(1+$C$6),2)*(IF($G$6="YES",$E$6,0)+IF($K$6="YES",$I$6,0)),2) | H95: =ROUND((IF(23<=2,$AD$25,$AD$25+(23-2)*$AE$25))*(1+$C$6),2)+ROUND(ROUND((IF(23<=2,$AD$25,$AD$25+(23-2)*$AE$25))*(1+$C$6),2)*(IF($G$6="YES",$E$6,0)+IF($K$6="YES",$I$6,0)),2)+(23*$E$8*IF($C$8="YES",1,0)) | I95: =ROUND((IF(23<=2,$AD$26,$AD$26+(23-2)*$AE$26))*(1+$C$6),2)+ROUND(ROUND((IF(23<=2,$AD$26,$AD$26+(23-2)*$AE$26))*(1+$C$6),2)*(IF($G$6="YES",$E$6,0)+IF($K$6="YES",$I$6,0)),2)
B96: 24 | C96: =ROUND((IF(24<=5,$AD$20,$AD$20+(24-5)*$AE$20))*(1+$C$6),2)+ROUND(ROUND((IF(24<=5,$AD$20,$AD$20+(24-5)*$AE$20))*(1+$C$6),2)*(IF($G$6="YES",$E$6,0)+IF($K$6="YES",$I$6,0)),2) | D96: =ROUND((IF(24<=15,$AD$21,$AD$21+(24-15)*$AE$21))*(1+$C$6),2)+ROUND(ROUND((IF(24<=15,$AD$21,$AD$21+(24-15)*$AE$21))*(1+$C$6),2)*(IF($G$6="YES",$E$6,0)+IF($K$6="YES",$I$6,0)),2) | E96: =ROUND((IF(24<=2,$AD$22,IF(24<=5,$AE$22,IF(24<=10,$AF$22,IF(24<=15,$AG$22,IF(24<=20,$AH$22,IF(24<=35,$AH$22+(24-20)*$AI$22,$AK$22+(24-35)*$AJ$22)))))))*(1+$C$6),2)+ROUND(ROUND((IF(24<=2,$AD$22,IF(24<=5,$AE$22,IF(24<=10,$AF$22,IF(24<=15,$AG$22,IF(24<=20,$AH$22,IF(24<=35,$AH$22+(24-20)*$AI$22,$AK$22+(24-35)*$AJ$22)))))))*(1+$C$6),2)*(IF($G$6="YES",$E$6,0)+IF($K$6="YES",$I$6,0)),2) | F96: =ROUND((IF(24<=2,$AD$23,IF(24<=5,$AE$23,IF(24<=10,$AF$23,IF(24<=15,$AG$23,IF(24<=20,$AH$23,IF(24<=35,$AH$23+(24-20)*$AI$23,$AK$23+(24-35)*$AJ$23)))))))*(1+$C$6),2)+ROUND(ROUND((IF(24<=2,$AD$23,IF(24<=5,$AE$23,IF(24<=10,$AF$23,IF(24<=15,$AG$23,IF(24<=20,$AH$23,IF(24<=35,$AH$23+(24-20)*$AI$23,$AK$23+(24-35)*$AJ$23)))))))*(1+$C$6),2)*(IF($G$6="YES",$E$6,0)+IF($K$6="YES",$I$6,0)),2) | G96: =ROUND((IF(24<=2,$AD$24,IF(24<=5,$AE$24,IF(24<=10,$AF$24,IF(24<=15,$AG$24,IF(24<=20,$AH$24,IF(24<=35,$AH$24+(24-20)*$AI$24,$AK$24+(24-35)*$AJ$24)))))))*(1+$C$6),2)+ROUND(ROUND((IF(24<=2,$AD$24,IF(24<=5,$AE$24,IF(24<=10,$AF$24,IF(24<=15,$AG$24,IF(24<=20,$AH$24,IF(24<=35,$AH$24+(24-20)*$AI$24,$AK$24+(24-35)*$AJ$24)))))))*(1+$C$6),2)*(IF($G$6="YES",$E$6,0)+IF($K$6="YES",$I$6,0)),2) | H96: =ROUND((IF(24<=2,$AD$25,$AD$25+(24-2)*$AE$25))*(1+$C$6),2)+ROUND(ROUND((IF(24<=2,$AD$25,$AD$25+(24-2)*$AE$25))*(1+$C$6),2)*(IF($G$6="YES",$E$6,0)+IF($K$6="YES",$I$6,0)),2)+(24*$E$8*IF($C$8="YES",1,0)) | I96: =ROUND((IF(24<=2,$AD$26,$AD$26+(24-2)*$AE$26))*(1+$C$6),2)+ROUND(ROUND((IF(24<=2,$AD$26,$AD$26+(24-2)*$AE$26))*(1+$C$6),2)*(IF($G$6="YES",$E$6,0)+IF($K$6="YES",$I$6,0)),2)
B97: 25 | C97: =ROUND((IF(25<=5,$AD$20,$AD$20+(25-5)*$AE$20))*(1+$C$6),2)+ROUND(ROUND((IF(25<=5,$AD$20,$AD$20+(25-5)*$AE$20))*(1+$C$6),2)*(IF($G$6="YES",$E$6,0)+IF($K$6="YES",$I$6,0)),2) | D97: =ROUND((IF(25<=15,$AD$21,$AD$21+(25-15)*$AE$21))*(1+$C$6),2)+ROUND(ROUND((IF(25<=15,$AD$21,$AD$21+(25-15)*$AE$21))*(1+$C$6),2)*(IF($G$6="YES",$E$6,0)+IF($K$6="YES",$I$6,0)),2) | E97: =ROUND((IF(25<=2,$AD$22,IF(25<=5,$AE$22,IF(25<=10,$AF$22,IF(25<=15,$AG$22,IF(25<=20,$AH$22,IF(25<=35,$AH$22+(25-20)*$AI$22,$AK$22+(25-35)*$AJ$22)))))))*(1+$C$6),2)+ROUND(ROUND((IF(25<=2,$AD$22,IF(25<=5,$AE$22,IF(25<=10,$AF$22,IF(25<=15,$AG$22,IF(25<=20,$AH$22,IF(25<=35,$AH$22+(25-20)*$AI$22,$AK$22+(25-35)*$AJ$22)))))))*(1+$C$6),2)*(IF($G$6="YES",$E$6,0)+IF($K$6="YES",$I$6,0)),2) | F97: =ROUND((IF(25<=2,$AD$23,IF(25<=5,$AE$23,IF(25<=10,$AF$23,IF(25<=15,$AG$23,IF(25<=20,$AH$23,IF(25<=35,$AH$23+(25-20)*$AI$23,$AK$23+(25-35)*$AJ$23)))))))*(1+$C$6),2)+ROUND(ROUND((IF(25<=2,$AD$23,IF(25<=5,$AE$23,IF(25<=10,$AF$23,IF(25<=15,$AG$23,IF(25<=20,$AH$23,IF(25<=35,$AH$23+(25-20)*$AI$23,$AK$23+(25-35)*$AJ$23)))))))*(1+$C$6),2)*(IF($G$6="YES",$E$6,0)+IF($K$6="YES",$I$6,0)),2) | G97: =ROUND((IF(25<=2,$AD$24,IF(25<=5,$AE$24,IF(25<=10,$AF$24,IF(25<=15,$AG$24,IF(25<=20,$AH$24,IF(25<=35,$AH$24+(25-20)*$AI$24,$AK$24+(25-35)*$AJ$24)))))))*(1+$C$6),2)+ROUND(ROUND((IF(25<=2,$AD$24,IF(25<=5,$AE$24,IF(25<=10,$AF$24,IF(25<=15,$AG$24,IF(25<=20,$AH$24,IF(25<=35,$AH$24+(25-20)*$AI$24,$AK$24+(25-35)*$AJ$24)))))))*(1+$C$6),2)*(IF($G$6="YES",$E$6,0)+IF($K$6="YES",$I$6,0)),2) | H97: =ROUND((IF(25<=2,$AD$25,$AD$25+(25-2)*$AE$25))*(1+$C$6),2)+ROUND(ROUND((IF(25<=2,$AD$25,$AD$25+(25-2)*$AE$25))*(1+$C$6),2)*(IF($G$6="YES",$E$6,0)+IF($K$6="YES",$I$6,0)),2)+(25*$E$8*IF($C$8="YES",1,0)) | I97: =ROUND((IF(25<=2,$AD$26,$AD$26+(25-2)*$AE$26))*(1+$C$6),2)+ROUND(ROUND((IF(25<=2,$AD$26,$AD$26+(25-2)*$AE$26))*(1+$C$6),2)*(IF($G$6="YES",$E$6,0)+IF($K$6="YES",$I$6,0)),2)
B98: 26 | C98: =ROUND((IF(26<=5,$AD$20,$AD$20+(26-5)*$AE$20))*(1+$C$6),2)+ROUND(ROUND((IF(26<=5,$AD$20,$AD$20+(26-5)*$AE$20))*(1+$C$6),2)*(IF($G$6="YES",$E$6,0)+IF($K$6="YES",$I$6,0)),2) | D98: =ROUND((IF(26<=15,$AD$21,$AD$21+(26-15)*$AE$21))*(1+$C$6),2)+ROUND(ROUND((IF(26<=15,$AD$21,$AD$21+(26-15)*$AE$21))*(1+$C$6),2)*(IF($G$6="YES",$E$6,0)+IF($K$6="YES",$I$6,0)),2) | E98: =ROUND((IF(26<=2,$AD$22,IF(26<=5,$AE$22,IF(26<=10,$AF$22,IF(26<=15,$AG$22,IF(26<=20,$AH$22,IF(26<=35,$AH$22+(26-20)*$AI$22,$AK$22+(26-35)*$AJ$22)))))))*(1+$C$6),2)+ROUND(ROUND((IF(26<=2,$AD$22,IF(26<=5,$AE$22,IF(26<=10,$AF$22,IF(26<=15,$AG$22,IF(26<=20,$AH$22,IF(26<=35,$AH$22+(26-20)*$AI$22,$AK$22+(26-35)*$AJ$22)))))))*(1+$C$6),2)*(IF($G$6="YES",$E$6,0)+IF($K$6="YES",$I$6,0)),2) | F98: =ROUND((IF(26<=2,$AD$23,IF(26<=5,$AE$23,IF(26<=10,$AF$23,IF(26<=15,$AG$23,IF(26<=20,$AH$23,IF(26<=35,$AH$23+(26-20)*$AI$23,$AK$23+(26-35)*$AJ$23)))))))*(1+$C$6),2)+ROUND(ROUND((IF(26<=2,$AD$23,IF(26<=5,$AE$23,IF(26<=10,$AF$23,IF(26<=15,$AG$23,IF(26<=20,$AH$23,IF(26<=35,$AH$23+(26-20)*$AI$23,$AK$23+(26-35)*$AJ$23)))))))*(1+$C$6),2)*(IF($G$6="YES",$E$6,0)+IF($K$6="YES",$I$6,0)),2) | G98: =ROUND((IF(26<=2,$AD$24,IF(26<=5,$AE$24,IF(26<=10,$AF$24,IF(26<=15,$AG$24,IF(26<=20,$AH$24,IF(26<=35,$AH$24+(26-20)*$AI$24,$AK$24+(26-35)*$AJ$24)))))))*(1+$C$6),2)+ROUND(ROUND((IF(26<=2,$AD$24,IF(26<=5,$AE$24,IF(26<=10,$AF$24,IF(26<=15,$AG$24,IF(26<=20,$AH$24,IF(26<=35,$AH$24+(26-20)*$AI$24,$AK$24+(26-35)*$AJ$24)))))))*(1+$C$6),2)*(IF($G$6="YES",$E$6,0)+IF($K$6="YES",$I$6,0)),2) | H98: =ROUND((IF(26<=2,$AD$25,$AD$25+(26-2)*$AE$25))*(1+$C$6),2)+ROUND(ROUND((IF(26<=2,$AD$25,$AD$25+(26-2)*$AE$25))*(1+$C$6),2)*(IF($G$6="YES",$E$6,0)+IF($K$6="YES",$I$6,0)),2)+(26*$E$8*IF($C$8="YES",1,0)) | I98: =ROUND((IF(26<=2,$AD$26,$AD$26+(26-2)*$AE$26))*(1+$C$6),2)+ROUND(ROUND((IF(26<=2,$AD$26,$AD$26+(26-2)*$AE$26))*(1+$C$6),2)*(IF($G$6="YES",$E$6,0)+IF($K$6="YES",$I$6,0)),2)
B99: 27 | C99: =ROUND((IF(27<=5,$AD$20,$AD$20+(27-5)*$AE$20))*(1+$C$6),2)+ROUND(ROUND((IF(27<=5,$AD$20,$AD$20+(27-5)*$AE$20))*(1+$C$6),2)*(IF($G$6="YES",$E$6,0)+IF($K$6="YES",$I$6,0)),2) | D99: =ROUND((IF(27<=15,$AD$21,$AD$21+(27-15)*$AE$21))*(1+$C$6),2)+ROUND(ROUND((IF(27<=15,$AD$21,$AD$21+(27-15)*$AE$21))*(1+$C$6),2)*(IF($G$6="YES",$E$6,0)+IF($K$6="YES",$I$6,0)),2) | E99: =ROUND((IF(27<=2,$AD$22,IF(27<=5,$AE$22,IF(27<=10,$AF$22,IF(27<=15,$AG$22,IF(27<=20,$AH$22,IF(27<=35,$AH$22+(27-20)*$AI$22,$AK$22+(27-35)*$AJ$22)))))))*(1+$C$6),2)+ROUND(ROUND((IF(27<=2,$AD$22,IF(27<=5,$AE$22,IF(27<=10,$AF$22,IF(27<=15,$AG$22,IF(27<=20,$AH$22,IF(27<=35,$AH$22+(27-20)*$AI$22,$AK$22+(27-35)*$AJ$22)))))))*(1+$C$6),2)*(IF($G$6="YES",$E$6,0)+IF($K$6="YES",$I$6,0)),2) | F99: =ROUND((IF(27<=2,$AD$23,IF(27<=5,$AE$23,IF(27<=10,$AF$23,IF(27<=15,$AG$23,IF(27<=20,$AH$23,IF(27<=35,$AH$23+(27-20)*$AI$23,$AK$23+(27-35)*$AJ$23)))))))*(1+$C$6),2)+ROUND(ROUND((IF(27<=2,$AD$23,IF(27<=5,$AE$23,IF(27<=10,$AF$23,IF(27<=15,$AG$23,IF(27<=20,$AH$23,IF(27<=35,$AH$23+(27-20)*$AI$23,$AK$23+(27-35)*$AJ$23)))))))*(1+$C$6),2)*(IF($G$6="YES",$E$6,0)+IF($K$6="YES",$I$6,0)),2) | G99: =ROUND((IF(27<=2,$AD$24,IF(27<=5,$AE$24,IF(27<=10,$AF$24,IF(27<=15,$AG$24,IF(27<=20,$AH$24,IF(27<=35,$AH$24+(27-20)*$AI$24,$AK$24+(27-35)*$AJ$24)))))))*(1+$C$6),2)+ROUND(ROUND((IF(27<=2,$AD$24,IF(27<=5,$AE$24,IF(27<=10,$AF$24,IF(27<=15,$AG$24,IF(27<=20,$AH$24,IF(27<=35,$AH$24+(27-20)*$AI$24,$AK$24+(27-35)*$AJ$24)))))))*(1+$C$6),2)*(IF($G$6="YES",$E$6,0)+IF($K$6="YES",$I$6,0)),2) | H99: =ROUND((IF(27<=2,$AD$25,$AD$25+(27-2)*$AE$25))*(1+$C$6),2)+ROUND(ROUND((IF(27<=2,$AD$25,$AD$25+(27-2)*$AE$25))*(1+$C$6),2)*(IF($G$6="YES",$E$6,0)+IF($K$6="YES",$I$6,0)),2)+(27*$E$8*IF($C$8="YES",1,0)) | I99: =ROUND((IF(27<=2,$AD$26,$AD$26+(27-2)*$AE$26))*(1+$C$6),2)+ROUND(ROUND((IF(27<=2,$AD$26,$AD$26+(27-2)*$AE$26))*(1+$C$6),2)*(IF($G$6="YES",$E$6,0)+IF($K$6="YES",$I$6,0)),2)
B100: 28 | C100: =ROUND((IF(28<=5,$AD$20,$AD$20+(28-5)*$AE$20))*(1+$C$6),2)+ROUND(ROUND((IF(28<=5,$AD$20,$AD$20+(28-5)*$AE$20))*(1+$C$6),2)*(IF($G$6="YES",$E$6,0)+IF($K$6="YES",$I$6,0)),2) | D100: =ROUND((IF(28<=15,$AD$21,$AD$21+(28-15)*$AE$21))*(1+$C$6),2)+ROUND(ROUND((IF(28<=15,$AD$21,$AD$21+(28-15)*$AE$21))*(1+$C$6),2)*(IF($G$6="YES",$E$6,0)+IF($K$6="YES",$I$6,0)),2) | E100: =ROUND((IF(28<=2,$AD$22,IF(28<=5,$AE$22,IF(28<=10,$AF$22,IF(28<=15,$AG$22,IF(28<=20,$AH$22,IF(28<=35,$AH$22+(28-20)*$AI$22,$AK$22+(28-35)*$AJ$22)))))))*(1+$C$6),2)+ROUND(ROUND((IF(28<=2,$AD$22,IF(28<=5,$AE$22,IF(28<=10,$AF$22,IF(28<=15,$AG$22,IF(28<=20,$AH$22,IF(28<=35,$AH$22+(28-20)*$AI$22,$AK$22+(28-35)*$AJ$22)))))))*(1+$C$6),2)*(IF($G$6="YES",$E$6,0)+IF($K$6="YES",$I$6,0)),2) | F100: =ROUND((IF(28<=2,$AD$23,IF(28<=5,$AE$23,IF(28<=10,$AF$23,IF(28<=15,$AG$23,IF(28<=20,$AH$23,IF(28<=35,$AH$23+(28-20)*$AI$23,$AK$23+(28-35)*$AJ$23)))))))*(1+$C$6),2)+ROUND(ROUND((IF(28<=2,$AD$23,IF(28<=5,$AE$23,IF(28<=10,$AF$23,IF(28<=15,$AG$23,IF(28<=20,$AH$23,IF(28<=35,$AH$23+(28-20)*$AI$23,$AK$23+(28-35)*$AJ$23)))))))*(1+$C$6),2)*(IF($G$6="YES",$E$6,0)+IF($K$6="YES",$I$6,0)),2) | G100: =ROUND((IF(28<=2,$AD$24,IF(28<=5,$AE$24,IF(28<=10,$AF$24,IF(28<=15,$AG$24,IF(28<=20,$AH$24,IF(28<=35,$AH$24+(28-20)*$AI$24,$AK$24+(28-35)*$AJ$24)))))))*(1+$C$6),2)+ROUND(ROUND((IF(28<=2,$AD$24,IF(28<=5,$AE$24,IF(28<=10,$AF$24,IF(28<=15,$AG$24,IF(28<=20,$AH$24,IF(28<=35,$AH$24+(28-20)*$AI$24,$AK$24+(28-35)*$AJ$24)))))))*(1+$C$6),2)*(IF($G$6="YES",$E$6,0)+IF($K$6="YES",$I$6,0)),2) | H100: =ROUND((IF(28<=2,$AD$25,$AD$25+(28-2)*$AE$25))*(1+$C$6),2)+ROUND(ROUND((IF(28<=2,$AD$25,$AD$25+(28-2)*$AE$25))*(1+$C$6),2)*(IF($G$6="YES",$E$6,0)+IF($K$6="YES",$I$6,0)),2)+(28*$E$8*IF($C$8="YES",1,0)) | I100: =ROUND((IF(28<=2,$AD$26,$AD$26+(28-2)*$AE$26))*(1+$C$6),2)+ROUND(ROUND((IF(28<=2,$AD$26,$AD$26+(28-2)*$AE$26))*(1+$C$6),2)*(IF($G$6="YES",$E$6,0)+IF($K$6="YES",$I$6,0)),2)
B101: 29 | C101: =ROUND((IF(29<=5,$AD$20,$AD$20+(29-5)*$AE$20))*(1+$C$6),2)+ROUND(ROUND((IF(29<=5,$AD$20,$AD$20+(29-5)*$AE$20))*(1+$C$6),2)*(IF($G$6="YES",$E$6,0)+IF($K$6="YES",$I$6,0)),2) | D101: =ROUND((IF(29<=15,$AD$21,$AD$21+(29-15)*$AE$21))*(1+$C$6),2)+ROUND(ROUND((IF(29<=15,$AD$21,$AD$21+(29-15)*$AE$21))*(1+$C$6),2)*(IF($G$6="YES",$E$6,0)+IF($K$6="YES",$I$6,0)),2) | E101: =ROUND((IF(29<=2,$AD$22,IF(29<=5,$AE$22,IF(29<=10,$AF$22,IF(29<=15,$AG$22,IF(29<=20,$AH$22,IF(29<=35,$AH$22+(29-20)*$AI$22,$AK$22+(29-35)*$AJ$22)))))))*(1+$C$6),2)+ROUND(ROUND((IF(29<=2,$AD$22,IF(29<=5,$AE$22,IF(29<=10,$AF$22,IF(29<=15,$AG$22,IF(29<=20,$AH$22,IF(29<=35,$AH$22+(29-20)*$AI$22,$AK$22+(29-35)*$AJ$22)))))))*(1+$C$6),2)*(IF($G$6="YES",$E$6,0)+IF($K$6="YES",$I$6,0)),2) | F101: =ROUND((IF(29<=2,$AD$23,IF(29<=5,$AE$23,IF(29<=10,$AF$23,IF(29<=15,$AG$23,IF(29<=20,$AH$23,IF(29<=35,$AH$23+(29-20)*$AI$23,$AK$23+(29-35)*$AJ$23)))))))*(1+$C$6),2)+ROUND(ROUND((IF(29<=2,$AD$23,IF(29<=5,$AE$23,IF(29<=10,$AF$23,IF(29<=15,$AG$23,IF(29<=20,$AH$23,IF(29<=35,$AH$23+(29-20)*$AI$23,$AK$23+(29-35)*$AJ$23)))))))*(1+$C$6),2)*(IF($G$6="YES",$E$6,0)+IF($K$6="YES",$I$6,0)),2) | G101: =ROUND((IF(29<=2,$AD$24,IF(29<=5,$AE$24,IF(29<=10,$AF$24,IF(29<=15,$AG$24,IF(29<=20,$AH$24,IF(29<=35,$AH$24+(29-20)*$AI$24,$AK$24+(29-35)*$AJ$24)))))))*(1+$C$6),2)+ROUND(ROUND((IF(29<=2,$AD$24,IF(29<=5,$AE$24,IF(29<=10,$AF$24,IF(29<=15,$AG$24,IF(29<=20,$AH$24,IF(29<=35,$AH$24+(29-20)*$AI$24,$AK$24+(29-35)*$AJ$24)))))))*(1+$C$6),2)*(IF($G$6="YES",$E$6,0)+IF($K$6="YES",$I$6,0)),2) | H101: =ROUND((IF(29<=2,$AD$25,$AD$25+(29-2)*$AE$25))*(1+$C$6),2)+ROUND(ROUND((IF(29<=2,$AD$25,$AD$25+(29-2)*$AE$25))*(1+$C$6),2)*(IF($G$6="YES",$E$6,0)+IF($K$6="YES",$I$6,0)),2)+(29*$E$8*IF($C$8="YES",1,0)) | I101: =ROUND((IF(29<=2,$AD$26,$AD$26+(29-2)*$AE$26))*(1+$C$6),2)+ROUND(ROUND((IF(29<=2,$AD$26,$AD$26+(29-2)*$AE$26))*(1+$C$6),2)*(IF($G$6="YES",$E$6,0)+IF($K$6="YES",$I$6,0)),2)
B102: 30 | C102: =ROUND((IF(30<=5,$AD$20,$AD$20+(30-5)*$AE$20))*(1+$C$6),2)+ROUND(ROUND((IF(30<=5,$AD$20,$AD$20+(30-5)*$AE$20))*(1+$C$6),2)*(IF($G$6="YES",$E$6,0)+IF($K$6="YES",$I$6,0)),2) | D102: =ROUND((IF(30<=15,$AD$21,$AD$21+(30-15)*$AE$21))*(1+$C$6),2)+ROUND(ROUND((IF(30<=15,$AD$21,$AD$21+(30-15)*$AE$21))*(1+$C$6),2)*(IF($G$6="YES",$E$6,0)+IF($K$6="YES",$I$6,0)),2) | E102: =ROUND((IF(30<=2,$AD$22,IF(30<=5,$AE$22,IF(30<=10,$AF$22,IF(30<=15,$AG$22,IF(30<=20,$AH$22,IF(30<=35,$AH$22+(30-20)*$AI$22,$AK$22+(30-35)*$AJ$22)))))))*(1+$C$6),2)+ROUND(ROUND((IF(30<=2,$AD$22,IF(30<=5,$AE$22,IF(30<=10,$AF$22,IF(30<=15,$AG$22,IF(30<=20,$AH$22,IF(30<=35,$AH$22+(30-20)*$AI$22,$AK$22+(30-35)*$AJ$22)))))))*(1+$C$6),2)*(IF($G$6="YES",$E$6,0)+IF($K$6="YES",$I$6,0)),2) | F102: =ROUND((IF(30<=2,$AD$23,IF(30<=5,$AE$23,IF(30<=10,$AF$23,IF(30<=15,$AG$23,IF(30<=20,$AH$23,IF(30<=35,$AH$23+(30-20)*$AI$23,$AK$23+(30-35)*$AJ$23)))))))*(1+$C$6),2)+ROUND(ROUND((IF(30<=2,$AD$23,IF(30<=5,$AE$23,IF(30<=10,$AF$23,IF(30<=15,$AG$23,IF(30<=20,$AH$23,IF(30<=35,$AH$23+(30-20)*$AI$23,$AK$23+(30-35)*$AJ$23)))))))*(1+$C$6),2)*(IF($G$6="YES",$E$6,0)+IF($K$6="YES",$I$6,0)),2) | G102: =ROUND((IF(30<=2,$AD$24,IF(30<=5,$AE$24,IF(30<=10,$AF$24,IF(30<=15,$AG$24,IF(30<=20,$AH$24,IF(30<=35,$AH$24+(30-20)*$AI$24,$AK$24+(30-35)*$AJ$24)))))))*(1+$C$6),2)+ROUND(ROUND((IF(30<=2,$AD$24,IF(30<=5,$AE$24,IF(30<=10,$AF$24,IF(30<=15,$AG$24,IF(30<=20,$AH$24,IF(30<=35,$AH$24+(30-20)*$AI$24,$AK$24+(30-35)*$AJ$24)))))))*(1+$C$6),2)*(IF($G$6="YES",$E$6,0)+IF($K$6="YES",$I$6,0)),2) | H102: =ROUND((IF(30<=2,$AD$25,$AD$25+(30-2)*$AE$25))*(1+$C$6),2)+ROUND(ROUND((IF(30<=2,$AD$25,$AD$25+(30-2)*$AE$25))*(1+$C$6),2)*(IF($G$6="YES",$E$6,0)+IF($K$6="YES",$I$6,0)),2)+(30*$E$8*IF($C$8="YES",1,0)) | I102: =ROUND((IF(30<=2,$AD$26,$AD$26+(30-2)*$AE$26))*(1+$C$6),2)+ROUND(ROUND((IF(30<=2,$AD$26,$AD$26+(30-2)*$AE$26))*(1+$C$6),2)*(IF($G$6="YES",$E$6,0)+IF($K$6="YES",$I$6,0)),2)
B103: 31 | C103: =ROUND((IF(31<=5,$AD$20,$AD$20+(31-5)*$AE$20))*(1+$C$6),2)+ROUND(ROUND((IF(31<=5,$AD$20,$AD$20+(31-5)*$AE$20))*(1+$C$6),2)*(IF($G$6="YES",$E$6,0)+IF($K$6="YES",$I$6,0)),2) | D103: =ROUND((IF(31<=15,$AD$21,$AD$21+(31-15)*$AE$21))*(1+$C$6),2)+ROUND(ROUND((IF(31<=15,$AD$21,$AD$21+(31-15)*$AE$21))*(1+$C$6),2)*(IF($G$6="YES",$E$6,0)+IF($K$6="YES",$I$6,0)),2) | E103: =ROUND((IF(31<=2,$AD$22,IF(31<=5,$AE$22,IF(31<=10,$AF$22,IF(31<=15,$AG$22,IF(31<=20,$AH$22,IF(31<=35,$AH$22+(31-20)*$AI$22,$AK$22+(31-35)*$AJ$22)))))))*(1+$C$6),2)+ROUND(ROUND((IF(31<=2,$AD$22,IF(31<=5,$AE$22,IF(31<=10,$AF$22,IF(31<=15,$AG$22,IF(31<=20,$AH$22,IF(31<=35,$AH$22+(31-20)*$AI$22,$AK$22+(31-35)*$AJ$22)))))))*(1+$C$6),2)*(IF($G$6="YES",$E$6,0)+IF($K$6="YES",$I$6,0)),2) | F103: =ROUND((IF(31<=2,$AD$23,IF(31<=5,$AE$23,IF(31<=10,$AF$23,IF(31<=15,$AG$23,IF(31<=20,$AH$23,IF(31<=35,$AH$23+(31-20)*$AI$23,$AK$23+(31-35)*$AJ$23)))))))*(1+$C$6),2)+ROUND(ROUND((IF(31<=2,$AD$23,IF(31<=5,$AE$23,IF(31<=10,$AF$23,IF(31<=15,$AG$23,IF(31<=20,$AH$23,IF(31<=35,$AH$23+(31-20)*$AI$23,$AK$23+(31-35)*$AJ$23)))))))*(1+$C$6),2)*(IF($G$6="YES",$E$6,0)+IF($K$6="YES",$I$6,0)),2) | G103: =ROUND((IF(31<=2,$AD$24,IF(31<=5,$AE$24,IF(31<=10,$AF$24,IF(31<=15,$AG$24,IF(31<=20,$AH$24,IF(31<=35,$AH$24+(31-20)*$AI$24,$AK$24+(31-35)*$AJ$24)))))))*(1+$C$6),2)+ROUND(ROUND((IF(31<=2,$AD$24,IF(31<=5,$AE$24,IF(31<=10,$AF$24,IF(31<=15,$AG$24,IF(31<=20,$AH$24,IF(31<=35,$AH$24+(31-20)*$AI$24,$AK$24+(31-35)*$AJ$24)))))))*(1+$C$6),2)*(IF($G$6="YES",$E$6,0)+IF($K$6="YES",$I$6,0)),2) | H103: =ROUND((IF(31<=2,$AD$25,$AD$25+(31-2)*$AE$25))*(1+$C$6),2)+ROUND(ROUND((IF(31<=2,$AD$25,$AD$25+(31-2)*$AE$25))*(1+$C$6),2)*(IF($G$6="YES",$E$6,0)+IF($K$6="YES",$I$6,0)),2)+(31*$E$8*IF($C$8="YES",1,0)) | I103: =ROUND((IF(31<=2,$AD$26,$AD$26+(31-2)*$AE$26))*(1+$C$6),2)+ROUND(ROUND((IF(31<=2,$AD$26,$AD$26+(31-2)*$AE$26))*(1+$C$6),2)*(IF($G$6="YES",$E$6,0)+IF($K$6="YES",$I$6,0)),2)
B104: 32 | C104: =ROUND((IF(32<=5,$AD$20,$AD$20+(32-5)*$AE$20))*(1+$C$6),2)+ROUND(ROUND((IF(32<=5,$AD$20,$AD$20+(32-5)*$AE$20))*(1+$C$6),2)*(IF($G$6="YES",$E$6,0)+IF($K$6="YES",$I$6,0)),2) | D104: =ROUND((IF(32<=15,$AD$21,$AD$21+(32-15)*$AE$21))*(1+$C$6),2)+ROUND(ROUND((IF(32<=15,$AD$21,$AD$21+(32-15)*$AE$21))*(1+$C$6),2)*(IF($G$6="YES",$E$6,0)+IF($K$6="YES",$I$6,0)),2) | E104: =ROUND((IF(32<=2,$AD$22,IF(32<=5,$AE$22,IF(32<=10,$AF$22,IF(32<=15,$AG$22,IF(32<=20,$AH$22,IF(32<=35,$AH$22+(32-20)*$AI$22,$AK$22+(32-35)*$AJ$22)))))))*(1+$C$6),2)+ROUND(ROUND((IF(32<=2,$AD$22,IF(32<=5,$AE$22,IF(32<=10,$AF$22,IF(32<=15,$AG$22,IF(32<=20,$AH$22,IF(32<=35,$AH$22+(32-20)*$AI$22,$AK$22+(32-35)*$AJ$22)))))))*(1+$C$6),2)*(IF($G$6="YES",$E$6,0)+IF($K$6="YES",$I$6,0)),2) | F104: =ROUND((IF(32<=2,$AD$23,IF(32<=5,$AE$23,IF(32<=10,$AF$23,IF(32<=15,$AG$23,IF(32<=20,$AH$23,IF(32<=35,$AH$23+(32-20)*$AI$23,$AK$23+(32-35)*$AJ$23)))))))*(1+$C$6),2)+ROUND(ROUND((IF(32<=2,$AD$23,IF(32<=5,$AE$23,IF(32<=10,$AF$23,IF(32<=15,$AG$23,IF(32<=20,$AH$23,IF(32<=35,$AH$23+(32-20)*$AI$23,$AK$23+(32-35)*$AJ$23)))))))*(1+$C$6),2)*(IF($G$6="YES",$E$6,0)+IF($K$6="YES",$I$6,0)),2) | G104: =ROUND((IF(32<=2,$AD$24,IF(32<=5,$AE$24,IF(32<=10,$AF$24,IF(32<=15,$AG$24,IF(32<=20,$AH$24,IF(32<=35,$AH$24+(32-20)*$AI$24,$AK$24+(32-35)*$AJ$24)))))))*(1+$C$6),2)+ROUND(ROUND((IF(32<=2,$AD$24,IF(32<=5,$AE$24,IF(32<=10,$AF$24,IF(32<=15,$AG$24,IF(32<=20,$AH$24,IF(32<=35,$AH$24+(32-20)*$AI$24,$AK$24+(32-35)*$AJ$24)))))))*(1+$C$6),2)*(IF($G$6="YES",$E$6,0)+IF($K$6="YES",$I$6,0)),2) | H104: =ROUND((IF(32<=2,$AD$25,$AD$25+(32-2)*$AE$25))*(1+$C$6),2)+ROUND(ROUND((IF(32<=2,$AD$25,$AD$25+(32-2)*$AE$25))*(1+$C$6),2)*(IF($G$6="YES",$E$6,0)+IF($K$6="YES",$I$6,0)),2)+(32*$E$8*IF($C$8="YES",1,0)) | I104: =ROUND((IF(32<=2,$AD$26,$AD$26+(32-2)*$AE$26))*(1+$C$6),2)+ROUND(ROUND((IF(32<=2,$AD$26,$AD$26+(32-2)*$AE$26))*(1+$C$6),2)*(IF($G$6="YES",$E$6,0)+IF($K$6="YES",$I$6,0)),2)
B105: 33 | C105: =ROUND((IF(33<=5,$AD$20,$AD$20+(33-5)*$AE$20))*(1+$C$6),2)+ROUND(ROUND((IF(33<=5,$AD$20,$AD$20+(33-5)*$AE$20))*(1+$C$6),2)*(IF($G$6="YES",$E$6,0)+IF($K$6="YES",$I$6,0)),2) | D105: =ROUND((IF(33<=15,$AD$21,$AD$21+(33-15)*$AE$21))*(1+$C$6),2)+ROUND(ROUND((IF(33<=15,$AD$21,$AD$21+(33-15)*$AE$21))*(1+$C$6),2)*(IF($G$6="YES",$E$6,0)+IF($K$6="YES",$I$6,0)),2) | E105: =ROUND((IF(33<=2,$AD$22,IF(33<=5,$AE$22,IF(33<=10,$AF$22,IF(33<=15,$AG$22,IF(33<=20,$AH$22,IF(33<=35,$AH$22+(33-20)*$AI$22,$AK$22+(33-35)*$AJ$22)))))))*(1+$C$6),2)+ROUND(ROUND((IF(33<=2,$AD$22,IF(33<=5,$AE$22,IF(33<=10,$AF$22,IF(33<=15,$AG$22,IF(33<=20,$AH$22,IF(33<=35,$AH$22+(33-20)*$AI$22,$AK$22+(33-35)*$AJ$22)))))))*(1+$C$6),2)*(IF($G$6="YES",$E$6,0)+IF($K$6="YES",$I$6,0)),2) | F105: =ROUND((IF(33<=2,$AD$23,IF(33<=5,$AE$23,IF(33<=10,$AF$23,IF(33<=15,$AG$23,IF(33<=20,$AH$23,IF(33<=35,$AH$23+(33-20)*$AI$23,$AK$23+(33-35)*$AJ$23)))))))*(1+$C$6),2)+ROUND(ROUND((IF(33<=2,$AD$23,IF(33<=5,$AE$23,IF(33<=10,$AF$23,IF(33<=15,$AG$23,IF(33<=20,$AH$23,IF(33<=35,$AH$23+(33-20)*$AI$23,$AK$23+(33-35)*$AJ$23)))))))*(1+$C$6),2)*(IF($G$6="YES",$E$6,0)+IF($K$6="YES",$I$6,0)),2) | G105: =ROUND((IF(33<=2,$AD$24,IF(33<=5,$AE$24,IF(33<=10,$AF$24,IF(33<=15,$AG$24,IF(33<=20,$AH$24,IF(33<=35,$AH$24+(33-20)*$AI$24,$AK$24+(33-35)*$AJ$24)))))))*(1+$C$6),2)+ROUND(ROUND((IF(33<=2,$AD$24,IF(33<=5,$AE$24,IF(33<=10,$AF$24,IF(33<=15,$AG$24,IF(33<=20,$AH$24,IF(33<=35,$AH$24+(33-20)*$AI$24,$AK$24+(33-35)*$AJ$24)))))))*(1+$C$6),2)*(IF($G$6="YES",$E$6,0)+IF($K$6="YES",$I$6,0)),2) | H105: =ROUND((IF(33<=2,$AD$25,$AD$25+(33-2)*$AE$25))*(1+$C$6),2)+ROUND(ROUND((IF(33<=2,$AD$25,$AD$25+(33-2)*$AE$25))*(1+$C$6),2)*(IF($G$6="YES",$E$6,0)+IF($K$6="YES",$I$6,0)),2)+(33*$E$8*IF($C$8="YES",1,0)) | I105: =ROUND((IF(33<=2,$AD$26,$AD$26+(33-2)*$AE$26))*(1+$C$6),2)+ROUND(ROUND((IF(33<=2,$AD$26,$AD$26+(33-2)*$AE$26))*(1+$C$6),2)*(IF($G$6="YES",$E$6,0)+IF($K$6="YES",$I$6,0)),2)
...

Sheet Volumetric Calculator
B2: VOLUMETRIC & PACKING CALCULATOR
B3: Check chargeable weight and indicative price for one or more parcels, compare against standard packaging sizes, or see what consolidating them into one box would cost.
B5: SETTINGS
B6: Price markup % (optional, on top of the quoted rate) | H6: 0 | I6: Round charge weight up once the decimal reaches | P6: 0.4
B8: Volumetric factor: Local/Priority (LPF/LPP) parcels divide L×W×H(cm) by 5000; Economy Road (ECO/ECOR) parcels divide by 4000. Chargeable weight is the greater of actual and volumetric weight, rounded per the rule above.
B10: A. YOUR PARCELS — enter dimensions (cm) and weight (kg); add a name if useful
B11: Item | C11: # | D11: L | E11: W | F11: H | G11: Actual kg | H11: Vol wt (/5000) | I11: Vol wt (/4000) | J11: Charge wt Local/PRI | K11: Charge wt ECO/R | L11: National-LPF | M11: National-LPP | N11: National-ECO | O11: National-ECOR | P11: Ecomms-LPF | Q11: Ecomms-LPP | R11: Ecomms-ECO | S11: Ecomms-ECOR | T11: Declared value | U11: Insurance premium (incl VAT)
B12: Item 1 | C12: 1 | D12: 1 | E12: 1 | F12: 1 | G12: 0.5 | H12: =IF(N(C12)>=1,(D12*E12*F12)/5000,"") | I12: =IF(N(C12)>=1,(D12*E12*F12)/4000,"") | J12: =IF(MOD(MAX(N(H12),N(C12)*N(G12)),1)>=$P$6,ROUNDUP(MAX(N(H12),N(C12)*N(G12)),0),ROUND(MAX(N(H12),N(C12)*N(G12)),0)) | K12: =IF(MOD(MAX(N(I12),N(C12)*N(G12)),1)>=$P$6,ROUNDUP(MAX(N(I12),N(C12)*N(G12)),0),ROUND(MAX(N(I12),N(C12)*N(G12)),0)) | L12: =IFERROR(VLOOKUP(J12,'Price Lookup (extended)'!$A$5:$Q$204,2,FALSE)*(1+$H$6),"-") | M12: =IFERROR(VLOOKUP(J12,'Price Lookup (extended)'!$A$5:$Q$204,4,FALSE)*(1+$H$6),"-") | N12: =IFERROR(VLOOKUP(K12,'Price Lookup (extended)'!$A$5:$Q$204,6,FALSE)*(1+$H$6),"-") | O12: =IFERROR(VLOOKUP(K12,'Price Lookup (extended)'!$A$5:$Q$204,8,FALSE)*(1+$H$6),"-") | P12: =IFERROR(VLOOKUP(J12,'Price Lookup (extended)'!$A$5:$Q$204,10,FALSE)*(1+$H$6),"-") | Q12: =IFERROR(VLOOKUP(J12,'Price Lookup (extended)'!$A$5:$Q$204,12,FALSE)*(1+$H$6),"-") | R12: =IFERROR(VLOOKUP(K12,'Price Lookup (extended)'!$A$5:$Q$204,14,FALSE)*(1+$H$6),"-") | S12: =IFERROR(VLOOKUP(K12,'Price Lookup (extended)'!$A$5:$Q$204,16,FALSE)*(1+$H$6),"-") | T12: 2000 | U12: =IF(OR('Rate Card'!$C$7="NO",N(T12)<=0),"-",MAX(MAX(0,N(T12)-'Rate Card'!$E$7)*'Rate Card'!$G$7*(1+'Rate Card'!$C$6),'Rate Card'!$I$7))
B13: Item 2 | C13: 2 | D13: 2 | E13: 2 | F13: 2 | G13: 0.5 | H13: =IF(N(C13)>=1,(D13*E13*F13)/5000,"") | I13: =IF(N(C13)>=1,(D13*E13*F13)/4000,"") | J13: =IF(MOD(MAX(N(H13),N(C13)*N(G13)),1)>=$P$6,ROUNDUP(MAX(N(H13),N(C13)*N(G13)),0),ROUND(MAX(N(H13),N(C13)*N(G13)),0)) | K13: =IF(MOD(MAX(N(I13),N(C13)*N(G13)),1)>=$P$6,ROUNDUP(MAX(N(I13),N(C13)*N(G13)),0),ROUND(MAX(N(I13),N(C13)*N(G13)),0)) | L13: =IFERROR(VLOOKUP(J13,'Price Lookup (extended)'!$A$5:$Q$204,2,FALSE)*(1+$H$6),"-") | M13: =IFERROR(VLOOKUP(J13,'Price Lookup (extended)'!$A$5:$Q$204,4,FALSE)*(1+$H$6),"-") | N13: =IFERROR(VLOOKUP(K13,'Price Lookup (extended)'!$A$5:$Q$204,6,FALSE)*(1+$H$6),"-") | O13: =IFERROR(VLOOKUP(K13,'Price Lookup (extended)'!$A$5:$Q$204,8,FALSE)*(1+$H$6),"-") | P13: =IFERROR(VLOOKUP(J13,'Price Lookup (extended)'!$A$5:$Q$204,10,FALSE)*(1+$H$6),"-") | Q13: =IFERROR(VLOOKUP(J13,'Price Lookup (extended)'!$A$5:$Q$204,12,FALSE)*(1+$H$6),"-") | R13: =IFERROR(VLOOKUP(K13,'Price Lookup (extended)'!$A$5:$Q$204,14,FALSE)*(1+$H$6),"-") | S13: =IFERROR(VLOOKUP(K13,'Price Lookup (extended)'!$A$5:$Q$204,16,FALSE)*(1+$H$6),"-") | T13: 2000 | U13: =IF(OR('Rate Card'!$C$7="NO",N(T13)<=0),"-",MAX(MAX(0,N(T13)-'Rate Card'!$E$7)*'Rate Card'!$G$7*(1+'Rate Card'!$C$6),'Rate Card'!$I$7))
B14: Item 3 | H14: =IF(N(C14)>=1,(D14*E14*F14)/5000,"") | I14: =IF(N(C14)>=1,(D14*E14*F14)/4000,"") | J14: =IF(MOD(MAX(N(H14),N(C14)*N(G14)),1)>=$P$6,ROUNDUP(MAX(N(H14),N(C14)*N(G14)),0),ROUND(MAX(N(H14),N(C14)*N(G14)),0)) | K14: =IF(MOD(MAX(N(I14),N(C14)*N(G14)),1)>=$P$6,ROUNDUP(MAX(N(I14),N(C14)*N(G14)),0),ROUND(MAX(N(I14),N(C14)*N(G14)),0)) | L14: =IFERROR(VLOOKUP(J14,'Price Lookup (extended)'!$A$5:$Q$204,2,FALSE)*(1+$H$6),"-") | M14: =IFERROR(VLOOKUP(J14,'Price Lookup (extended)'!$A$5:$Q$204,4,FALSE)*(1+$H$6),"-") | N14: =IFERROR(VLOOKUP(K14,'Price Lookup (extended)'!$A$5:$Q$204,6,FALSE)*(1+$H$6),"-") | O14: =IFERROR(VLOOKUP(K14,'Price Lookup (extended)'!$A$5:$Q$204,8,FALSE)*(1+$H$6),"-") | P14: =IFERROR(VLOOKUP(J14,'Price Lookup (extended)'!$A$5:$Q$204,10,FALSE)*(1+$H$6),"-") | Q14: =IFERROR(VLOOKUP(J14,'Price Lookup (extended)'!$A$5:$Q$204,12,FALSE)*(1+$H$6),"-") | R14: =IFERROR(VLOOKUP(K14,'Price Lookup (extended)'!$A$5:$Q$204,14,FALSE)*(1+$H$6),"-") | S14: =IFERROR(VLOOKUP(K14,'Price Lookup (extended)'!$A$5:$Q$204,16,FALSE)*(1+$H$6),"-") | U14: =IF(OR('Rate Card'!$C$7="NO",N(T14)<=0),"-",MAX(MAX(0,N(T14)-'Rate Card'!$E$7)*'Rate Card'!$G$7*(1+'Rate Card'!$C$6),'Rate Card'!$I$7))
B15: Item 4 | H15: =IF(N(C15)>=1,(D15*E15*F15)/5000,"") | I15: =IF(N(C15)>=1,(D15*E15*F15)/4000,"") | J15: =IF(MOD(MAX(N(H15),N(C15)*N(G15)),1)>=$P$6,ROUNDUP(MAX(N(H15),N(C15)*N(G15)),0),ROUND(MAX(N(H15),N(C15)*N(G15)),0)) | K15: =IF(MOD(MAX(N(I15),N(C15)*N(G15)),1)>=$P$6,ROUNDUP(MAX(N(I15),N(C15)*N(G15)),0),ROUND(MAX(N(I15),N(C15)*N(G15)),0)) | L15: =IFERROR(VLOOKUP(J15,'Price Lookup (extended)'!$A$5:$Q$204,2,FALSE)*(1+$H$6),"-") | M15: =IFERROR(VLOOKUP(J15,'Price Lookup (extended)'!$A$5:$Q$204,4,FALSE)*(1+$H$6),"-") | N15: =IFERROR(VLOOKUP(K15,'Price Lookup (extended)'!$A$5:$Q$204,6,FALSE)*(1+$H$6),"-") | O15: =IFERROR(VLOOKUP(K15,'Price Lookup (extended)'!$A$5:$Q$204,8,FALSE)*(1+$H$6),"-") | P15: =IFERROR(VLOOKUP(J15,'Price Lookup (extended)'!$A$5:$Q$204,10,FALSE)*(1+$H$6),"-") | Q15: =IFERROR(VLOOKUP(J15,'Price Lookup (extended)'!$A$5:$Q$204,12,FALSE)*(1+$H$6),"-") | R15: =IFERROR(VLOOKUP(K15,'Price Lookup (extended)'!$A$5:$Q$204,14,FALSE)*(1+$H$6),"-") | S15: =IFERROR(VLOOKUP(K15,'Price Lookup (extended)'!$A$5:$Q$204,16,FALSE)*(1+$H$6),"-") | U15: =IF(OR('Rate Card'!$C$7="NO",N(T15)<=0),"-",MAX(MAX(0,N(T15)-'Rate Card'!$E$7)*'Rate Card'!$G$7*(1+'Rate Card'!$C$6),'Rate Card'!$I$7))
B16: Item 5 | H16: =IF(N(C16)>=1,(D16*E16*F16)/5000,"") | I16: =IF(N(C16)>=1,(D16*E16*F16)/4000,"") | J16: =IF(MOD(MAX(N(H16),N(C16)*N(G16)),1)>=$P$6,ROUNDUP(MAX(N(H16),N(C16)*N(G16)),0),ROUND(MAX(N(H16),N(C16)*N(G16)),0)) | K16: =IF(MOD(MAX(N(I16),N(C16)*N(G16)),1)>=$P$6,ROUNDUP(MAX(N(I16),N(C16)*N(G16)),0),ROUND(MAX(N(I16),N(C16)*N(G16)),0)) | L16: =IFERROR(VLOOKUP(J16,'Price Lookup (extended)'!$A$5:$Q$204,2,FALSE)*(1+$H$6),"-") | M16: =IFERROR(VLOOKUP(J16,'Price Lookup (extended)'!$A$5:$Q$204,4,FALSE)*(1+$H$6),"-") | N16: =IFERROR(VLOOKUP(K16,'Price Lookup (extended)'!$A$5:$Q$204,6,FALSE)*(1+$H$6),"-") | O16: =IFERROR(VLOOKUP(K16,'Price Lookup (extended)'!$A$5:$Q$204,8,FALSE)*(1+$H$6),"-") | P16: =IFERROR(VLOOKUP(J16,'Price Lookup (extended)'!$A$5:$Q$204,10,FALSE)*(1+$H$6),"-") | Q16: =IFERROR(VLOOKUP(J16,'Price Lookup (extended)'!$A$5:$Q$204,12,FALSE)*(1+$H$6),"-") | R16: =IFERROR(VLOOKUP(K16,'Price Lookup (extended)'!$A$5:$Q$204,14,FALSE)*(1+$H$6),"-") | S16: =IFERROR(VLOOKUP(K16,'Price Lookup (extended)'!$A$5:$Q$204,16,FALSE)*(1+$H$6),"-") | U16: =IF(OR('Rate Card'!$C$7="NO",N(T16)<=0),"-",MAX(MAX(0,N(T16)-'Rate Card'!$E$7)*'Rate Card'!$G$7*(1+'Rate Card'!$C$6),'Rate Card'!$I$7))
B17: TOTAL | C17: =SUM(C12:C16) | G17: =SUMPRODUCT(C12:C16,G12:G16) | H17: =SUM(H12:H16) | I17: =SUM(I12:I16) | T17: =SUM(T12:T16)
B18: Insurance uses the rate/threshold/minimum set in Global Settings on the Rate Card sheet. Leave Declared value blank for items you don't want to insure.
B20: B. STANDARD PACKAGING OPTIONS — reference pricing for our standard box sizes
B21: Charge weight is the greater of this box's own volumetric weight and the real total weight entered in Section A ("Actual kg" TOTAL) — not the box's rated "Max kg", which is shown for reference only.
B22: Box | C22: L | D22: W | E22: H | F22: Max kg | G22: Vol wt (/5000) | H22: Vol wt (/4000) | I22: Charge wt Local/PRI | J22: Charge wt ECO/R | K22: National-LPF | L22: National-LPP | M22: National-ECO | N22: National-ECOR | O22: Ecomms-LPF | P22: Ecomms-LPP | Q22: Ecomms-ECO | R22: Ecomms-ECOR
B23: Flyer | C23: 40 | D23: 30 | E23: 5 | F23: 2 | G23: =(C23*D23*E23)/5000 | H23: =(C23*D23*E23)/4000 | I23: =IF(MOD(MAX(G23,F23,N($G$17)),1)>=$P$6,ROUNDUP(MAX(G23,F23,N($G$17)),0),ROUND(MAX(G23,F23,N($G$17)),0)) | J23: =IF(MOD(MAX(H23,F23,N($G$17)),1)>=$P$6,ROUNDUP(MAX(H23,F23,N($G$17)),0),ROUND(MAX(H23,F23,N($G$17)),0)) | K23: =IFERROR(VLOOKUP(I23,'Price Lookup (extended)'!$A$5:$Q$204,2,FALSE)*(1+$H$6),"-") | L23: =IFERROR(VLOOKUP(I23,'Price Lookup (extended)'!$A$5:$Q$204,4,FALSE)*(1+$H$6),"-") | M23: =IFERROR(VLOOKUP(J23,'Price Lookup (extended)'!$A$5:$Q$204,6,FALSE)*(1+$H$6),"-") | N23: =IFERROR(VLOOKUP(J23,'Price Lookup (extended)'!$A$5:$Q$204,8,FALSE)*(1+$H$6),"-") | O23: =IFERROR(VLOOKUP(I23,'Price Lookup (extended)'!$A$5:$Q$204,10,FALSE)*(1+$H$6),"-") | P23: =IFERROR(VLOOKUP(I23,'Price Lookup (extended)'!$A$5:$Q$204,12,FALSE)*(1+$H$6),"-") | Q23: =IFERROR(VLOOKUP(J23,'Price Lookup (extended)'!$A$5:$Q$204,14,FALSE)*(1+$H$6),"-") | R23: =IFERROR(VLOOKUP(J23,'Price Lookup (extended)'!$A$5:$Q$204,16,FALSE)*(1+$H$6),"-")
B24: Small (S) | C24: 60 | D24: 41 | E24: 8 | F24: 5 | G24: =(C24*D24*E24)/5000 | H24: =(C24*D24*E24)/4000 | I24: =IF(MOD(MAX(G24,F24,N($G$17)),1)>=$P$6,ROUNDUP(MAX(G24,F24,N($G$17)),0),ROUND(MAX(G24,F24,N($G$17)),0)) | J24: =IF(MOD(MAX(H24,F24,N($G$17)),1)>=$P$6,ROUNDUP(MAX(H24,F24,N($G$17)),0),ROUND(MAX(H24,F24,N($G$17)),0)) | K24: =IFERROR(VLOOKUP(I24,'Price Lookup (extended)'!$A$5:$Q$204,2,FALSE)*(1+$H$6),"-") | L24: =IFERROR(VLOOKUP(I24,'Price Lookup (extended)'!$A$5:$Q$204,4,FALSE)*(1+$H$6),"-") | M24: =IFERROR(VLOOKUP(J24,'Price Lookup (extended)'!$A$5:$Q$204,6,FALSE)*(1+$H$6),"-") | N24: =IFERROR(VLOOKUP(J24,'Price Lookup (extended)'!$A$5:$Q$204,8,FALSE)*(1+$H$6),"-") | O24: =IFERROR(VLOOKUP(I24,'Price Lookup (extended)'!$A$5:$Q$204,10,FALSE)*(1+$H$6),"-") | P24: =IFERROR(VLOOKUP(I24,'Price Lookup (extended)'!$A$5:$Q$204,12,FALSE)*(1+$H$6),"-") | Q24: =IFERROR(VLOOKUP(J24,'Price Lookup (extended)'!$A$5:$Q$204,14,FALSE)*(1+$H$6),"-") | R24: =IFERROR(VLOOKUP(J24,'Price Lookup (extended)'!$A$5:$Q$204,16,FALSE)*(1+$H$6),"-")
B25: Medium (M) | C25: 60 | D25: 41 | E25: 19 | F25: 10 | G25: =(C25*D25*E25)/5000 | H25: =(C25*D25*E25)/4000 | I25: =IF(MOD(MAX(G25,F25,N($G$17)),1)>=$P$6,ROUNDUP(MAX(G25,F25,N($G$17)),0),ROUND(MAX(G25,F25,N($G$17)),0)) | J25: =IF(MOD(MAX(H25,F25,N($G$17)),1)>=$P$6,ROUNDUP(MAX(H25,F25,N($G$17)),0),ROUND(MAX(H25,F25,N($G$17)),0)) | K25: =IFERROR(VLOOKUP(I25,'Price Lookup (extended)'!$A$5:$Q$204,2,FALSE)*(1+$H$6),"-") | L25: =IFERROR(VLOOKUP(I25,'Price Lookup (extended)'!$A$5:$Q$204,4,FALSE)*(1+$H$6),"-") | M25: =IFERROR(VLOOKUP(J25,'Price Lookup (extended)'!$A$5:$Q$204,6,FALSE)*(1+$H$6),"-") | N25: =IFERROR(VLOOKUP(J25,'Price Lookup (extended)'!$A$5:$Q$204,8,FALSE)*(1+$H$6),"-") | O25: =IFERROR(VLOOKUP(I25,'Price Lookup (extended)'!$A$5:$Q$204,10,FALSE)*(1+$H$6),"-") | P25: =IFERROR(VLOOKUP(I25,'Price Lookup (extended)'!$A$5:$Q$204,12,FALSE)*(1+$H$6),"-") | Q25: =IFERROR(VLOOKUP(J25,'Price Lookup (extended)'!$A$5:$Q$204,14,FALSE)*(1+$H$6),"-") | R25: =IFERROR(VLOOKUP(J25,'Price Lookup (extended)'!$A$5:$Q$204,16,FALSE)*(1+$H$6),"-")
B26: Large (L) | C26: 60 | D26: 41 | E26: 41 | F26: 15 | G26: =(C26*D26*E26)/5000 | H26: =(C26*D26*E26)/4000 | I26: =IF(MOD(MAX(G26,F26,N($G$17)),1)>=$P$6,ROUNDUP(MAX(G26,F26,N($G$17)),0),ROUND(MAX(G26,F26,N($G$17)),0)) | J26: =IF(MOD(MAX(H26,F26,N($G$17)),1)>=$P$6,ROUNDUP(MAX(H26,F26,N($G$17)),0),ROUND(MAX(H26,F26,N($G$17)),0)) | K26: =IFERROR(VLOOKUP(I26,'Price Lookup (extended)'!$A$5:$Q$204,2,FALSE)*(1+$H$6),"-") | L26: =IFERROR(VLOOKUP(I26,'Price Lookup (extended)'!$A$5:$Q$204,4,FALSE)*(1+$H$6),"-") | M26: =IFERROR(VLOOKUP(J26,'Price Lookup (extended)'!$A$5:$Q$204,6,FALSE)*(1+$H$6),"-") | N26: =IFERROR(VLOOKUP(J26,'Price Lookup (extended)'!$A$5:$Q$204,8,FALSE)*(1+$H$6),"-") | O26: =IFERROR(VLOOKUP(I26,'Price Lookup (extended)'!$A$5:$Q$204,10,FALSE)*(1+$H$6),"-") | P26: =IFERROR(VLOOKUP(I26,'Price Lookup (extended)'!$A$5:$Q$204,12,FALSE)*(1+$H$6),"-") | Q26: =IFERROR(VLOOKUP(J26,'Price Lookup (extended)'!$A$5:$Q$204,14,FALSE)*(1+$H$6),"-") | R26: =IFERROR(VLOOKUP(J26,'Price Lookup (extended)'!$A$5:$Q$204,16,FALSE)*(1+$H$6),"-")
B27: Extra-Large (XL) | C27: 60 | D27: 41 | E27: 69 | F27: 20 | G27: =(C27*D27*E27)/5000 | H27: =(C27*D27*E27)/4000 | I27: =IF(MOD(MAX(G27,F27,N($G$17)),1)>=$P$6,ROUNDUP(MAX(G27,F27,N($G$17)),0),ROUND(MAX(G27,F27,N($G$17)),0)) | J27: =IF(MOD(MAX(H27,F27,N($G$17)),1)>=$P$6,ROUNDUP(MAX(H27,F27,N($G$17)),0),ROUND(MAX(H27,F27,N($G$17)),0)) | K27: =IFERROR(VLOOKUP(I27,'Price Lookup (extended)'!$A$5:$Q$204,2,FALSE)*(1+$H$6),"-") | L27: =IFERROR(VLOOKUP(I27,'Price Lookup (extended)'!$A$5:$Q$204,4,FALSE)*(1+$H$6),"-") | M27: =IFERROR(VLOOKUP(J27,'Price Lookup (extended)'!$A$5:$Q$204,6,FALSE)*(1+$H$6),"-") | N27: =IFERROR(VLOOKUP(J27,'Price Lookup (extended)'!$A$5:$Q$204,8,FALSE)*(1+$H$6),"-") | O27: =IFERROR(VLOOKUP(I27,'Price Lookup (extended)'!$A$5:$Q$204,10,FALSE)*(1+$H$6),"-") | P27: =IFERROR(VLOOKUP(I27,'Price Lookup (extended)'!$A$5:$Q$204,12,FALSE)*(1+$H$6),"-") | Q27: =IFERROR(VLOOKUP(J27,'Price Lookup (extended)'!$A$5:$Q$204,14,FALSE)*(1+$H$6),"-") | R27: =IFERROR(VLOOKUP(J27,'Price Lookup (extended)'!$A$5:$Q$204,16,FALSE)*(1+$H$6),"-")
B30: C. CONSOLIDATED BOX — what would it cost to pack Section A's items into one box?
B31: Box size = the largest length/width/height needed across Section A's items, plus 2cm clearance on each dimension. Weight and declared value default to the totals from Section A — overwrite Declared value below if the consolidated shipment should be insured for a different amount.
C32: L | D32: W | E32: H | F32: Total kg | G32: Vol wt (/5000) | H32: Vol wt (/4000) | I32: Charge wt Local/PRI | J32: Charge wt ECO/R | K32: National-LPF | L32: National-LPP | M32: National-ECO | N32: National-ECOR | O32: Ecomms-LPF | P32: Ecomms-LPP | Q32: Ecomms-ECO | R32: Ecomms-ECOR | S32: Declared value | T32: Insurance premium (incl VAT)
B33: Consolidated box | C33: =IFERROR(MAX(D12:D16)+2,"") | D33: =IFERROR(MAX(E12:E16)+2,"") | E33: =IFERROR(MAX(F12:F16)+2,"") | F33: =$G$17 | G33: =IF($C$17>=1,(C33*D33*E33)/5000,"") | H33: =IF($C$17>=1,(C33*D33*E33)/4000,"") | I33: =IF(MOD(MAX(N(G33),F33),1)>=$P$6,ROUNDUP(MAX(N(G33),F33),0),ROUND(MAX(N(G33),F33),0)) | J33: =IF(MOD(MAX(N(H33),F33),1)>=$P$6,ROUNDUP(MAX(N(H33),F33),0),ROUND(MAX(N(H33),F33),0)) | K33: =IFERROR(VLOOKUP(I33,'Price Lookup (extended)'!$A$5:$Q$204,2,FALSE)*(1+$H$6),"-") | L33: =IFERROR(VLOOKUP(I33,'Price Lookup (extended)'!$A$5:$Q$204,4,FALSE)*(1+$H$6),"-") | M33: =IFERROR(VLOOKUP(J33,'Price Lookup (extended)'!$A$5:$Q$204,6,FALSE)*(1+$H$6),"-") | N33: =IFERROR(VLOOKUP(J33,'Price Lookup (extended)'!$A$5:$Q$204,8,FALSE)*(1+$H$6),"-") | O33: =IFERROR(VLOOKUP(I33,'Price Lookup (extended)'!$A$5:$Q$204,10,FALSE)*(1+$H$6),"-") | P33: =IFERROR(VLOOKUP(I33,'Price Lookup (extended)'!$A$5:$Q$204,12,FALSE)*(1+$H$6),"-") | Q33: =IFERROR(VLOOKUP(J33,'Price Lookup (extended)'!$A$5:$Q$204,14,FALSE)*(1+$H$6),"-") | R33: =IFERROR(VLOOKUP(J33,'Price Lookup (extended)'!$A$5:$Q$204,16,FALSE)*(1+$H$6),"-") | S33: =$T$17 | T33: =IF(OR('Rate Card'!$C$7="NO",N(S33)<=0),"-",MAX(MAX(0,N(S33)-'Rate Card'!$E$7)*'Rate Card'!$G$7*(1+'Rate Card'!$C$6),'Rate Card'!$I$7))
B35: D. LOCKER SIZE REFERENCE — recommended parcel size to fit each PUDO locker
B36: Locker size | C36: Locker inside (L) | D36: Locker inside (W) | E36: Locker inside (H) | F36: Max kg | G36: Recommended parcel L (locker - 2cm) | H36: Recommended parcel W (locker - 2cm) | I36: Recommended parcel H (locker - 2cm)
B37: Extra Small | C37: 60 | D37: 17 | E37: 8 | F37: 2 | G37: =C37-2 | H37: =D37-2 | I37: =E37-2
B38: Small | C38: 60 | D38: 41 | E38: 8 | F38: 5 | G38: =C38-2 | H38: =D38-2 | I38: =E38-2
B39: Medium | C39: 60 | D39: 41 | E39: 19 | F39: 10 | G39: =C39-2 | H39: =D39-2 | I39: =E39-2
B40: Large | C40: 60 | D40: 41 | E40: 41 | F40: 15 | G40: =C40-2 | H40: =D40-2 | I40: =E40-2
B41: Extra-Large (XL) | C41: 60 | D41: 41 | E41: 69 | F41: 20 | G41: =C41-2 | H41: =D41-2 | I41: =E41-2
B42: See the 'Rate Card' sheet for locker pricing (Locker<->Locker, Locker<->Door, etc.).

Sheet Price Lookup (extended)
A1: Price Lookup (extended) — internal helper sheet, feeds the Volumetric Calculator
A2: Do not edit here. Every price below is a formula pointing at the 'Rate Card' sheet's hidden source-input cells, extended out to 200kg so the calculator can look up heavy or bulky consolidated shipments. LPF/LPP are blank beyond 35kg because the rate cards say to use the ECO/ECOR rate at that point instead (shown in the next columns).
A4: Kg | B4: NAT-LPF-excl | C4: NAT-LPF-incl | D4: NAT-LPP-excl | E4: NAT-LPP-incl | F4: NAT-ECO-excl | G4: NAT-ECO-incl | H4: NAT-ECOR-excl | I4: NAT-ECOR-incl | J4: ECO-LPF-excl | K4: ECO-LPF-incl | L4: ECO-LPP-excl | M4: ECO-LPP-incl | N4: ECO-ECO-excl | O4: ECO-ECO-incl | P4: ECO-ECOR-excl | Q4: ECO-ECOR-incl
A5: 1 | B5: =IF(1<=5,'Rate Card'!$AD$20,'Rate Card'!$AD$20+(1-5)*'Rate Card'!$AE$20) | C5: =ROUND((IF(1<=5,'Rate Card'!$AD$20,'Rate Card'!$AD$20+(1-5)*'Rate Card'!$AE$20))*(1+'Rate Card'!$C$6),2)+ROUND(ROUND((IF(1<=5,'Rate Card'!$AD$20,'Rate Card'!$AD$20+(1-5)*'Rate Card'!$AE$20))*(1+'Rate Card'!$C$6),2)*(IF('Rate Card'!$G$6="YES",'Rate Card'!$E$6,0)+IF('Rate Card'!$K$6="YES",'Rate Card'!$I$6,0)),2) | D5: =IF(1<=15,'Rate Card'!$AD$21,'Rate Card'!$AD$21+(1-15)*'Rate Card'!$AE$21) | E5: =ROUND((IF(1<=15,'Rate Card'!$AD$21,'Rate Card'!$AD$21+(1-15)*'Rate Card'!$AE$21))*(1+'Rate Card'!$C$6),2)+ROUND(ROUND((IF(1<=15,'Rate Card'!$AD$21,'Rate Card'!$AD$21+(1-15)*'Rate Card'!$AE$21))*(1+'Rate Card'!$C$6),2)*(IF('Rate Card'!$G$6="YES",'Rate Card'!$E$6,0)+IF('Rate Card'!$K$6="YES",'Rate Card'!$I$6,0)),2) | F5: =IF(1<=2,'Rate Card'!$AD$22,IF(1<=5,'Rate Card'!$AE$22,IF(1<=10,'Rate Card'!$AF$22,IF(1<=15,'Rate Card'!$AG$22,IF(1<=20,'Rate Card'!$AH$22,IF(1<=35,'Rate Card'!$AH$22+(1-20)*'Rate Card'!$AI$22,'Rate Card'!$AK$22+(1-35)*'Rate Card'!$AJ$22)))))) | G5: =ROUND((IF(1<=2,'Rate Card'!$AD$22,IF(1<=5,'Rate Card'!$AE$22,IF(1<=10,'Rate Card'!$AF$22,IF(1<=15,'Rate Card'!$AG$22,IF(1<=20,'Rate Card'!$AH$22,IF(1<=35,'Rate Card'!$AH$22+(1-20)*'Rate Card'!$AI$22,'Rate Card'!$AK$22+(1-35)*'Rate Card'!$AJ$22)))))))*(1+'Rate Card'!$C$6),2)+ROUND(ROUND((IF(1<=2,'Rate Card'!$AD$22,IF(1<=5,'Rate Card'!$AE$22,IF(1<=10,'Rate Card'!$AF$22,IF(1<=15,'Rate Card'!$AG$22,IF(1<=20,'Rate Card'!$AH$22,IF(1<=35,'Rate Card'!$AH$22+(1-20)*'Rate Card'!$AI$22,'Rate Card'!$AK$22+(1-35)*'Rate Card'!$AJ$22)))))))*(1+'Rate Card'!$C$6),2)*(IF('Rate Card'!$G$6="YES",'Rate Card'!$E$6,0)+IF('Rate Card'!$K$6="YES",'Rate Card'!$I$6,0)),2) | H5: =IF(1<=2,'Rate Card'!$AD$23,IF(1<=5,'Rate Card'!$AE$23,IF(1<=10,'Rate Card'!$AF$23,IF(1<=15,'Rate Card'!$AG$23,IF(1<=20,'Rate Card'!$AH$23,IF(1<=35,'Rate Card'!$AH$23+(1-20)*'Rate Card'!$AI$23,'Rate Card'!$AK$23+(1-35)*'Rate Card'!$AJ$23)))))) | I5: =ROUND((IF(1<=2,'Rate Card'!$AD$23,IF(1<=5,'Rate Card'!$AE$23,IF(1<=10,'Rate Card'!$AF$23,IF(1<=15,'Rate Card'!$AG$23,IF(1<=20,'Rate Card'!$AH$23,IF(1<=35,'Rate Card'!$AH$23+(1-20)*'Rate Card'!$AI$23,'Rate Card'!$AK$23+(1-35)*'Rate Card'!$AJ$23)))))))*(1+'Rate Card'!$C$6),2)+ROUND(ROUND((IF(1<=2,'Rate Card'!$AD$23,IF(1<=5,'Rate Card'!$AE$23,IF(1<=10,'Rate Card'!$AF$23,IF(1<=15,'Rate Card'!$AG$23,IF(1<=20,'Rate Card'!$AH$23,IF(1<=35,'Rate Card'!$AH$23+(1-20)*'Rate Card'!$AI$23,'Rate Card'!$AK$23+(1-35)*'Rate Card'!$AJ$23)))))))*(1+'Rate Card'!$C$6),2)*(IF('Rate Card'!$G$6="YES",'Rate Card'!$E$6,0)+IF('Rate Card'!$K$6="YES",'Rate Card'!$I$6,0)),2) | J5: =IF(1<=5,'Rate Card'!$AD$117,'Rate Card'!$AD$117+(1-5)*'Rate Card'!$AE$117) | K5: =ROUND((IF(1<=5,'Rate Card'!$AD$117,'Rate Card'!$AD$117+(1-5)*'Rate Card'!$AE$117))*(1+'Rate Card'!$C$6),2)+ROUND(ROUND((IF(1<=5,'Rate Card'!$AD$117,'Rate Card'!$AD$117+(1-5)*'Rate Card'!$AE$117))*(1+'Rate Card'!$C$6),2)*(IF('Rate Card'!$G$6="YES",'Rate Card'!$E$6,0)+IF('Rate Card'!$K$6="YES",'Rate Card'!$I$6,0)),2) | L5: =IF(1<=15,'Rate Card'!$AD$118,'Rate Card'!$AD$118+(1-15)*'Rate Card'!$AE$118) | M5: =ROUND((IF(1<=15,'Rate Card'!$AD$118,'Rate Card'!$AD$118+(1-15)*'Rate Card'!$AE$118))*(1+'Rate Card'!$C$6),2)+ROUND(ROUND((IF(1<=15,'Rate Card'!$AD$118,'Rate Card'!$AD$118+(1-15)*'Rate Card'!$AE$118))*(1+'Rate Card'!$C$6),2)*(IF('Rate Card'!$G$6="YES",'Rate Card'!$E$6,0)+IF('Rate Card'!$K$6="YES",'Rate Card'!$I$6,0)),2) | N5: =IF(1<=2,'Rate Card'!$AD$119,IF(1<=5,'Rate Card'!$AE$119,IF(1<=10,'Rate Card'!$AF$119,IF(1<=15,'Rate Card'!$AG$119,IF(1<=20,'Rate Card'!$AH$119,IF(1<=35,'Rate Card'!$AH$119+(1-20)*'Rate Card'!$AI$119,'Rate Card'!$AK$119+(1-35)*'Rate Card'!$AJ$119)))))) | O5: =ROUND((IF(1<=2,'Rate Card'!$AD$119,IF(1<=5,'Rate Card'!$AE$119,IF(1<=10,'Rate Card'!$AF$119,IF(1<=15,'Rate Card'!$AG$119,IF(1<=20,'Rate Card'!$AH$119,IF(1<=35,'Rate Card'!$AH$119+(1-20)*'Rate Card'!$AI$119,'Rate Card'!$AK$119+(1-35)*'Rate Card'!$AJ$119)))))))*(1+'Rate Card'!$C$6),2)+ROUND(ROUND((IF(1<=2,'Rate Card'!$AD$119,IF(1<=5,'Rate Card'!$AE$119,IF(1<=10,'Rate Card'!$AF$119,IF(1<=15,'Rate Card'!$AG$119,IF(1<=20,'Rate Card'!$AH$119,IF(1<=35,'Rate Card'!$AH$119+(1-20)*'Rate Card'!$AI$119,'Rate Card'!$AK$119+(1-35)*'Rate Card'!$AJ$119)))))))*(1+'Rate Card'!$C$6),2)*(IF('Rate Card'!$G$6="YES",'Rate Card'!$E$6,0)+IF('Rate Card'!$K$6="YES",'Rate Card'!$I$6,0)),2) | P5: =IF(1<=2,'Rate Card'!$AD$120,IF(1<=5,'Rate Card'!$AE$120,IF(1<=10,'Rate Card'!$AF$120,IF(1<=15,'Rate Card'!$AG$120,IF(1<=20,'Rate Card'!$AH$120,IF(1<=35,'Rate Card'!$AH$120+(1-20)*'Rate Card'!$AI$120,'Rate Card'!$AK$120+(1-35)*'Rate Card'!$AJ$120)))))) | Q5: =ROUND((IF(1<=2,'Rate Card'!$AD$120,IF(1<=5,'Rate Card'!$AE$120,IF(1<=10,'Rate Card'!$AF$120,IF(1<=15,'Rate Card'!$AG$120,IF(1<=20,'Rate Card'!$AH$120,IF(1<=35,'Rate Card'!$AH$120+(1-20)*'Rate Card'!$AI$120,'Rate Card'!$AK$120+(1-35)*'Rate Card'!$AJ$120)))))))*(1+'Rate Card'!$C$6),2)+ROUND(ROUND((IF(1<=2,'Rate Card'!$AD$120,IF(1<=5,'Rate Card'!$AE$120,IF(1<=10,'Rate Card'!$AF$120,IF(1<=15,'Rate Card'!$AG$120,IF(1<=20,'Rate Card'!$AH$120,IF(1<=35,'Rate Card'!$AH$120+(1-20)*'Rate Card'!$AI$120,'Rate Card'!$AK$120+(1-35)*'Rate Card'!$AJ$120)))))))*(1+'Rate Card'!$C$6),2)*(IF('Rate Card'!$G$6="YES",'Rate Card'!$E$6,0)+IF('Rate Card'!$K$6="YES",'Rate Card'!$I$6,0)),2)
A6: 2 | B6: =IF(2<=5,'Rate Card'!$AD$20,'Rate Card'!$AD$20+(2-5)*'Rate Card'!$AE$20) | C6: =ROUND((IF(2<=5,'Rate Card'!$AD$20,'Rate Card'!$AD$20+(2-5)*'Rate Card'!$AE$20))*(1+'Rate Card'!$C$6),2)+ROUND(ROUND((IF(2<=5,'Rate Card'!$AD$20,'Rate Card'!$AD$20+(2-5)*'Rate Card'!$AE$20))*(1+'Rate Card'!$C$6),2)*(IF('Rate Card'!$G$6="YES",'Rate Card'!$E$6,0)+IF('Rate Card'!$K$6="YES",'Rate Card'!$I$6,0)),2) | D6: =IF(2<=15,'Rate Card'!$AD$21,'Rate Card'!$AD$21+(2-15)*'Rate Card'!$AE$21) | E6: =ROUND((IF(2<=15,'Rate Card'!$AD$21,'Rate Card'!$AD$21+(2-15)*'Rate Card'!$AE$21))*(1+'Rate Card'!$C$6),2)+ROUND(ROUND((IF(2<=15,'Rate Card'!$AD$21,'Rate Card'!$AD$21+(2-15)*'Rate Card'!$AE$21))*(1+'Rate Card'!$C$6),2)*(IF('Rate Card'!$G$6="YES",'Rate Card'!$E$6,0)+IF('Rate Card'!$K$6="YES",'Rate Card'!$I$6,0)),2) | F6: =IF(2<=2,'Rate Card'!$AD$22,IF(2<=5,'Rate Card'!$AE$22,IF(2<=10,'Rate Card'!$AF$22,IF(2<=15,'Rate Card'!$AG$22,IF(2<=20,'Rate Card'!$AH$22,IF(2<=35,'Rate Card'!$AH$22+(2-20)*'Rate Card'!$AI$22,'Rate Card'!$AK$22+(2-35)*'Rate Card'!$AJ$22)))))) | G6: =ROUND((IF(2<=2,'Rate Card'!$AD$22,IF(2<=5,'Rate Card'!$AE$22,IF(2<=10,'Rate Card'!$AF$22,IF(2<=15,'Rate Card'!$AG$22,IF(2<=20,'Rate Card'!$AH$22,IF(2<=35,'Rate Card'!$AH$22+(2-20)*'Rate Card'!$AI$22,'Rate Card'!$AK$22+(2-35)*'Rate Card'!$AJ$22)))))))*(1+'Rate Card'!$C$6),2)+ROUND(ROUND((IF(2<=2,'Rate Card'!$AD$22,IF(2<=5,'Rate Card'!$AE$22,IF(2<=10,'Rate Card'!$AF$22,IF(2<=15,'Rate Card'!$AG$22,IF(2<=20,'Rate Card'!$AH$22,IF(2<=35,'Rate Card'!$AH$22+(2-20)*'Rate Card'!$AI$22,'Rate Card'!$AK$22+(2-35)*'Rate Card'!$AJ$22)))))))*(1+'Rate Card'!$C$6),2)*(IF('Rate Card'!$G$6="YES",'Rate Card'!$E$6,0)+IF('Rate Card'!$K$6="YES",'Rate Card'!$I$6,0)),2) | H6: =IF(2<=2,'Rate Card'!$AD$23,IF(2<=5,'Rate Card'!$AE$23,IF(2<=10,'Rate Card'!$AF$23,IF(2<=15,'Rate Card'!$AG$23,IF(2<=20,'Rate Card'!$AH$23,IF(2<=35,'Rate Card'!$AH$23+(2-20)*'Rate Card'!$AI$23,'Rate Card'!$AK$23+(2-35)*'Rate Card'!$AJ$23)))))) | I6: =ROUND((IF(2<=2,'Rate Card'!$AD$23,IF(2<=5,'Rate Card'!$AE$23,IF(2<=10,'Rate Card'!$AF$23,IF(2<=15,'Rate Card'!$AG$23,IF(2<=20,'Rate Card'!$AH$23,IF(2<=35,'Rate Card'!$AH$23+(2-20)*'Rate Card'!$AI$23,'Rate Card'!$AK$23+(2-35)*'Rate Card'!$AJ$23)))))))*(1+'Rate Card'!$C$6),2)+ROUND(ROUND((IF(2<=2,'Rate Card'!$AD$23,IF(2<=5,'Rate Card'!$AE$23,IF(2<=10,'Rate Card'!$AF$23,IF(2<=15,'Rate Card'!$AG$23,IF(2<=20,'Rate Card'!$AH$23,IF(2<=35,'Rate Card'!$AH$23+(2-20)*'Rate Card'!$AI$23,'Rate Card'!$AK$23+(2-35)*'Rate Card'!$AJ$23)))))))*(1+'Rate Card'!$C$6),2)*(IF('Rate Card'!$G$6="YES",'Rate Card'!$E$6,0)+IF('Rate Card'!$K$6="YES",'Rate Card'!$I$6,0)),2) | J6: =IF(2<=5,'Rate Card'!$AD$117,'Rate Card'!$AD$117+(2-5)*'Rate Card'!$AE$117) | K6: =ROUND((IF(2<=5,'Rate Card'!$AD$117,'Rate Card'!$AD$117+(2-5)*'Rate Card'!$AE$117))*(1+'Rate Card'!$C$6),2)+ROUND(ROUND((IF(2<=5,'Rate Card'!$AD$117,'Rate Card'!$AD$117+(2-5)*'Rate Card'!$AE$117))*(1+'Rate Card'!$C$6),2)*(IF('Rate Card'!$G$6="YES",'Rate Card'!$E$6,0)+IF('Rate Card'!$K$6="YES",'Rate Card'!$I$6,0)),2) | L6: =IF(2<=15,'Rate Card'!$AD$118,'Rate Card'!$AD$118+(2-15)*'Rate Card'!$AE$118) | M6: =ROUND((IF(2<=15,'Rate Card'!$AD$118,'Rate Card'!$AD$118+(2-15)*'Rate Card'!$AE$118))*(1+'Rate Card'!$C$6),2)+ROUND(ROUND((IF(2<=15,'Rate Card'!$AD$118,'Rate Card'!$AD$118+(2-15)*'Rate Card'!$AE$118))*(1+'Rate Card'!$C$6),2)*(IF('Rate Card'!$G$6="YES",'Rate Card'!$E$6,0)+IF('Rate Card'!$K$6="YES",'Rate Card'!$I$6,0)),2) | N6: =IF(2<=2,'Rate Card'!$AD$119,IF(2<=5,'Rate Card'!$AE$119,IF(2<=10,'Rate Card'!$AF$119,IF(2<=15,'Rate Card'!$AG$119,IF(2<=20,'Rate Card'!$AH$119,IF(2<=35,'Rate Card'!$AH$119+(2-20)*'Rate Card'!$AI$119,'Rate Card'!$AK$119+(2-35)*'Rate Card'!$AJ$119)))))) | O6: =ROUND((IF(2<=2,'Rate Card'!$AD$119,IF(2<=5,'Rate Card'!$AE$119,IF(2<=10,'Rate Card'!$AF$119,IF(2<=15,'Rate Card'!$AG$119,IF(2<=20,'Rate Card'!$AH$119,IF(2<=35,'Rate Card'!$AH$119+(2-20)*'Rate Card'!$AI$119,'Rate Card'!$AK$119+(2-35)*'Rate Card'!$AJ$119)))))))*(1+'Rate Card'!$C$6),2)+ROUND(ROUND((IF(2<=2,'Rate Card'!$AD$119,IF(2<=5,'Rate Card'!$AE$119,IF(2<=10,'Rate Card'!$AF$119,IF(2<=15,'Rate Card'!$AG$119,IF(2<=20,'Rate Card'!$AH$119,IF(2<=35,'Rate Card'!$AH$119+(2-20)*'Rate Card'!$AI$119,'Rate Card'!$AK$119+(2-35)*'Rate Card'!$AJ$119)))))))*(1+'Rate Card'!$C$6),2)*(IF('Rate Card'!$G$6="YES",'Rate Card'!$E$6,0)+IF('Rate Card'!$K$6="YES",'Rate Card'!$I$6,0)),2) | P6: =IF(2<=2,'Rate Card'!$AD$120,IF(2<=5,'Rate Card'!$AE$120,IF(2<=10,'Rate Card'!$AF$120,IF(2<=15,'Rate Card'!$AG$120,IF(2<=20,'Rate Card'!$AH$120,IF(2<=35,'Rate Card'!$AH$120+(2-20)*'Rate Card'!$AI$120,'Rate Card'!$AK$120+(2-35)*'Rate Card'!$AJ$120)))))) | Q6: =ROUND((IF(2<=2,'Rate Card'!$AD$120,IF(2<=5,'Rate Card'!$AE$120,IF(2<=10,'Rate Card'!$AF$120,IF(2<=15,'Rate Card'!$AG$120,IF(2<=20,'Rate Card'!$AH$120,IF(2<=35,'Rate Card'!$AH$120+(2-20)*'Rate Card'!$AI$120,'Rate Card'!$AK$120+(2-35)*'Rate Card'!$AJ$120)))))))*(1+'Rate Card'!$C$6),2)+ROUND(ROUND((IF(2<=2,'Rate Card'!$AD$120,IF(2<=5,'Rate Card'!$AE$120,IF(2<=10,'Rate Card'!$AF$120,IF(2<=15,'Rate Card'!$AG$120,IF(2<=20,'Rate Card'!$AH$120,IF(2<=35,'Rate Card'!$AH$120+(2-20)*'Rate Card'!$AI$120,'Rate Card'!$AK$120+(2-35)*'Rate Card'!$AJ$120)))))))*(1+'Rate Card'!$C$6),2)*(IF('Rate Card'!$G$6="YES",'Rate Card'!$E$6,0)+IF('Rate Card'!$K$6="YES",'Rate Card'!$I$6,0)),2)
A7: 3 | B7: =IF(3<=5,'Rate Card'!$AD$20,'Rate Card'!$AD$20+(3-5)*'Rate Card'!$AE$20) | C7: =ROUND((IF(3<=5,'Rate Card'!$AD$20,'Rate Card'!$AD$20+(3-5)*'Rate Card'!$AE$20))*(1+'Rate Card'!$C$6),2)+ROUND(ROUND((IF(3<=5,'Rate Card'!$AD$20,'Rate Card'!$AD$20+(3-5)*'Rate Card'!$AE$20))*(1+'Rate Card'!$C$6),2)*(IF('Rate Card'!$G$6="YES",'Rate Card'!$E$6,0)+IF('Rate Card'!$K$6="YES",'Rate Card'!$I$6,0)),2) | D7: =IF(3<=15,'Rate Card'!$AD$21,'Rate Card'!$AD$21+(3-15)*'Rate Card'!$AE$21) | E7: =ROUND((IF(3<=15,'Rate Card'!$AD$21,'Rate Card'!$AD$21+(3-15)*'Rate Card'!$AE$21))*(1+'Rate Card'!$C$6),2)+ROUND(ROUND((IF(3<=15,'Rate Card'!$AD$21,'Rate Card'!$AD$21+(3-15)*'Rate Card'!$AE$21))*(1+'Rate Card'!$C$6),2)*(IF('Rate Card'!$G$6="YES",'Rate Card'!$E$6,0)+IF('Rate Card'!$K$6="YES",'Rate Card'!$I$6,0)),2) | F7: =IF(3<=2,'Rate Card'!$AD$22,IF(3<=5,'Rate Card'!$AE$22,IF(3<=10,'Rate Card'!$AF$22,IF(3<=15,'Rate Card'!$AG$22,IF(3<=20,'Rate Card'!$AH$22,IF(3<=35,'Rate Card'!$AH$22+(3-20)*'Rate Card'!$AI$22,'Rate Card'!$AK$22+(3-35)*'Rate Card'!$AJ$22)))))) | G7: =ROUND((IF(3<=2,'Rate Card'!$AD$22,IF(3<=5,'Rate Card'!$AE$22,IF(3<=10,'Rate Card'!$AF$22,IF(3<=15,'Rate Card'!$AG$22,IF(3<=20,'Rate Card'!$AH$22,IF(3<=35,'Rate Card'!$AH$22+(3-20)*'Rate Card'!$AI$22,'Rate Card'!$AK$22+(3-35)*'Rate Card'!$AJ$22)))))))*(1+'Rate Card'!$C$6),2)+ROUND(ROUND((IF(3<=2,'Rate Card'!$AD$22,IF(3<=5,'Rate Card'!$AE$22,IF(3<=10,'Rate Card'!$AF$22,IF(3<=15,'Rate Card'!$AG$22,IF(3<=20,'Rate Card'!$AH$22,IF(3<=35,'Rate Card'!$AH$22+(3-20)*'Rate Card'!$AI$22,'Rate Card'!$AK$22+(3-35)*'Rate Card'!$AJ$22)))))))*(1+'Rate Card'!$C$6),2)*(IF('Rate Card'!$G$6="YES",'Rate Card'!$E$6,0)+IF('Rate Card'!$K$6="YES",'Rate Card'!$I$6,0)),2) | H7: =IF(3<=2,'Rate Card'!$AD$23,IF(3<=5,'Rate Card'!$AE$23,IF(3<=10,'Rate Card'!$AF$23,IF(3<=15,'Rate Card'!$AG$23,IF(3<=20,'Rate Card'!$AH$23,IF(3<=35,'Rate Card'!$AH$23+(3-20)*'Rate Card'!$AI$23,'Rate Card'!$AK$23+(3-35)*'Rate Card'!$AJ$23)))))) | I7: =ROUND((IF(3<=2,'Rate Card'!$AD$23,IF(3<=5,'Rate Card'!$AE$23,IF(3<=10,'Rate Card'!$AF$23,IF(3<=15,'Rate Card'!$AG$23,IF(3<=20,'Rate Card'!$AH$23,IF(3<=35,'Rate Card'!$AH$23+(3-20)*'Rate Card'!$AI$23,'Rate Card'!$AK$23+(3-35)*'Rate Card'!$AJ$23)))))))*(1+'Rate Card'!$C$6),2)+ROUND(ROUND((IF(3<=2,'Rate Card'!$AD$23,IF(3<=5,'Rate Card'!$AE$23,IF(3<=10,'Rate Card'!$AF$23,IF(3<=15,'Rate Card'!$AG$23,IF(3<=20,'Rate Card'!$AH$23,IF(3<=35,'Rate Card'!$AH$23+(3-20)*'Rate Card'!$AI$23,'Rate Card'!$AK$23+(3-35)*'Rate Card'!$AJ$23)))))))*(1+'Rate Card'!$C$6),2)*(IF('Rate Card'!$G$6="YES",'Rate Card'!$E$6,0)+IF('Rate Card'!$K$6="YES",'Rate Card'!$I$6,0)),2) | J7: =IF(3<=5,'Rate Card'!$AD$117,'Rate Card'!$AD$117+(3-5)*'Rate Card'!$AE$117) | K7: =ROUND((IF(3<=5,'Rate Card'!$AD$117,'Rate Card'!$AD$117+(3-5)*'Rate Card'!$AE$117))*(1+'Rate Card'!$C$6),2)+ROUND(ROUND((IF(3<=5,'Rate Card'!$AD$117,'Rate Card'!$AD$117+(3-5)*'Rate Card'!$AE$117))*(1+'Rate Card'!$C$6),2)*(IF('Rate Card'!$G$6="YES",'Rate Card'!$E$6,0)+IF('Rate Card'!$K$6="YES",'Rate Card'!$I$6,0)),2) | L7: =IF(3<=15,'Rate Card'!$AD$118,'Rate Card'!$AD$118+(3-15)*'Rate Card'!$AE$118) | M7: =ROUND((IF(3<=15,'Rate Card'!$AD$118,'Rate Card'!$AD$118+(3-15)*'Rate Card'!$AE$118))*(1+'Rate Card'!$C$6),2)+ROUND(ROUND((IF(3<=15,'Rate Card'!$AD$118,'Rate Card'!$AD$118+(3-15)*'Rate Card'!$AE$118))*(1+'Rate Card'!$C$6),2)*(IF('Rate Card'!$G$6="YES",'Rate Card'!$E$6,0)+IF('Rate Card'!$K$6="YES",'Rate Card'!$I$6,0)),2) | N7: =IF(3<=2,'Rate Card'!$AD$119,IF(3<=5,'Rate Card'!$AE$119,IF(3<=10,'Rate Card'!$AF$119,IF(3<=15,'Rate Card'!$AG$119,IF(3<=20,'Rate Card'!$AH$119,IF(3<=35,'Rate Card'!$AH$119+(3-20)*'Rate Card'!$AI$119,'Rate Card'!$AK$119+(3-35)*'Rate Card'!$AJ$119)))))) | O7: =ROUND((IF(3<=2,'Rate Card'!$AD$119,IF(3<=5,'Rate Card'!$AE$119,IF(3<=10,'Rate Card'!$AF$119,IF(3<=15,'Rate Card'!$AG$119,IF(3<=20,'Rate Card'!$AH$119,IF(3<=35,'Rate Card'!$AH$119+(3-20)*'Rate Card'!$AI$119,'Rate Card'!$AK$119+(3-35)*'Rate Card'!$AJ$119)))))))*(1+'Rate Card'!$C$6),2)+ROUND(ROUND((IF(3<=2,'Rate Card'!$AD$119,IF(3<=5,'Rate Card'!$AE$119,IF(3<=10,'Rate Card'!$AF$119,IF(3<=15,'Rate Card'!$AG$119,IF(3<=20,'Rate Card'!$AH$119,IF(3<=35,'Rate Card'!$AH$119+(3-20)*'Rate Card'!$AI$119,'Rate Card'!$AK$119+(3-35)*'Rate Card'!$AJ$119)))))))*(1+'Rate Card'!$C$6),2)*(IF('Rate Card'!$G$6="YES",'Rate Card'!$E$6,0)+IF('Rate Card'!$K$6="YES",'Rate Card'!$I$6,0)),2) | P7: =IF(3<=2,'Rate Card'!$AD$120,IF(3<=5,'Rate Card'!$AE$120,IF(3<=10,'Rate Card'!$AF$120,IF(3<=15,'Rate Card'!$AG$120,IF(3<=20,'Rate Card'!$AH$120,IF(3<=35,'Rate Card'!$AH$120+(3-20)*'Rate Card'!$AI$120,'Rate Card'!$AK$120+(3-35)*'Rate Card'!$AJ$120)))))) | Q7: =ROUND((IF(3<=2,'Rate Card'!$AD$120,IF(3<=5,'Rate Card'!$AE$120,IF(3<=10,'Rate Card'!$AF$120,IF(3<=15,'Rate Card'!$AG$120,IF(3<=20,'Rate Card'!$AH$120,IF(3<=35,'Rate Card'!$AH$120+(3-20)*'Rate Card'!$AI$120,'Rate Card'!$AK$120+(3-35)*'Rate Card'!$AJ$120)))))))*(1+'Rate Card'!$C$6),2)+ROUND(ROUND((IF(3<=2,'Rate Card'!$AD$120,IF(3<=5,'Rate Card'!$AE$120,IF(3<=10,'Rate Card'!$AF$120,IF(3<=15,'Rate Card'!$AG$120,IF(3<=20,'Rate Card'!$AH$120,IF(3<=35,'Rate Card'!$AH$120+(3-20)*'Rate Card'!$AI$120,'Rate Card'!$AK$120+(3-35)*'Rate Card'!$AJ$120)))))))*(1+'Rate Card'!$C$6),2)*(IF('Rate Card'!$G$6="YES",'Rate Card'!$E$6,0)+IF('Rate Card'!$K$6="YES",'Rate Card'!$I$6,0)),2)
A8: 4 | B8: =IF(4<=5,'Rate Card'!$AD$20,'Rate Card'!$AD$20+(4-5)*'Rate Card'!$AE$20) | C8: =ROUND((IF(4<=5,'Rate Card'!$AD$20,'Rate Card'!$AD$20+(4-5)*'Rate Card'!$AE$20))*(1+'Rate Card'!$C$6),2)+ROUND(ROUND((IF(4<=5,'Rate Card'!$AD$20,'Rate Card'!$AD$20+(4-5)*'Rate Card'!$AE$20))*(1+'Rate Card'!$C$6),2)*(IF('Rate Card'!$G$6="YES",'Rate Card'!$E$6,0)+IF('Rate Card'!$K$6="YES",'Rate Card'!$I$6,0)),2) | D8: =IF(4<=15,'Rate Card'!$AD$21,'Rate Card'!$AD$21+(4-15)*'Rate Card'!$AE$21) | E8: =ROUND((IF(4<=15,'Rate Card'!$AD$21,'Rate Card'!$AD$21+(4-15)*'Rate Card'!$AE$21))*(1+'Rate Card'!$C$6),2)+ROUND(ROUND((IF(4<=15,'Rate Card'!$AD$21,'Rate Card'!$AD$21+(4-15)*'Rate Card'!$AE$21))*(1+'Rate Card'!$C$6),2)*(IF('Rate Card'!$G$6="YES",'Rate Card'!$E$6,0)+IF('Rate Card'!$K$6="YES",'Rate Card'!$I$6,0)),2) | F8: =IF(4<=2,'Rate Card'!$AD$22,IF(4<=5,'Rate Card'!$AE$22,IF(4<=10,'Rate Card'!$AF$22,IF(4<=15,'Rate Card'!$AG$22,IF(4<=20,'Rate Card'!$AH$22,IF(4<=35,'Rate Card'!$AH$22+(4-20)*'Rate Card'!$AI$22,'Rate Card'!$AK$22+(4-35)*'Rate Card'!$AJ$22)))))) | G8: =ROUND((IF(4<=2,'Rate Card'!$AD$22,IF(4<=5,'Rate Card'!$AE$22,IF(4<=10,'Rate Card'!$AF$22,IF(4<=15,'Rate Card'!$AG$22,IF(4<=20,'Rate Card'!$AH$22,IF(4<=35,'Rate Card'!$AH$22+(4-20)*'Rate Card'!$AI$22,'Rate Card'!$AK$22+(4-35)*'Rate Card'!$AJ$22)))))))*(1+'Rate Card'!$C$6),2)+ROUND(ROUND((IF(4<=2,'Rate Card'!$AD$22,IF(4<=5,'Rate Card'!$AE$22,IF(4<=10,'Rate Card'!$AF$22,IF(4<=15,'Rate Card'!$AG$22,IF(4<=20,'Rate Card'!$AH$22,IF(4<=35,'Rate Card'!$AH$22+(4-20)*'Rate Card'!$AI$22,'Rate Card'!$AK$22+(4-35)*'Rate Card'!$AJ$22)))))))*(1+'Rate Card'!$C$6),2)*(IF('Rate Card'!$G$6="YES",'Rate Card'!$E$6,0)+IF('Rate Card'!$K$6="YES",'Rate Card'!$I$6,0)),2) | H8: =IF(4<=2,'Rate Card'!$AD$23,IF(4<=5,'Rate Card'!$AE$23,IF(4<=10,'Rate Card'!$AF$23,IF(4<=15,'Rate Card'!$AG$23,IF(4<=20,'Rate Card'!$AH$23,IF(4<=35,'Rate Card'!$AH$23+(4-20)*'Rate Card'!$AI$23,'Rate Card'!$AK$23+(4-35)*'Rate Card'!$AJ$23)))))) | I8: =ROUND((IF(4<=2,'Rate Card'!$AD$23,IF(4<=5,'Rate Card'!$AE$23,IF(4<=10,'Rate Card'!$AF$23,IF(4<=15,'Rate Card'!$AG$23,IF(4<=20,'Rate Card'!$AH$23,IF(4<=35,'Rate Card'!$AH$23+(4-20)*'Rate Card'!$AI$23,'Rate Card'!$AK$23+(4-35)*'Rate Card'!$AJ$23)))))))*(1+'Rate Card'!$C$6),2)+ROUND(ROUND((IF(4<=2,'Rate Card'!$AD$23,IF(4<=5,'Rate Card'!$AE$23,IF(4<=10,'Rate Card'!$AF$23,IF(4<=15,'Rate Card'!$AG$23,IF(4<=20,'Rate Card'!$AH$23,IF(4<=35,'Rate Card'!$AH$23+(4-20)*'Rate Card'!$AI$23,'Rate Card'!$AK$23+(4-35)*'Rate Card'!$AJ$23)))))))*(1+'Rate Card'!$C$6),2)*(IF('Rate Card'!$G$6="YES",'Rate Card'!$E$6,0)+IF('Rate Card'!$K$6="YES",'Rate Card'!$I$6,0)),2) | J8: =IF(4<=5,'Rate Card'!$AD$117,'Rate Card'!$AD$117+(4-5)*'Rate Card'!$AE$117) | K8: =ROUND((IF(4<=5,'Rate Card'!$AD$117,'Rate Card'!$AD$117+(4-5)*'Rate Card'!$AE$117))*(1+'Rate Card'!$C$6),2)+ROUND(ROUND((IF(4<=5,'Rate Card'!$AD$117,'Rate Card'!$AD$117+(4-5)*'Rate Card'!$AE$117))*(1+'Rate Card'!$C$6),2)*(IF('Rate Card'!$G$6="YES",'Rate Card'!$E$6,0)+IF('Rate Card'!$K$6="YES",'Rate Card'!$I$6,0)),2) | L8: =IF(4<=15,'Rate Card'!$AD$118,'Rate Card'!$AD$118+(4-15)*'Rate Card'!$AE$118) | M8: =ROUND((IF(4<=15,'Rate Card'!$AD$118,'Rate Card'!$AD$118+(4-15)*'Rate Card'!$AE$118))*(1+'Rate Card'!$C$6),2)+ROUND(ROUND((IF(4<=15,'Rate Card'!$AD$118,'Rate Card'!$AD$118+(4-15)*'Rate Card'!$AE$118))*(1+'Rate Card'!$C$6),2)*(IF('Rate Card'!$G$6="YES",'Rate Card'!$E$6,0)+IF('Rate Card'!$K$6="YES",'Rate Card'!$I$6,0)),2) | N8: =IF(4<=2,'Rate Card'!$AD$119,IF(4<=5,'Rate Card'!$AE$119,IF(4<=10,'Rate Card'!$AF$119,IF(4<=15,'Rate Card'!$AG$119,IF(4<=20,'Rate Card'!$AH$119,IF(4<=35,'Rate Card'!$AH$119+(4-20)*'Rate Card'!$AI$119,'Rate Card'!$AK$119+(4-35)*'Rate Card'!$AJ$119)))))) | O8: =ROUND((IF(4<=2,'Rate Card'!$AD$119,IF(4<=5,'Rate Card'!$AE$119,IF(4<=10,'Rate Card'!$AF$119,IF(4<=15,'Rate Card'!$AG$119,IF(4<=20,'Rate Card'!$AH$119,IF(4<=35,'Rate Card'!$AH$119+(4-20)*'Rate Card'!$AI$119,'Rate Card'!$AK$119+(4-35)*'Rate Card'!$AJ$119)))))))*(1+'Rate Card'!$C$6),2)+ROUND(ROUND((IF(4<=2,'Rate Card'!$AD$119,IF(4<=5,'Rate Card'!$AE$119,IF(4<=10,'Rate Card'!$AF$119,IF(4<=15,'Rate Card'!$AG$119,IF(4<=20,'Rate Card'!$AH$119,IF(4<=35,'Rate Card'!$AH$119+(4-20)*'Rate Card'!$AI$119,'Rate Card'!$AK$119+(4-35)*'Rate Card'!$AJ$119)))))))*(1+'Rate Card'!$C$6),2)*(IF('Rate Card'!$G$6="YES",'Rate Card'!$E$6,0)+IF('Rate Card'!$K$6="YES",'Rate Card'!$I$6,0)),2) | P8: =IF(4<=2,'Rate Card'!$AD$120,IF(4<=5,'Rate Card'!$AE$120,IF(4<=10,'Rate Card'!$AF$120,IF(4<=15,'Rate Card'!$AG$120,IF(4<=20,'Rate Card'!$AH$120,IF(4<=35,'Rate Card'!$AH$120+(4-20)*'Rate Card'!$AI$120,'Rate Card'!$AK$120+(4-35)*'Rate Card'!$AJ$120)))))) | Q8: =ROUND((IF(4<=2,'Rate Card'!$AD$120,IF(4<=5,'Rate Card'!$AE$120,IF(4<=10,'Rate Card'!$AF$120,IF(4<=15,'Rate Card'!$AG$120,IF(4<=20,'Rate Card'!$AH$120,IF(4<=35,'Rate Card'!$AH$120+(4-20)*'Rate Card'!$AI$120,'Rate Card'!$AK$120+(4-35)*'Rate Card'!$AJ$120)))))))*(1+'Rate Card'!$C$6),2)+ROUND(ROUND((IF(4<=2,'Rate Card'!$AD$120,IF(4<=5,'Rate Card'!$AE$120,IF(4<=10,'Rate Card'!$AF$120,IF(4<=15,'Rate Card'!$AG$120,IF(4<=20,'Rate Card'!$AH$120,IF(4<=35,'Rate Card'!$AH$120+(4-20)*'Rate Card'!$AI$120,'Rate Card'!$AK$120+(4-35)*'Rate Card'!$AJ$120)))))))*(1+'Rate Card'!$C$6),2)*(IF('Rate Card'!$G$6="YES",'Rate Card'!$E$6,0)+IF('Rate Card'!$K$6="YES",'Rate Card'!$I$6,0)),2)
A9: 5 | B9: =IF(5<=5,'Rate Card'!$AD$20,'Rate Card'!$AD$20+(5-5)*'Rate Card'!$AE$20) | C9: =ROUND((IF(5<=5,'Rate Card'!$AD$20,'Rate Card'!$AD$20+(5-5)*'Rate Card'!$AE$20))*(1+'Rate Card'!$C$6),2)+ROUND(ROUND((IF(5<=5,'Rate Card'!$AD$20,'Rate Card'!$AD$20+(5-5)*'Rate Card'!$AE$20))*(1+'Rate Card'!$C$6),2)*(IF('Rate Card'!$G$6="YES",'Rate Card'!$E$6,0)+IF('Rate Card'!$K$6="YES",'Rate Card'!$I$6,0)),2) | D9: =IF(5<=15,'Rate Card'!$AD$21,'Rate Card'!$AD$21+(5-15)*'Rate Card'!$AE$21) | E9: =ROUND((IF(5<=15,'Rate Card'!$AD$21,'Rate Card'!$AD$21+(5-15)*'Rate Card'!$AE$21))*(1+'Rate Card'!$C$6),2)+ROUND(ROUND((IF(5<=15,'Rate Card'!$AD$21,'Rate Card'!$AD$21+(5-15)*'Rate Card'!$AE$21))*(1+'Rate Card'!$C$6),2)*(IF('Rate Card'!$G$6="YES",'Rate Card'!$E$6,0)+IF('Rate Card'!$K$6="YES",'Rate Card'!$I$6,0)),2) | F9: =IF(5<=2,'Rate Card'!$AD$22,IF(5<=5,'Rate Card'!$AE$22,IF(5<=10,'Rate Card'!$AF$22,IF(5<=15,'Rate Card'!$AG$22,IF(5<=20,'Rate Card'!$AH$22,IF(5<=35,'Rate Card'!$AH$22+(5-20)*'Rate Card'!$AI$22,'Rate Card'!$AK$22+(5-35)*'Rate Card'!$AJ$22)))))) | G9: =ROUND((IF(5<=2,'Rate Card'!$AD$22,IF(5<=5,'Rate Card'!$AE$22,IF(5<=10,'Rate Card'!$AF$22,IF(5<=15,'Rate Card'!$AG$22,IF(5<=20,'Rate Card'!$AH$22,IF(5<=35,'Rate Card'!$AH$22+(5-20)*'Rate Card'!$AI$22,'Rate Card'!$AK$22+(5-35)*'Rate Card'!$AJ$22)))))))*(1+'Rate Card'!$C$6),2)+ROUND(ROUND((IF(5<=2,'Rate Card'!$AD$22,IF(5<=5,'Rate Card'!$AE$22,IF(5<=10,'Rate Card'!$AF$22,IF(5<=15,'Rate Card'!$AG$22,IF(5<=20,'Rate Card'!$AH$22,IF(5<=35,'Rate Card'!$AH$22+(5-20)*'Rate Card'!$AI$22,'Rate Card'!$AK$22+(5-35)*'Rate Card'!$AJ$22)))))))*(1+'Rate Card'!$C$6),2)*(IF('Rate Card'!$G$6="YES",'Rate Card'!$E$6,0)+IF('Rate Card'!$K$6="YES",'Rate Card'!$I$6,0)),2) | H9: =IF(5<=2,'Rate Card'!$AD$23,IF(5<=5,'Rate Card'!$AE$23,IF(5<=10,'Rate Card'!$AF$23,IF(5<=15,'Rate Card'!$AG$23,IF(5<=20,'Rate Card'!$AH$23,IF(5<=35,'Rate Card'!$AH$23+(5-20)*'Rate Card'!$AI$23,'Rate Card'!$AK$23+(5-35)*'Rate Card'!$AJ$23)))))) | I9: =ROUND((IF(5<=2,'Rate Card'!$AD$23,IF(5<=5,'Rate Card'!$AE$23,IF(5<=10,'Rate Card'!$AF$23,IF(5<=15,'Rate Card'!$AG$23,IF(5<=20,'Rate Card'!$AH$23,IF(5<=35,'Rate Card'!$AH$23+(5-20)*'Rate Card'!$AI$23,'Rate Card'!$AK$23+(5-35)*'Rate Card'!$AJ$23)))))))*(1+'Rate Card'!$C$6),2)+ROUND(ROUND((IF(5<=2,'Rate Card'!$AD$23,IF(5<=5,'Rate Card'!$AE$23,IF(5<=10,'Rate Card'!$AF$23,IF(5<=15,'Rate Card'!$AG$23,IF(5<=20,'Rate Card'!$AH$23,IF(5<=35,'Rate Card'!$AH$23+(5-20)*'Rate Card'!$AI$23,'Rate Card'!$AK$23+(5-35)*'Rate Card'!$AJ$23)))))))*(1+'Rate Card'!$C$6),2)*(IF('Rate Card'!$G$6="YES",'Rate Card'!$E$6,0)+IF('Rate Card'!$K$6="YES",'Rate Card'!$I$6,0)),2) | J9: =IF(5<=5,'Rate Card'!$AD$117,'Rate Card'!$AD$117+(5-5)*'Rate Card'!$AE$117) | K9: =ROUND((IF(5<=5,'Rate Card'!$AD$117,'Rate Card'!$AD$117+(5-5)*'Rate Card'!$AE$117))*(1+'Rate Card'!$C$6),2)+ROUND(ROUND((IF(5<=5,'Rate Card'!$AD$117,'Rate Card'!$AD$117+(5-5)*'Rate Card'!$AE$117))*(1+'Rate Card'!$C$6),2)*(IF('Rate Card'!$G$6="YES",'Rate Card'!$E$6,0)+IF('Rate Card'!$K$6="YES",'Rate Card'!$I$6,0)),2) | L9: =IF(5<=15,'Rate Card'!$AD$118,'Rate Card'!$AD$118+(5-15)*'Rate Card'!$AE$118) | M9: =ROUND((IF(5<=15,'Rate Card'!$AD$118,'Rate Card'!$AD$118+(5-15)*'Rate Card'!$AE$118))*(1+'Rate Card'!$C$6),2)+ROUND(ROUND((IF(5<=15,'Rate Card'!$AD$118,'Rate Card'!$AD$118+(5-15)*'Rate Card'!$AE$118))*(1+'Rate Card'!$C$6),2)*(IF('Rate Card'!$G$6="YES",'Rate Card'!$E$6,0)+IF('Rate Card'!$K$6="YES",'Rate Card'!$I$6,0)),2) | N9: =IF(5<=2,'Rate Card'!$AD$119,IF(5<=5,'Rate Card'!$AE$119,IF(5<=10,'Rate Card'!$AF$119,IF(5<=15,'Rate Card'!$AG$119,IF(5<=20,'Rate Card'!$AH$119,IF(5<=35,'Rate Card'!$AH$119+(5-20)*'Rate Card'!$AI$119,'Rate Card'!$AK$119+(5-35)*'Rate Card'!$AJ$119)))))) | O9: =ROUND((IF(5<=2,'Rate Card'!$AD$119,IF(5<=5,'Rate Card'!$AE$119,IF(5<=10,'Rate Card'!$AF$119,IF(5<=15,'Rate Card'!$AG$119,IF(5<=20,'Rate Card'!$AH$119,IF(5<=35,'Rate Card'!$AH$119+(5-20)*'Rate Card'!$AI$119,'Rate Card'!$AK$119+(5-35)*'Rate Card'!$AJ$119)))))))*(1+'Rate Card'!$C$6),2)+ROUND(ROUND((IF(5<=2,'Rate Card'!$AD$119,IF(5<=5,'Rate Card'!$AE$119,IF(5<=10,'Rate Card'!$AF$119,IF(5<=15,'Rate Card'!$AG$119,IF(5<=20,'Rate Card'!$AH$119,IF(5<=35,'Rate Card'!$AH$119+(5-20)*'Rate Card'!$AI$119,'Rate Card'!$AK$119+(5-35)*'Rate Card'!$AJ$119)))))))*(1+'Rate Card'!$C$6),2)*(IF('Rate Card'!$G$6="YES",'Rate Card'!$E$6,0)+IF('Rate Card'!$K$6="YES",'Rate Card'!$I$6,0)),2) | P9: =IF(5<=2,'Rate Card'!$AD$120,IF(5<=5,'Rate Card'!$AE$120,IF(5<=10,'Rate Card'!$AF$120,IF(5<=15,'Rate Card'!$AG$120,IF(5<=20,'Rate Card'!$AH$120,IF(5<=35,'Rate Card'!$AH$120+(5-20)*'Rate Card'!$AI$120,'Rate Card'!$AK$120+(5-35)*'Rate Card'!$AJ$120)))))) | Q9: =ROUND((IF(5<=2,'Rate Card'!$AD$120,IF(5<=5,'Rate Card'!$AE$120,IF(5<=10,'Rate Card'!$AF$120,IF(5<=15,'Rate Card'!$AG$120,IF(5<=20,'Rate Card'!$AH$120,IF(5<=35,'Rate Card'!$AH$120+(5-20)*'Rate Card'!$AI$120,'Rate Card'!$AK$120+(5-35)*'Rate Card'!$AJ$120)))))))*(1+'Rate Card'!$C$6),2)+ROUND(ROUND((IF(5<=2,'Rate Card'!$AD$120,IF(5<=5,'Rate Card'!$AE$120,IF(5<=10,'Rate Card'!$AF$120,IF(5<=15,'Rate Card'!$AG$120,IF(5<=20,'Rate Card'!$AH$120,IF(5<=35,'Rate Card'!$AH$120+(5-20)*'Rate Card'!$AI$120,'Rate Card'!$AK$120+(5-35)*'Rate Card'!$AJ$120)))))))*(1+'Rate Card'!$C$6),2)*(IF('Rate Card'!$G$6="YES",'Rate Card'!$E$6,0)+IF('Rate Card'!$K$6="YES",'Rate Card'!$I$6,0)),2)
A10: 6 | B10: =IF(6<=5,'Rate Card'!$AD$20,'Rate Card'!$AD$20+(6-5)*'Rate Card'!$AE$20) | C10: =ROUND((IF(6<=5,'Rate Card'!$AD$20,'Rate Card'!$AD$20+(6-5)*'Rate Card'!$AE$20))*(1+'Rate Card'!$C$6),2)+ROUND(ROUND((IF(6<=5,'Rate Card'!$AD$20,'Rate Card'!$AD$20+(6-5)*'Rate Card'!$AE$20))*(1+'Rate Card'!$C$6),2)*(IF('Rate Card'!$G$6="YES",'Rate Card'!$E$6,0)+IF('Rate Card'!$K$6="YES",'Rate Card'!$I$6,0)),2) | D10: =IF(6<=15,'Rate Card'!$AD$21,'Rate Card'!$AD$21+(6-15)*'Rate Card'!$AE$21) | E10: =ROUND((IF(6<=15,'Rate Card'!$AD$21,'Rate Card'!$AD$21+(6-15)*'Rate Card'!$AE$21))*(1+'Rate Card'!$C$6),2)+ROUND(ROUND((IF(6<=15,'Rate Card'!$AD$21,'Rate Card'!$AD$21+(6-15)*'Rate Card'!$AE$21))*(1+'Rate Card'!$C$6),2)*(IF('Rate Card'!$G$6="YES",'Rate Card'!$E$6,0)+IF('Rate Card'!$K$6="YES",'Rate Card'!$I$6,0)),2) | F10: =IF(6<=2,'Rate Card'!$AD$22,IF(6<=5,'Rate Card'!$AE$22,IF(6<=10,'Rate Card'!$AF$22,IF(6<=15,'Rate Card'!$AG$22,IF(6<=20,'Rate Card'!$AH$22,IF(6<=35,'Rate Card'!$AH$22+(6-20)*'Rate Card'!$AI$22,'Rate Card'!$AK$22+(6-35)*'Rate Card'!$AJ$22)))))) | G10: =ROUND((IF(6<=2,'Rate Card'!$AD$22,IF(6<=5,'Rate Card'!$AE$22,IF(6<=10,'Rate Card'!$AF$22,IF(6<=15,'Rate Card'!$AG$22,IF(6<=20,'Rate Card'!$AH$22,IF(6<=35,'Rate Card'!$AH$22+(6-20)*'Rate Card'!$AI$22,'Rate Card'!$AK$22+(6-35)*'Rate Card'!$AJ$22)))))))*(1+'Rate Card'!$C$6),2)+ROUND(ROUND((IF(6<=2,'Rate Card'!$AD$22,IF(6<=5,'Rate Card'!$AE$22,IF(6<=10,'Rate Card'!$AF$22,IF(6<=15,'Rate Card'!$AG$22,IF(6<=20,'Rate Card'!$AH$22,IF(6<=35,'Rate Card'!$AH$22+(6-20)*'Rate Card'!$AI$22,'Rate Card'!$AK$22+(6-35)*'Rate Card'!$AJ$22)))))))*(1+'Rate Card'!$C$6),2)*(IF('Rate Card'!$G$6="YES",'Rate Card'!$E$6,0)+IF('Rate Card'!$K$6="YES",'Rate Card'!$I$6,0)),2) | H10: =IF(6<=2,'Rate Card'!$AD$23,IF(6<=5,'Rate Card'!$AE$23,IF(6<=10,'Rate Card'!$AF$23,IF(6<=15,'Rate Card'!$AG$23,IF(6<=20,'Rate Card'!$AH$23,IF(6<=35,'Rate Card'!$AH$23+(6-20)*'Rate Card'!$AI$23,'Rate Card'!$AK$23+(6-35)*'Rate Card'!$AJ$23)))))) | I10: =ROUND((IF(6<=2,'Rate Card'!$AD$23,IF(6<=5,'Rate Card'!$AE$23,IF(6<=10,'Rate Card'!$AF$23,IF(6<=15,'Rate Card'!$AG$23,IF(6<=20,'Rate Card'!$AH$23,IF(6<=35,'Rate Card'!$AH$23+(6-20)*'Rate Card'!$AI$23,'Rate Card'!$AK$23+(6-35)*'Rate Card'!$AJ$23)))))))*(1+'Rate Card'!$C$6),2)+ROUND(ROUND((IF(6<=2,'Rate Card'!$AD$23,IF(6<=5,'Rate Card'!$AE$23,IF(6<=10,'Rate Card'!$AF$23,IF(6<=15,'Rate Card'!$AG$23,IF(6<=20,'Rate Card'!$AH$23,IF(6<=35,'Rate Card'!$AH$23+(6-20)*'Rate Card'!$AI$23,'Rate Card'!$AK$23+(6-35)*'Rate Card'!$AJ$23)))))))*(1+'Rate Card'!$C$6),2)*(IF('Rate Card'!$G$6="YES",'Rate Card'!$E$6,0)+IF('Rate Card'!$K$6="YES",'Rate Card'!$I$6,0)),2) | J10: =IF(6<=5,'Rate Card'!$AD$117,'Rate Card'!$AD$117+(6-5)*'Rate Card'!$AE$117) | K10: =ROUND((IF(6<=5,'Rate Card'!$AD$117,'Rate Card'!$AD$117+(6-5)*'Rate Card'!$AE$117))*(1+'Rate Card'!$C$6),2)+ROUND(ROUND((IF(6<=5,'Rate Card'!$AD$117,'Rate Card'!$AD$117+(6-5)*'Rate Card'!$AE$117))*(1+'Rate Card'!$C$6),2)*(IF('Rate Card'!$G$6="YES",'Rate Card'!$E$6,0)+IF('Rate Card'!$K$6="YES",'Rate Card'!$I$6,0)),2) | L10: =IF(6<=15,'Rate Card'!$AD$118,'Rate Card'!$AD$118+(6-15)*'Rate Card'!$AE$118) | M10: =ROUND((IF(6<=15,'Rate Card'!$AD$118,'Rate Card'!$AD$118+(6-15)*'Rate Card'!$AE$118))*(1+'Rate Card'!$C$6),2)+ROUND(ROUND((IF(6<=15,'Rate Card'!$AD$118,'Rate Card'!$AD$118+(6-15)*'Rate Card'!$AE$118))*(1+'Rate Card'!$C$6),2)*(IF('Rate Card'!$G$6="YES",'Rate Card'!$E$6,0)+IF('Rate Card'!$K$6="YES",'Rate Card'!$I$6,0)),2) | N10: =IF(6<=2,'Rate Card'!$AD$119,IF(6<=5,'Rate Card'!$AE$119,IF(6<=10,'Rate Card'!$AF$119,IF(6<=15,'Rate Card'!$AG$119,IF(6<=20,'Rate Card'!$AH$119,IF(6<=35,'Rate Card'!$AH$119+(6-20)*'Rate Card'!$AI$119,'Rate Card'!$AK$119+(6-35)*'Rate Card'!$AJ$119)))))) | O10: =ROUND((IF(6<=2,'Rate Card'!$AD$119,IF(6<=5,'Rate Card'!$AE$119,IF(6<=10,'Rate Card'!$AF$119,IF(6<=15,'Rate Card'!$AG$119,IF(6<=20,'Rate Card'!$AH$119,IF(6<=35,'Rate Card'!$AH$119+(6-20)*'Rate Card'!$AI$119,'Rate Card'!$AK$119+(6-35)*'Rate Card'!$AJ$119)))))))*(1+'Rate Card'!$C$6),2)+ROUND(ROUND((IF(6<=2,'Rate Card'!$AD$119,IF(6<=5,'Rate Card'!$AE$119,IF(6<=10,'Rate Card'!$AF$119,IF(6<=15,'Rate Card'!$AG$119,IF(6<=20,'Rate Card'!$AH$119,IF(6<=35,'Rate Card'!$AH$119+(6-20)*'Rate Card'!$AI$119,'Rate Card'!$AK$119+(6-35)*'Rate Card'!$AJ$119)))))))*(1+'Rate Card'!$C$6),2)*(IF('Rate Card'!$G$6="YES",'Rate Card'!$E$6,0)+IF('Rate Card'!$K$6="YES",'Rate Card'!$I$6,0)),2) | P10: =IF(6<=2,'Rate Card'!$AD$120,IF(6<=5,'Rate Card'!$AE$120,IF(6<=10,'Rate Card'!$AF$120,IF(6<=15,'Rate Card'!$AG$120,IF(6<=20,'Rate Card'!$AH$120,IF(6<=35,'Rate Card'!$AH$120+(6-20)*'Rate Card'!$AI$120,'Rate Card'!$AK$120+(6-35)*'Rate Card'!$AJ$120)))))) | Q10: =ROUND((IF(6<=2,'Rate Card'!$AD$120,IF(6<=5,'Rate Card'!$AE$120,IF(6<=10,'Rate Card'!$AF$120,IF(6<=15,'Rate Card'!$AG$120,IF(6<=20,'Rate Card'!$AH$120,IF(6<=35,'Rate Card'!$AH$120+(6-20)*'Rate Card'!$AI$120,'Rate Card'!$AK$120+(6-35)*'Rate Card'!$AJ$120)))))))*(1+'Rate Card'!$C$6),2)+ROUND(ROUND((IF(6<=2,'Rate Card'!$AD$120,IF(6<=5,'Rate Card'!$AE$120,IF(6<=10,'Rate Card'!$AF$120,IF(6<=15,'Rate Card'!$AG$120,IF(6<=20,'Rate Card'!$AH$120,IF(6<=35,'Rate Card'!$AH$120+(6-20)*'Rate Card'!$AI$120,'Rate Card'!$AK$120+(6-35)*'Rate Card'!$AJ$120)))))))*(1+'Rate Card'!$C$6),2)*(IF('Rate Card'!$G$6="YES",'Rate Card'!$E$6,0)+IF('Rate Card'!$K$6="YES",'Rate Card'!$I$6,0)),2)
A11: 7 | B11: =IF(7<=5,'Rate Card'!$AD$20,'Rate Card'!$AD$20+(7-5)*'Rate Card'!$AE$20) | C11: =ROUND((IF(7<=5,'Rate Card'!$AD$20,'Rate Card'!$AD$20+(7-5)*'Rate Card'!$AE$20))*(1+'Rate Card'!$C$6),2)+ROUND(ROUND((IF(7<=5,'Rate Card'!$AD$20,'Rate Card'!$AD$20+(7-5)*'Rate Card'!$AE$20))*(1+'Rate Card'!$C$6),2)*(IF('Rate Card'!$G$6="YES",'Rate Card'!$E$6,0)+IF('Rate Card'!$K$6="YES",'Rate Card'!$I$6,0)),2) | D11: =IF(7<=15,'Rate Card'!$AD$21,'Rate Card'!$AD$21+(7-15)*'Rate Card'!$AE$21) | E11: =ROUND((IF(7<=15,'Rate Card'!$AD$21,'Rate Card'!$AD$21+(7-15)*'Rate Card'!$AE$21))*(1+'Rate Card'!$C$6),2)+ROUND(ROUND((IF(7<=15,'Rate Card'!$AD$21,'Rate Card'!$AD$21+(7-15)*'Rate Card'!$AE$21))*(1+'Rate Card'!$C$6),2)*(IF('Rate Card'!$G$6="YES",'Rate Card'!$E$6,0)+IF('Rate Card'!$K$6="YES",'Rate Card'!$I$6,0)),2) | F11: =IF(7<=2,'Rate Card'!$AD$22,IF(7<=5,'Rate Card'!$AE$22,IF(7<=10,'Rate Card'!$AF$22,IF(7<=15,'Rate Card'!$AG$22,IF(7<=20,'Rate Card'!$AH$22,IF(7<=35,'Rate Card'!$AH$22+(7-20)*'Rate Card'!$AI$22,'Rate Card'!$AK$22+(7-35)*'Rate Card'!$AJ$22)))))) | G11: =ROUND((IF(7<=2,'Rate Card'!$AD$22,IF(7<=5,'Rate Card'!$AE$22,IF(7<=10,'Rate Card'!$AF$22,IF(7<=15,'Rate Card'!$AG$22,IF(7<=20,'Rate Card'!$AH$22,IF(7<=35,'Rate Card'!$AH$22+(7-20)*'Rate Card'!$AI$22,'Rate Card'!$AK$22+(7-35)*'Rate Card'!$AJ$22)))))))*(1+'Rate Card'!$C$6),2)+ROUND(ROUND((IF(7<=2,'Rate Card'!$AD$22,IF(7<=5,'Rate Card'!$AE$22,IF(7<=10,'Rate Card'!$AF$22,IF(7<=15,'Rate Card'!$AG$22,IF(7<=20,'Rate Card'!$AH$22,IF(7<=35,'Rate Card'!$AH$22+(7-20)*'Rate Card'!$AI$22,'Rate Card'!$AK$22+(7-35)*'Rate Card'!$AJ$22)))))))*(1+'Rate Card'!$C$6),2)*(IF('Rate Card'!$G$6="YES",'Rate Card'!$E$6,0)+IF('Rate Card'!$K$6="YES",'Rate Card'!$I$6,0)),2) | H11: =IF(7<=2,'Rate Card'!$AD$23,IF(7<=5,'Rate Card'!$AE$23,IF(7<=10,'Rate Card'!$AF$23,IF(7<=15,'Rate Card'!$AG$23,IF(7<=20,'Rate Card'!$AH$23,IF(7<=35,'Rate Card'!$AH$23+(7-20)*'Rate Card'!$AI$23,'Rate Card'!$AK$23+(7-35)*'Rate Card'!$AJ$23)))))) | I11: =ROUND((IF(7<=2,'Rate Card'!$AD$23,IF(7<=5,'Rate Card'!$AE$23,IF(7<=10,'Rate Card'!$AF$23,IF(7<=15,'Rate Card'!$AG$23,IF(7<=20,'Rate Card'!$AH$23,IF(7<=35,'Rate Card'!$AH$23+(7-20)*'Rate Card'!$AI$23,'Rate Card'!$AK$23+(7-35)*'Rate Card'!$AJ$23)))))))*(1+'Rate Card'!$C$6),2)+ROUND(ROUND((IF(7<=2,'Rate Card'!$AD$23,IF(7<=5,'Rate Card'!$AE$23,IF(7<=10,'Rate Card'!$AF$23,IF(7<=15,'Rate Card'!$AG$23,IF(7<=20,'Rate Card'!$AH$23,IF(7<=35,'Rate Card'!$AH$23+(7-20)*'Rate Card'!$AI$23,'Rate Card'!$AK$23+(7-35)*'Rate Card'!$AJ$23)))))))*(1+'Rate Card'!$C$6),2)*(IF('Rate Card'!$G$6="YES",'Rate Card'!$E$6,0)+IF('Rate Card'!$K$6="YES",'Rate Card'!$I$6,0)),2) | J11: =IF(7<=5,'Rate Card'!$AD$117,'Rate Card'!$AD$117+(7-5)*'Rate Card'!$AE$117) | K11: =ROUND((IF(7<=5,'Rate Card'!$AD$117,'Rate Card'!$AD$117+(7-5)*'Rate Card'!$AE$117))*(1+'Rate Card'!$C$6),2)+ROUND(ROUND((IF(7<=5,'Rate Card'!$AD$117,'Rate Card'!$AD$117+(7-5)*'Rate Card'!$AE$117))*(1+'Rate Card'!$C$6),2)*(IF('Rate Card'!$G$6="YES",'Rate Card'!$E$6,0)+IF('Rate Card'!$K$6="YES",'Rate Card'!$I$6,0)),2) | L11: =IF(7<=15,'Rate Card'!$AD$118,'Rate Card'!$AD$118+(7-15)*'Rate Card'!$AE$118) | M11: =ROUND((IF(7<=15,'Rate Card'!$AD$118,'Rate Card'!$AD$118+(7-15)*'Rate Card'!$AE$118))*(1+'Rate Card'!$C$6),2)+ROUND(ROUND((IF(7<=15,'Rate Card'!$AD$118,'Rate Card'!$AD$118+(7-15)*'Rate Card'!$AE$118))*(1+'Rate Card'!$C$6),2)*(IF('Rate Card'!$G$6="YES",'Rate Card'!$E$6,0)+IF('Rate Card'!$K$6="YES",'Rate Card'!$I$6,0)),2) | N11: =IF(7<=2,'Rate Card'!$AD$119,IF(7<=5,'Rate Card'!$AE$119,IF(7<=10,'Rate Card'!$AF$119,IF(7<=15,'Rate Card'!$AG$119,IF(7<=20,'Rate Card'!$AH$119,IF(7<=35,'Rate Card'!$AH$119+(7-20)*'Rate Card'!$AI$119,'Rate Card'!$AK$119+(7-35)*'Rate Card'!$AJ$119)))))) | O11: =ROUND((IF(7<=2,'Rate Card'!$AD$119,IF(7<=5,'Rate Card'!$AE$119,IF(7<=10,'Rate Card'!$AF$119,IF(7<=15,'Rate Card'!$AG$119,IF(7<=20,'Rate Card'!$AH$119,IF(7<=35,'Rate Card'!$AH$119+(7-20)*'Rate Card'!$AI$119,'Rate Card'!$AK$119+(7-35)*'Rate Card'!$AJ$119)))))))*(1+'Rate Card'!$C$6),2)+ROUND(ROUND((IF(7<=2,'Rate Card'!$AD$119,IF(7<=5,'Rate Card'!$AE$119,IF(7<=10,'Rate Card'!$AF$119,IF(7<=15,'Rate Card'!$AG$119,IF(7<=20,'Rate Card'!$AH$119,IF(7<=35,'Rate Card'!$AH$119+(7-20)*'Rate Card'!$AI$119,'Rate Card'!$AK$119+(7-35)*'Rate Card'!$AJ$119)))))))*(1+'Rate Card'!$C$6),2)*(IF('Rate Card'!$G$6="YES",'Rate Card'!$E$6,0)+IF('Rate Card'!$K$6="YES",'Rate Card'!$I$6,0)),2) | P11: =IF(7<=2,'Rate Card'!$AD$120,IF(7<=5,'Rate Card'!$AE$120,IF(7<=10,'Rate Card'!$AF$120,IF(7<=15,'Rate Card'!$AG$120,IF(7<=20,'Rate Card'!$AH$120,IF(7<=35,'Rate Card'!$AH$120+(7-20)*'Rate Card'!$AI$120,'Rate Card'!$AK$120+(7-35)*'Rate Card'!$AJ$120)))))) | Q11: =ROUND((IF(7<=2,'Rate Card'!$AD$120,IF(7<=5,'Rate Card'!$AE$120,IF(7<=10,'Rate Card'!$AF$120,IF(7<=15,'Rate Card'!$AG$120,IF(7<=20,'Rate Card'!$AH$120,IF(7<=35,'Rate Card'!$AH$120+(7-20)*'Rate Card'!$AI$120,'Rate Card'!$AK$120+(7-35)*'Rate Card'!$AJ$120)))))))*(1+'Rate Card'!$C$6),2)+ROUND(ROUND((IF(7<=2,'Rate Card'!$AD$120,IF(7<=5,'Rate Card'!$AE$120,IF(7<=10,'Rate Card'!$AF$120,IF(7<=15,'Rate Card'!$AG$120,IF(7<=20,'Rate Card'!$AH$120,IF(7<=35,'Rate Card'!$AH$120+(7-20)*'Rate Card'!$AI$120,'Rate Card'!$AK$120+(7-35)*'Rate Card'!$AJ$120)))))))*(1+'Rate Card'!$C$6),2)*(IF('Rate Card'!$G$6="YES",'Rate Card'!$E$6,0)+IF('Rate Card'!$K$6="YES",'Rate Card'!$I$6,0)),2)
A12: 8 | B12: =IF(8<=5,'Rate Card'!$AD$20,'Rate Card'!$AD$20+(8-5)*'Rate Card'!$AE$20) | C12: =ROUND((IF(8<=5,'Rate Card'!$AD$20,'Rate Card'!$AD$20+(8-5)*'Rate Card'!$AE$20))*(1+'Rate Card'!$C$6),2)+ROUND(ROUND((IF(8<=5,'Rate Card'!$AD$20,'Rate Card'!$AD$20+(8-5)*'Rate Card'!$AE$20))*(1+'Rate Card'!$C$6),2)*(IF('Rate Card'!$G$6="YES",'Rate Card'!$E$6,0)+IF('Rate Card'!$K$6="YES",'Rate Card'!$I$6,0)),2) | D12: =IF(8<=15,'Rate Card'!$AD$21,'Rate Card'!$AD$21+(8-15)*'Rate Card'!$AE$21) | E12: =ROUND((IF(8<=15,'Rate Card'!$AD$21,'Rate Card'!$AD$21+(8-15)*'Rate Card'!$AE$21))*(1+'Rate Card'!$C$6),2)+ROUND(ROUND((IF(8<=15,'Rate Card'!$AD$21,'Rate Card'!$AD$21+(8-15)*'Rate Card'!$AE$21))*(1+'Rate Card'!$C$6),2)*(IF('Rate Card'!$G$6="YES",'Rate Card'!$E$6,0)+IF('Rate Card'!$K$6="YES",'Rate Card'!$I$6,0)),2) | F12: =IF(8<=2,'Rate Card'!$AD$22,IF(8<=5,'Rate Card'!$AE$22,IF(8<=10,'Rate Card'!$AF$22,IF(8<=15,'Rate Card'!$AG$22,IF(8<=20,'Rate Card'!$AH$22,IF(8<=35,'Rate Card'!$AH$22+(8-20)*'Rate Card'!$AI$22,'Rate Card'!$AK$22+(8-35)*'Rate Card'!$AJ$22)))))) | G12: =ROUND((IF(8<=2,'Rate Card'!$AD$22,IF(8<=5,'Rate Card'!$AE$22,IF(8<=10,'Rate Card'!$AF$22,IF(8<=15,'Rate Card'!$AG$22,IF(8<=20,'Rate Card'!$AH$22,IF(8<=35,'Rate Card'!$AH$22+(8-20)*'Rate Card'!$AI$22,'Rate Card'!$AK$22+(8-35)*'Rate Card'!$AJ$22)))))))*(1+'Rate Card'!$C$6),2)+ROUND(ROUND((IF(8<=2,'Rate Card'!$AD$22,IF(8<=5,'Rate Card'!$AE$22,IF(8<=10,'Rate Card'!$AF$22,IF(8<=15,'Rate Card'!$AG$22,IF(8<=20,'Rate Card'!$AH$22,IF(8<=35,'Rate Card'!$AH$22+(8-20)*'Rate Card'!$AI$22,'Rate Card'!$AK$22+(8-35)*'Rate Card'!$AJ$22)))))))*(1+'Rate Card'!$C$6),2)*(IF('Rate Card'!$G$6="YES",'Rate Card'!$E$6,0)+IF('Rate Card'!$K$6="YES",'Rate Card'!$I$6,0)),2) | H12: =IF(8<=2,'Rate Card'!$AD$23,IF(8<=5,'Rate Card'!$AE$23,IF(8<=10,'Rate Card'!$AF$23,IF(8<=15,'Rate Card'!$AG$23,IF(8<=20,'Rate Card'!$AH$23,IF(8<=35,'Rate Card'!$AH$23+(8-20)*'Rate Card'!$AI$23,'Rate Card'!$AK$23+(8-35)*'Rate Card'!$AJ$23)))))) | I12: =ROUND((IF(8<=2,'Rate Card'!$AD$23,IF(8<=5,'Rate Card'!$AE$23,IF(8<=10,'Rate Card'!$AF$23,IF(8<=15,'Rate Card'!$AG$23,IF(8<=20,'Rate Card'!$AH$23,IF(8<=35,'Rate Card'!$AH$23+(8-20)*'Rate Card'!$AI$23,'Rate Card'!$AK$23+(8-35)*'Rate Card'!$AJ$23)))))))*(1+'Rate Card'!$C$6),2)+ROUND(ROUND((IF(8<=2,'Rate Card'!$AD$23,IF(8<=5,'Rate Card'!$AE$23,IF(8<=10,'Rate Card'!$AF$23,IF(8<=15,'Rate Card'!$AG$23,IF(8<=20,'Rate Card'!$AH$23,IF(8<=35,'Rate Card'!$AH$23+(8-20)*'Rate Card'!$AI$23,'Rate Card'!$AK$23+(8-35)*'Rate Card'!$AJ$23)))))))*(1+'Rate Card'!$C$6),2)*(IF('Rate Card'!$G$6="YES",'Rate Card'!$E$6,0)+IF('Rate Card'!$K$6="YES",'Rate Card'!$I$6,0)),2) | J12: =IF(8<=5,'Rate Card'!$AD$117,'Rate Card'!$AD$117+(8-5)*'Rate Card'!$AE$117) | K12: =ROUND((IF(8<=5,'Rate Card'!$AD$117,'Rate Card'!$AD$117+(8-5)*'Rate Card'!$AE$117))*(1+'Rate Card'!$C$6),2)+ROUND(ROUND((IF(8<=5,'Rate Card'!$AD$117,'Rate Card'!$AD$117+(8-5)*'Rate Card'!$AE$117))*(1+'Rate Card'!$C$6),2)*(IF('Rate Card'!$G$6="YES",'Rate Card'!$E$6,0)+IF('Rate Card'!$K$6="YES",'Rate Card'!$I$6,0)),2) | L12: =IF(8<=15,'Rate Card'!$AD$118,'Rate Card'!$AD$118+(8-15)*'Rate Card'!$AE$118) | M12: =ROUND((IF(8<=15,'Rate Card'!$AD$118,'Rate Card'!$AD$118+(8-15)*'Rate Card'!$AE$118))*(1+'Rate Card'!$C$6),2)+ROUND(ROUND((IF(8<=15,'Rate Card'!$AD$118,'Rate Card'!$AD$118+(8-15)*'Rate Card'!$AE$118))*(1+'Rate Card'!$C$6),2)*(IF('Rate Card'!$G$6="YES",'Rate Card'!$E$6,0)+IF('Rate Card'!$K$6="YES",'Rate Card'!$I$6,0)),2) | N12: =IF(8<=2,'Rate Card'!$AD$119,IF(8<=5,'Rate Card'!$AE$119,IF(8<=10,'Rate Card'!$AF$119,IF(8<=15,'Rate Card'!$AG$119,IF(8<=20,'Rate Card'!$AH$119,IF(8<=35,'Rate Card'!$AH$119+(8-20)*'Rate Card'!$AI$119,'Rate Card'!$AK$119+(8-35)*'Rate Card'!$AJ$119)))))) | O12: =ROUND((IF(8<=2,'Rate Card'!$AD$119,IF(8<=5,'Rate Card'!$AE$119,IF(8<=10,'Rate Card'!$AF$119,IF(8<=15,'Rate Card'!$AG$119,IF(8<=20,'Rate Card'!$AH$119,IF(8<=35,'Rate Card'!$AH$119+(8-20)*'Rate Card'!$AI$119,'Rate Card'!$AK$119+(8-35)*'Rate Card'!$AJ$119)))))))*(1+'Rate Card'!$C$6),2)+ROUND(ROUND((IF(8<=2,'Rate Card'!$AD$119,IF(8<=5,'Rate Card'!$AE$119,IF(8<=10,'Rate Card'!$AF$119,IF(8<=15,'Rate Card'!$AG$119,IF(8<=20,'Rate Card'!$AH$119,IF(8<=35,'Rate Card'!$AH$119+(8-20)*'Rate Card'!$AI$119,'Rate Card'!$AK$119+(8-35)*'Rate Card'!$AJ$119)))))))*(1+'Rate Card'!$C$6),2)*(IF('Rate Card'!$G$6="YES",'Rate Card'!$E$6,0)+IF('Rate Card'!$K$6="YES",'Rate Card'!$I$6,0)),2) | P12: =IF(8<=2,'Rate Card'!$AD$120,IF(8<=5,'Rate Card'!$AE$120,IF(8<=10,'Rate Card'!$AF$120,IF(8<=15,'Rate Card'!$AG$120,IF(8<=20,'Rate Card'!$AH$120,IF(8<=35,'Rate Card'!$AH$120+(8-20)*'Rate Card'!$AI$120,'Rate Card'!$AK$120+(8-35)*'Rate Card'!$AJ$120)))))) | Q12: =ROUND((IF(8<=2,'Rate Card'!$AD$120,IF(8<=5,'Rate Card'!$AE$120,IF(8<=10,'Rate Card'!$AF$120,IF(8<=15,'Rate Card'!$AG$120,IF(8<=20,'Rate Card'!$AH$120,IF(8<=35,'Rate Card'!$AH$120+(8-20)*'Rate Card'!$AI$120,'Rate Card'!$AK$120+(8-35)*'Rate Card'!$AJ$120)))))))*(1+'Rate Card'!$C$6),2)+ROUND(ROUND((IF(8<=2,'Rate Card'!$AD$120,IF(8<=5,'Rate Card'!$AE$120,IF(8<=10,'Rate Card'!$AF$120,IF(8<=15,'Rate Card'!$AG$120,IF(8<=20,'Rate Card'!$AH$120,IF(8<=35,'Rate Card'!$AH$120+(8-20)*'Rate Card'!$AI$120,'Rate Card'!$AK$120+(8-35)*'Rate Card'!$AJ$120)))))))*(1+'Rate Card'!$C$6),2)*(IF('Rate Card'!$G$6="YES",'Rate Card'!$E$6,0)+IF('Rate Card'!$K$6="YES",'Rate Card'!$I$6,0)),2)
A13: 9 | B13: =IF(9<=5,'Rate Card'!$AD$20,'Rate Card'!$AD$20+(9-5)*'Rate Card'!$AE$20) | C13: =ROUND((IF(9<=5,'Rate Card'!$AD$20,'Rate Card'!$AD$20+(9-5)*'Rate Card'!$AE$20))*(1+'Rate Card'!$C$6),2)+ROUND(ROUND((IF(9<=5,'Rate Card'!$AD$20,'Rate Card'!$AD$20+(9-5)*'Rate Card'!$AE$20))*(1+'Rate Card'!$C$6),2)*(IF('Rate Card'!$G$6="YES",'Rate Card'!$E$6,0)+IF('Rate Card'!$K$6="YES",'Rate Card'!$I$6,0)),2) | D13: =IF(9<=15,'Rate Card'!$AD$21,'Rate Card'!$AD$21+(9-15)*'Rate Card'!$AE$21) | E13: =ROUND((IF(9<=15,'Rate Card'!$AD$21,'Rate Card'!$AD$21+(9-15)*'Rate Card'!$AE$21))*(1+'Rate Card'!$C$6),2)+ROUND(ROUND((IF(9<=15,'Rate Card'!$AD$21,'Rate Card'!$AD$21+(9-15)*'Rate Card'!$AE$21))*(1+'Rate Card'!$C$6),2)*(IF('Rate Card'!$G$6="YES",'Rate Card'!$E$6,0)+IF('Rate Card'!$K$6="YES",'Rate Card'!$I$6,0)),2) | F13: =IF(9<=2,'Rate Card'!$AD$22,IF(9<=5,'Rate Card'!$AE$22,IF(9<=10,'Rate Card'!$AF$22,IF(9<=15,'Rate Card'!$AG$22,IF(9<=20,'Rate Card'!$AH$22,IF(9<=35,'Rate Card'!$AH$22+(9-20)*'Rate Card'!$AI$22,'Rate Card'!$AK$22+(9-35)*'Rate Card'!$AJ$22)))))) | G13: =ROUND((IF(9<=2,'Rate Card'!$AD$22,IF(9<=5,'Rate Card'!$AE$22,IF(9<=10,'Rate Card'!$AF$22,IF(9<=15,'Rate Card'!$AG$22,IF(9<=20,'Rate Card'!$AH$22,IF(9<=35,'Rate Card'!$AH$22+(9-20)*'Rate Card'!$AI$22,'Rate Card'!$AK$22+(9-35)*'Rate Card'!$AJ$22)))))))*(1+'Rate Card'!$C$6),2)+ROUND(ROUND((IF(9<=2,'Rate Card'!$AD$22,IF(9<=5,'Rate Card'!$AE$22,IF(9<=10,'Rate Card'!$AF$22,IF(9<=15,'Rate Card'!$AG$22,IF(9<=20,'Rate Card'!$AH$22,IF(9<=35,'Rate Card'!$AH$22+(9-20)*'Rate Card'!$AI$22,'Rate Card'!$AK$22+(9-35)*'Rate Card'!$AJ$22)))))))*(1+'Rate Card'!$C$6),2)*(IF('Rate Card'!$G$6="YES",'Rate Card'!$E$6,0)+IF('Rate Card'!$K$6="YES",'Rate Card'!$I$6,0)),2) | H13: =IF(9<=2,'Rate Card'!$AD$23,IF(9<=5,'Rate Card'!$AE$23,IF(9<=10,'Rate Card'!$AF$23,IF(9<=15,'Rate Card'!$AG$23,IF(9<=20,'Rate Card'!$AH$23,IF(9<=35,'Rate Card'!$AH$23+(9-20)*'Rate Card'!$AI$23,'Rate Card'!$AK$23+(9-35)*'Rate Card'!$AJ$23)))))) | I13: =ROUND((IF(9<=2,'Rate Card'!$AD$23,IF(9<=5,'Rate Card'!$AE$23,IF(9<=10,'Rate Card'!$AF$23,IF(9<=15,'Rate Card'!$AG$23,IF(9<=20,'Rate Card'!$AH$23,IF(9<=35,'Rate Card'!$AH$23+(9-20)*'Rate Card'!$AI$23,'Rate Card'!$AK$23+(9-35)*'Rate Card'!$AJ$23)))))))*(1+'Rate Card'!$C$6),2)+ROUND(ROUND((IF(9<=2,'Rate Card'!$AD$23,IF(9<=5,'Rate Card'!$AE$23,IF(9<=10,'Rate Card'!$AF$23,IF(9<=15,'Rate Card'!$AG$23,IF(9<=20,'Rate Card'!$AH$23,IF(9<=35,'Rate Card'!$AH$23+(9-20)*'Rate Card'!$AI$23,'Rate Card'!$AK$23+(9-35)*'Rate Card'!$AJ$23)))))))*(1+'Rate Card'!$C$6),2)*(IF('Rate Card'!$G$6="YES",'Rate Card'!$E$6,0)+IF('Rate Card'!$K$6="YES",'Rate Card'!$I$6,0)),2) | J13: =IF(9<=5,'Rate Card'!$AD$117,'Rate Card'!$AD$117+(9-5)*'Rate Card'!$AE$117) | K13: =ROUND((IF(9<=5,'Rate Card'!$AD$117,'Rate Card'!$AD$117+(9-5)*'Rate Card'!$AE$117))*(1+'Rate Card'!$C$6),2)+ROUND(ROUND((IF(9<=5,'Rate Card'!$AD$117,'Rate Card'!$AD$117+(9-5)*'Rate Card'!$AE$117))*(1+'Rate Card'!$C$6),2)*(IF('Rate Card'!$G$6="YES",'Rate Card'!$E$6,0)+IF('Rate Card'!$K$6="YES",'Rate Card'!$I$6,0)),2) | L13: =IF(9<=15,'Rate Card'!$AD$118,'Rate Card'!$AD$118+(9-15)*'Rate Card'!$AE$118) | M13: =ROUND((IF(9<=15,'Rate Card'!$AD$118,'Rate Card'!$AD$118+(9-15)*'Rate Card'!$AE$118))*(1+'Rate Card'!$C$6),2)+ROUND(ROUND((IF(9<=15,'Rate Card'!$AD$118,'Rate Card'!$AD$118+(9-15)*'Rate Card'!$AE$118))*(1+'Rate Card'!$C$6),2)*(IF('Rate Card'!$G$6="YES",'Rate Card'!$E$6,0)+IF('Rate Card'!$K$6="YES",'Rate Card'!$I$6,0)),2) | N13: =IF(9<=2,'Rate Card'!$AD$119,IF(9<=5,'Rate Card'!$AE$119,IF(9<=10,'Rate Card'!$AF$119,IF(9<=15,'Rate Card'!$AG$119,IF(9<=20,'Rate Card'!$AH$119,IF(9<=35,'Rate Card'!$AH$119+(9-20)*'Rate Card'!$AI$119,'Rate Card'!$AK$119+(9-35)*'Rate Card'!$AJ$119)))))) | O13: =ROUND((IF(9<=2,'Rate Card'!$AD$119,IF(9<=5,'Rate Card'!$AE$119,IF(9<=10,'Rate Card'!$AF$119,IF(9<=15,'Rate Card'!$AG$119,IF(9<=20,'Rate Card'!$AH$119,IF(9<=35,'Rate Card'!$AH$119+(9-20)*'Rate Card'!$AI$119,'Rate Card'!$AK$119+(9-35)*'Rate Card'!$AJ$119)))))))*(1+'Rate Card'!$C$6),2)+ROUND(ROUND((IF(9<=2,'Rate Card'!$AD$119,IF(9<=5,'Rate Card'!$AE$119,IF(9<=10,'Rate Card'!$AF$119,IF(9<=15,'Rate Card'!$AG$119,IF(9<=20,'Rate Card'!$AH$119,IF(9<=35,'Rate Card'!$AH$119+(9-20)*'Rate Card'!$AI$119,'Rate Card'!$AK$119+(9-35)*'Rate Card'!$AJ$119)))))))*(1+'Rate Card'!$C$6),2)*(IF('Rate Card'!$G$6="YES",'Rate Card'!$E$6,0)+IF('Rate Card'!$K$6="YES",'Rate Card'!$I$6,0)),2) | P13: =IF(9<=2,'Rate Card'!$AD$120,IF(9<=5,'Rate Card'!$AE$120,IF(9<=10,'Rate Card'!$AF$120,IF(9<=15,'Rate Card'!$AG$120,IF(9<=20,'Rate Card'!$AH$120,IF(9<=35,'Rate Card'!$AH$120+(9-20)*'Rate Card'!$AI$120,'Rate Card'!$AK$120+(9-35)*'Rate Card'!$AJ$120)))))) | Q13: =ROUND((IF(9<=2,'Rate Card'!$AD$120,IF(9<=5,'Rate Card'!$AE$120,IF(9<=10,'Rate Card'!$AF$120,IF(9<=15,'Rate Card'!$AG$120,IF(9<=20,'Rate Card'!$AH$120,IF(9<=35,'Rate Card'!$AH$120+(9-20)*'Rate Card'!$AI$120,'Rate Card'!$AK$120+(9-35)*'Rate Card'!$AJ$120)))))))*(1+'Rate Card'!$C$6),2)+ROUND(ROUND((IF(9<=2,'Rate Card'!$AD$120,IF(9<=5,'Rate Card'!$AE$120,IF(9<=10,'Rate Card'!$AF$120,IF(9<=15,'Rate Card'!$AG$120,IF(9<=20,'Rate Card'!$AH$120,IF(9<=35,'Rate Card'!$AH$120+(9-20)*'Rate Card'!$AI$120,'Rate Card'!$AK$120+(9-35)*'Rate Card'!$AJ$120)))))))*(1+'Rate Card'!$C$6),2)*(IF('Rate Card'!$G$6="YES",'Rate Card'!$E$6,0)+IF('Rate Card'!$K$6="YES",'Rate Card'!$I$6,0)),2)
A14: 10 | B14: =IF(10<=5,'Rate Card'!$AD$20,'Rate Card'!$AD$20+(10-5)*'Rate Card'!$AE$20) | C14: =ROUND((IF(10<=5,'Rate Card'!$AD$20,'Rate Card'!$AD$20+(10-5)*'Rate Card'!$AE$20))*(1+'Rate Card'!$C$6),2)+ROUND(ROUND((IF(10<=5,'Rate Card'!$AD$20,'Rate Card'!$AD$20+(10-5)*'Rate Card'!$AE$20))*(1+'Rate Card'!$C$6),2)*(IF('Rate Card'!$G$6="YES",'Rate Card'!$E$6,0)+IF('Rate Card'!$K$6="YES",'Rate Card'!$I$6,0)),2) | D14: =IF(10<=15,'Rate Card'!$AD$21,'Rate Card'!$AD$21+(10-15)*'Rate Card'!$AE$21) | E14: =ROUND((IF(10<=15,'Rate Card'!$AD$21,'Rate Card'!$AD$21+(10-15)*'Rate Card'!$AE$21))*(1+'Rate Card'!$C$6),2)+ROUND(ROUND((IF(10<=15,'Rate Card'!$AD$21,'Rate Card'!$AD$21+(10-15)*'Rate Card'!$AE$21))*(1+'Rate Card'!$C$6),2)*(IF('Rate Card'!$G$6="YES",'Rate Card'!$E$6,0)+IF('Rate Card'!$K$6="YES",'Rate Card'!$I$6,0)),2) | F14: =IF(10<=2,'Rate Card'!$AD$22,IF(10<=5,'Rate Card'!$AE$22,IF(10<=10,'Rate Card'!$AF$22,IF(10<=15,'Rate Card'!$AG$22,IF(10<=20,'Rate Card'!$AH$22,IF(10<=35,'Rate Card'!$AH$22+(10-20)*'Rate Card'!$AI$22,'Rate Card'!$AK$22+(10-35)*'Rate Card'!$AJ$22)))))) | G14: =ROUND((IF(10<=2,'Rate Card'!$AD$22,IF(10<=5,'Rate Card'!$AE$22,IF(10<=10,'Rate Card'!$AF$22,IF(10<=15,'Rate Card'!$AG$22,IF(10<=20,'Rate Card'!$AH$22,IF(10<=35,'Rate Card'!$AH$22+(10-20)*'Rate Card'!$AI$22,'Rate Card'!$AK$22+(10-35)*'Rate Card'!$AJ$22)))))))*(1+'Rate Card'!$C$6),2)+ROUND(ROUND((IF(10<=2,'Rate Card'!$AD$22,IF(10<=5,'Rate Card'!$AE$22,IF(10<=10,'Rate Card'!$AF$22,IF(10<=15,'Rate Card'!$AG$22,IF(10<=20,'Rate Card'!$AH$22,IF(10<=35,'Rate Card'!$AH$22+(10-20)*'Rate Card'!$AI$22,'Rate Card'!$AK$22+(10-35)*'Rate Card'!$AJ$22)))))))*(1+'Rate Card'!$C$6),2)*(IF('Rate Card'!$G$6="YES",'Rate Card'!$E$6,0)+IF('Rate Card'!$K$6="YES",'Rate Card'!$I$6,0)),2) | H14: =IF(10<=2,'Rate Card'!$AD$23,IF(10<=5,'Rate Card'!$AE$23,IF(10<=10,'Rate Card'!$AF$23,IF(10<=15,'Rate Card'!$AG$23,IF(10<=20,'Rate Card'!$AH$23,IF(10<=35,'Rate Card'!$AH$23+(10-20)*'Rate Card'!$AI$23,'Rate Card'!$AK$23+(10-35)*'Rate Card'!$AJ$23)))))) | I14: =ROUND((IF(10<=2,'Rate Card'!$AD$23,IF(10<=5,'Rate Card'!$AE$23,IF(10<=10,'Rate Card'!$AF$23,IF(10<=15,'Rate Card'!$AG$23,IF(10<=20,'Rate Card'!$AH$23,IF(10<=35,'Rate Card'!$AH$23+(10-20)*'Rate Card'!$AI$23,'Rate Card'!$AK$23+(10-35)*'Rate Card'!$AJ$23)))))))*(1+'Rate Card'!$C$6),2)+ROUND(ROUND((IF(10<=2,'Rate Card'!$AD$23,IF(10<=5,'Rate Card'!$AE$23,IF(10<=10,'Rate Card'!$AF$23,IF(10<=15,'Rate Card'!$AG$23,IF(10<=20,'Rate Card'!$AH$23,IF(10<=35,'Rate Card'!$AH$23+(10-20)*'Rate Card'!$AI$23,'Rate Card'!$AK$23+(10-35)*'Rate Card'!$AJ$23)))))))*(1+'Rate Card'!$C$6),2)*(IF('Rate Card'!$G$6="YES",'Rate Card'!$E$6,0)+IF('Rate Card'!$K$6="YES",'Rate Card'!$I$6,0)),2) | J14: =IF(10<=5,'Rate Card'!$AD$117,'Rate Card'!$AD$117+(10-5)*'Rate Card'!$AE$117) | K14: =ROUND((IF(10<=5,'Rate Card'!$AD$117,'Rate Card'!$AD$117+(10-5)*'Rate Card'!$AE$117))*(1+'Rate Card'!$C$6),2)+ROUND(ROUND((IF(10<=5,'Rate Card'!$AD$117,'Rate Card'!$AD$117+(10-5)*'Rate Card'!$AE$117))*(1+'Rate Card'!$C$6),2)*(IF('Rate Card'!$G$6="YES",'Rate Card'!$E$6,0)+IF('Rate Card'!$K$6="YES",'Rate Card'!$I$6,0)),2) | L14: =IF(10<=15,'Rate Card'!$AD$118,'Rate Card'!$AD$118+(10-15)*'Rate Card'!$AE$118) | M14: =ROUND((IF(10<=15,'Rate Card'!$AD$118,'Rate Card'!$AD$118+(10-15)*'Rate Card'!$AE$118))*(1+'Rate Card'!$C$6),2)+ROUND(ROUND((IF(10<=15,'Rate Card'!$AD$118,'Rate Card'!$AD$118+(10-15)*'Rate Card'!$AE$118))*(1+'Rate Card'!$C$6),2)*(IF('Rate Card'!$G$6="YES",'Rate Card'!$E$6,0)+IF('Rate Card'!$K$6="YES",'Rate Card'!$I$6,0)),2) | N14: =IF(10<=2,'Rate Card'!$AD$119,IF(10<=5,'Rate Card'!$AE$119,IF(10<=10,'Rate Card'!$AF$119,IF(10<=15,'Rate Card'!$AG$119,IF(10<=20,'Rate Card'!$AH$119,IF(10<=35,'Rate Card'!$AH$119+(10-20)*'Rate Card'!$AI$119,'Rate Card'!$AK$119+(10-35)*'Rate Card'!$AJ$119)))))) | O14: =ROUND((IF(10<=2,'Rate Card'!$AD$119,IF(10<=5,'Rate Card'!$AE$119,IF(10<=10,'Rate Card'!$AF$119,IF(10<=15,'Rate Card'!$AG$119,IF(10<=20,'Rate Card'!$AH$119,IF(10<=35,'Rate Card'!$AH$119+(10-20)*'Rate Card'!$AI$119,'Rate Card'!$AK$119+(10-35)*'Rate Card'!$AJ$119)))))))*(1+'Rate Card'!$C$6),2)+ROUND(ROUND((IF(10<=2,'Rate Card'!$AD$119,IF(10<=5,'Rate Card'!$AE$119,IF(10<=10,'Rate Card'!$AF$119,IF(10<=15,'Rate Card'!$AG$119,IF(10<=20,'Rate Card'!$AH$119,IF(10<=35,'Rate Card'!$AH$119+(10-20)*'Rate Card'!$AI$119,'Rate Card'!$AK$119+(10-35)*'Rate Card'!$AJ$119)))))))*(1+'Rate Card'!$C$6),2)*(IF('Rate Card'!$G$6="YES",'Rate Card'!$E$6,0)+IF('Rate Card'!$K$6="YES",'Rate Card'!$I$6,0)),2) | P14: =IF(10<=2,'Rate Card'!$AD$120,IF(10<=5,'Rate Card'!$AE$120,IF(10<=10,'Rate Card'!$AF$120,IF(10<=15,'Rate Card'!$AG$120,IF(10<=20,'Rate Card'!$AH$120,IF(10<=35,'Rate Card'!$AH$120+(10-20)*'Rate Card'!$AI$120,'Rate Card'!$AK$120+(10-35)*'Rate Card'!$AJ$120)))))) | Q14: =ROUND((IF(10<=2,'Rate Card'!$AD$120,IF(10<=5,'Rate Card'!$AE$120,IF(10<=10,'Rate Card'!$AF$120,IF(10<=15,'Rate Card'!$AG$120,IF(10<=20,'Rate Card'!$AH$120,IF(10<=35,'Rate Card'!$AH$120+(10-20)*'Rate Card'!$AI$120,'Rate Card'!$AK$120+(10-35)*'Rate Card'!$AJ$120)))))))*(1+'Rate Card'!$C$6),2)+ROUND(ROUND((IF(10<=2,'Rate Card'!$AD$120,IF(10<=5,'Rate Card'!$AE$120,IF(10<=10,'Rate Card'!$AF$120,IF(10<=15,'Rate Card'!$AG$120,IF(10<=20,'Rate Card'!$AH$120,IF(10<=35,'Rate Card'!$AH$120+(10-20)*'Rate Card'!$AI$120,'Rate Card'!$AK$120+(10-35)*'Rate Card'!$AJ$120)))))))*(1+'Rate Card'!$C$6),2)*(IF('Rate Card'!$G$6="YES",'Rate Card'!$E$6,0)+IF('Rate Card'!$K$6="YES",'Rate Card'!$I$6,0)),2)
A15: 11 | B15: =IF(11<=5,'Rate Card'!$AD$20,'Rate Card'!$AD$20+(11-5)*'Rate Card'!$AE$20) | C15: =ROUND((IF(11<=5,'Rate Card'!$AD$20,'Rate Card'!$AD$20+(11-5)*'Rate Card'!$AE$20))*(1+'Rate Card'!$C$6),2)+ROUND(ROUND((IF(11<=5,'Rate Card'!$AD$20,'Rate Card'!$AD$20+(11-5)*'Rate Card'!$AE$20))*(1+'Rate Card'!$C$6),2)*(IF('Rate Card'!$G$6="YES",'Rate Card'!$E$6,0)+IF('Rate Card'!$K$6="YES",'Rate Card'!$I$6,0)),2) | D15: =IF(11<=15,'Rate Card'!$AD$21,'Rate Card'!$AD$21+(11-15)*'Rate Card'!$AE$21) | E15: =ROUND((IF(11<=15,'Rate Card'!$AD$21,'Rate Card'!$AD$21+(11-15)*'Rate Card'!$AE$21))*(1+'Rate Card'!$C$6),2)+ROUND(ROUND((IF(11<=15,'Rate Card'!$AD$21,'Rate Card'!$AD$21+(11-15)*'Rate Card'!$AE$21))*(1+'Rate Card'!$C$6),2)*(IF('Rate Card'!$G$6="YES",'Rate Card'!$E$6,0)+IF('Rate Card'!$K$6="YES",'Rate Card'!$I$6,0)),2) | F15: =IF(11<=2,'Rate Card'!$AD$22,IF(11<=5,'Rate Card'!$AE$22,IF(11<=10,'Rate Card'!$AF$22,IF(11<=15,'Rate Card'!$AG$22,IF(11<=20,'Rate Card'!$AH$22,IF(11<=35,'Rate Card'!$AH$22+(11-20)*'Rate Card'!$AI$22,'Rate Card'!$AK$22+(11-35)*'Rate Card'!$AJ$22)))))) | G15: =ROUND((IF(11<=2,'Rate Card'!$AD$22,IF(11<=5,'Rate Card'!$AE$22,IF(11<=10,'Rate Card'!$AF$22,IF(11<=15,'Rate Card'!$AG$22,IF(11<=20,'Rate Card'!$AH$22,IF(11<=35,'Rate Card'!$AH$22+(11-20)*'Rate Card'!$AI$22,'Rate Card'!$AK$22+(11-35)*'Rate Card'!$AJ$22)))))))*(1+'Rate Card'!$C$6),2)+ROUND(ROUND((IF(11<=2,'Rate Card'!$AD$22,IF(11<=5,'Rate Card'!$AE$22,IF(11<=10,'Rate Card'!$AF$22,IF(11<=15,'Rate Card'!$AG$22,IF(11<=20,'Rate Card'!$AH$22,IF(11<=35,'Rate Card'!$AH$22+(11-20)*'Rate Card'!$AI$22,'Rate Card'!$AK$22+(11-35)*'Rate Card'!$AJ$22)))))))*(1+'Rate Card'!$C$6),2)*(IF('Rate Card'!$G$6="YES",'Rate Card'!$E$6,0)+IF('Rate Card'!$K$6="YES",'Rate Card'!$I$6,0)),2) | H15: =IF(11<=2,'Rate Card'!$AD$23,IF(11<=5,'Rate Card'!$AE$23,IF(11<=10,'Rate Card'!$AF$23,IF(11<=15,'Rate Card'!$AG$23,IF(11<=20,'Rate Card'!$AH$23,IF(11<=35,'Rate Card'!$AH$23+(11-20)*'Rate Card'!$AI$23,'Rate Card'!$AK$23+(11-35)*'Rate Card'!$AJ$23)))))) | I15: =ROUND((IF(11<=2,'Rate Card'!$AD$23,IF(11<=5,'Rate Card'!$AE$23,IF(11<=10,'Rate Card'!$AF$23,IF(11<=15,'Rate Card'!$AG$23,IF(11<=20,'Rate Card'!$AH$23,IF(11<=35,'Rate Card'!$AH$23+(11-20)*'Rate Card'!$AI$23,'Rate Card'!$AK$23+(11-35)*'Rate Card'!$AJ$23)))))))*(1+'Rate Card'!$C$6),2)+ROUND(ROUND((IF(11<=2,'Rate Card'!$AD$23,IF(11<=5,'Rate Card'!$AE$23,IF(11<=10,'Rate Card'!$AF$23,IF(11<=15,'Rate Card'!$AG$23,IF(11<=20,'Rate Card'!$AH$23,IF(11<=35,'Rate Card'!$AH$23+(11-20)*'Rate Card'!$AI$23,'Rate Card'!$AK$23+(11-35)*'Rate Card'!$AJ$23)))))))*(1+'Rate Card'!$C$6),2)*(IF('Rate Card'!$G$6="YES",'Rate Card'!$E$6,0)+IF('Rate Card'!$K$6="YES",'Rate Card'!$I$6,0)),2) | J15: =IF(11<=5,'Rate Card'!$AD$117,'Rate Card'!$AD$117+(11-5)*'Rate Card'!$AE$117) | K15: =ROUND((IF(11<=5,'Rate Card'!$AD$117,'Rate Card'!$AD$117+(11-5)*'Rate Card'!$AE$117))*(1+'Rate Card'!$C$6),2)+ROUND(ROUND((IF(11<=5,'Rate Card'!$AD$117,'Rate Card'!$AD$117+(11-5)*'Rate Card'!$AE$117))*(1+'Rate Card'!$C$6),2)*(IF('Rate Card'!$G$6="YES",'Rate Card'!$E$6,0)+IF('Rate Card'!$K$6="YES",'Rate Card'!$I$6,0)),2) | L15: =IF(11<=15,'Rate Card'!$AD$118,'Rate Card'!$AD$118+(11-15)*'Rate Card'!$AE$118) | M15: =ROUND((IF(11<=15,'Rate Card'!$AD$118,'Rate Card'!$AD$118+(11-15)*'Rate Card'!$AE$118))*(1+'Rate Card'!$C$6),2)+ROUND(ROUND((IF(11<=15,'Rate Card'!$AD$118,'Rate Card'!$AD$118+(11-15)*'Rate Card'!$AE$118))*(1+'Rate Card'!$C$6),2)*(IF('Rate Card'!$G$6="YES",'Rate Card'!$E$6,0)+IF('Rate Card'!$K$6="YES",'Rate Card'!$I$6,0)),2) | N15: =IF(11<=2,'Rate Card'!$AD$119,IF(11<=5,'Rate Card'!$AE$119,IF(11<=10,'Rate Card'!$AF$119,IF(11<=15,'Rate Card'!$AG$119,IF(11<=20,'Rate Card'!$AH$119,IF(11<=35,'Rate Card'!$AH$119+(11-20)*'Rate Card'!$AI$119,'Rate Card'!$AK$119+(11-35)*'Rate Card'!$AJ$119)))))) | O15: =ROUND((IF(11<=2,'Rate Card'!$AD$119,IF(11<=5,'Rate Card'!$AE$119,IF(11<=10,'Rate Card'!$AF$119,IF(11<=15,'Rate Card'!$AG$119,IF(11<=20,'Rate Card'!$AH$119,IF(11<=35,'Rate Card'!$AH$119+(11-20)*'Rate Card'!$AI$119,'Rate Card'!$AK$119+(11-35)*'Rate Card'!$AJ$119)))))))*(1+'Rate Card'!$C$6),2)+ROUND(ROUND((IF(11<=2,'Rate Card'!$AD$119,IF(11<=5,'Rate Card'!$AE$119,IF(11<=10,'Rate Card'!$AF$119,IF(11<=15,'Rate Card'!$AG$119,IF(11<=20,'Rate Card'!$AH$119,IF(11<=35,'Rate Card'!$AH$119+(11-20)*'Rate Card'!$AI$119,'Rate Card'!$AK$119+(11-35)*'Rate Card'!$AJ$119)))))))*(1+'Rate Card'!$C$6),2)*(IF('Rate Card'!$G$6="YES",'Rate Card'!$E$6,0)+IF('Rate Card'!$K$6="YES",'Rate Card'!$I$6,0)),2) | P15: =IF(11<=2,'Rate Card'!$AD$120,IF(11<=5,'Rate Card'!$AE$120,IF(11<=10,'Rate Card'!$AF$120,IF(11<=15,'Rate Card'!$AG$120,IF(11<=20,'Rate Card'!$AH$120,IF(11<=35,'Rate Card'!$AH$120+(11-20)*'Rate Card'!$AI$120,'Rate Card'!$AK$120+(11-35)*'Rate Card'!$AJ$120)))))) | Q15: =ROUND((IF(11<=2,'Rate Card'!$AD$120,IF(11<=5,'Rate Card'!$AE$120,IF(11<=10,'Rate Card'!$AF$120,IF(11<=15,'Rate Card'!$AG$120,IF(11<=20,'Rate Card'!$AH$120,IF(11<=35,'Rate Card'!$AH$120+(11-20)*'Rate Card'!$AI$120,'Rate Card'!$AK$120+(11-35)*'Rate Card'!$AJ$120)))))))*(1+'Rate Card'!$C$6),2)+ROUND(ROUND((IF(11<=2,'Rate Card'!$AD$120,IF(11<=5,'Rate Card'!$AE$120,IF(11<=10,'Rate Card'!$AF$120,IF(11<=15,'Rate Card'!$AG$120,IF(11<=20,'Rate Card'!$AH$120,IF(11<=35,'Rate Card'!$AH$120+(11-20)*'Rate Card'!$AI$120,'Rate Card'!$AK$120+(11-35)*'Rate Card'!$AJ$120)))))))*(1+'Rate Card'!$C$6),2)*(IF('Rate Card'!$G$6="YES",'Rate Card'!$E$6,0)+IF('Rate Card'!$K$6="YES",'Rate Card'!$I$6,0)),2)
A16: 12 | B16: =IF(12<=5,'Rate Card'!$AD$20,'Rate Card'!$AD$20+(12-5)*'Rate Card'!$AE$20) | C16: =ROUND((IF(12<=5,'Rate Card'!$AD$20,'Rate Card'!$AD$20+(12-5)*'Rate Card'!$AE$20))*(1+'Rate Card'!$C$6),2)+ROUND(ROUND((IF(12<=5,'Rate Card'!$AD$20,'Rate Card'!$AD$20+(12-5)*'Rate Card'!$AE$20))*(1+'Rate Card'!$C$6),2)*(IF('Rate Card'!$G$6="YES",'Rate Card'!$E$6,0)+IF('Rate Card'!$K$6="YES",'Rate Card'!$I$6,0)),2) | D16: =IF(12<=15,'Rate Card'!$AD$21,'Rate Card'!$AD$21+(12-15)*'Rate Card'!$AE$21) | E16: =ROUND((IF(12<=15,'Rate Card'!$AD$21,'Rate Card'!$AD$21+(12-15)*'Rate Card'!$AE$21))*(1+'Rate Card'!$C$6),2)+ROUND(ROUND((IF(12<=15,'Rate Card'!$AD$21,'Rate Card'!$AD$21+(12-15)*'Rate Card'!$AE$21))*(1+'Rate Card'!$C$6),2)*(IF('Rate Card'!$G$6="YES",'Rate Card'!$E$6,0)+IF('Rate Card'!$K$6="YES",'Rate Card'!$I$6,0)),2) | F16: =IF(12<=2,'Rate Card'!$AD$22,IF(12<=5,'Rate Card'!$AE$22,IF(12<=10,'Rate Card'!$AF$22,IF(12<=15,'Rate Card'!$AG$22,IF(12<=20,'Rate Card'!$AH$22,IF(12<=35,'Rate Card'!$AH$22+(12-20)*'Rate Card'!$AI$22,'Rate Card'!$AK$22+(12-35)*'Rate Card'!$AJ$22)))))) | G16: =ROUND((IF(12<=2,'Rate Card'!$AD$22,IF(12<=5,'Rate Card'!$AE$22,IF(12<=10,'Rate Card'!$AF$22,IF(12<=15,'Rate Card'!$AG$22,IF(12<=20,'Rate Card'!$AH$22,IF(12<=35,'Rate Card'!$AH$22+(12-20)*'Rate Card'!$AI$22,'Rate Card'!$AK$22+(12-35)*'Rate Card'!$AJ$22)))))))*(1+'Rate Card'!$C$6),2)+ROUND(ROUND((IF(12<=2,'Rate Card'!$AD$22,IF(12<=5,'Rate Card'!$AE$22,IF(12<=10,'Rate Card'!$AF$22,IF(12<=15,'Rate Card'!$AG$22,IF(12<=20,'Rate Card'!$AH$22,IF(12<=35,'Rate Card'!$AH$22+(12-20)*'Rate Card'!$AI$22,'Rate Card'!$AK$22+(12-35)*'Rate Card'!$AJ$22)))))))*(1+'Rate Card'!$C$6),2)*(IF('Rate Card'!$G$6="YES",'Rate Card'!$E$6,0)+IF('Rate Card'!$K$6="YES",'Rate Card'!$I$6,0)),2) | H16: =IF(12<=2,'Rate Card'!$AD$23,IF(12<=5,'Rate Card'!$AE$23,IF(12<=10,'Rate Card'!$AF$23,IF(12<=15,'Rate Card'!$AG$23,IF(12<=20,'Rate Card'!$AH$23,IF(12<=35,'Rate Card'!$AH$23+(12-20)*'Rate Card'!$AI$23,'Rate Card'!$AK$23+(12-35)*'Rate Card'!$AJ$23)))))) | I16: =ROUND((IF(12<=2,'Rate Card'!$AD$23,IF(12<=5,'Rate Card'!$AE$23,IF(12<=10,'Rate Card'!$AF$23,IF(12<=15,'Rate Card'!$AG$23,IF(12<=20,'Rate Card'!$AH$23,IF(12<=35,'Rate Card'!$AH$23+(12-20)*'Rate Card'!$AI$23,'Rate Card'!$AK$23+(12-35)*'Rate Card'!$AJ$23)))))))*(1+'Rate Card'!$C$6),2)+ROUND(ROUND((IF(12<=2,'Rate Card'!$AD$23,IF(12<=5,'Rate Card'!$AE$23,IF(12<=10,'Rate Card'!$AF$23,IF(12<=15,'Rate Card'!$AG$23,IF(12<=20,'Rate Card'!$AH$23,IF(12<=35,'Rate Card'!$AH$23+(12-20)*'Rate Card'!$AI$23,'Rate Card'!$AK$23+(12-35)*'Rate Card'!$AJ$23)))))))*(1+'Rate Card'!$C$6),2)*(IF('Rate Card'!$G$6="YES",'Rate Card'!$E$6,0)+IF('Rate Card'!$K$6="YES",'Rate Card'!$I$6,0)),2) | J16: =IF(12<=5,'Rate Card'!$AD$117,'Rate Card'!$AD$117+(12-5)*'Rate Card'!$AE$117) | K16: =ROUND((IF(12<=5,'Rate Card'!$AD$117,'Rate Card'!$AD$117+(12-5)*'Rate Card'!$AE$117))*(1+'Rate Card'!$C$6),2)+ROUND(ROUND((IF(12<=5,'Rate Card'!$AD$117,'Rate Card'!$AD$117+(12-5)*'Rate Card'!$AE$117))*(1+'Rate Card'!$C$6),2)*(IF('Rate Card'!$G$6="YES",'Rate Card'!$E$6,0)+IF('Rate Card'!$K$6="YES",'Rate Card'!$I$6,0)),2) | L16: =IF(12<=15,'Rate Card'!$AD$118,'Rate Card'!$AD$118+(12-15)*'Rate Card'!$AE$118) | M16: =ROUND((IF(12<=15,'Rate Card'!$AD$118,'Rate Card'!$AD$118+(12-15)*'Rate Card'!$AE$118))*(1+'Rate Card'!$C$6),2)+ROUND(ROUND((IF(12<=15,'Rate Card'!$AD$118,'Rate Card'!$AD$118+(12-15)*'Rate Card'!$AE$118))*(1+'Rate Card'!$C$6),2)*(IF('Rate Card'!$G$6="YES",'Rate Card'!$E$6,0)+IF('Rate Card'!$K$6="YES",'Rate Card'!$I$6,0)),2) | N16: =IF(12<=2,'Rate Card'!$AD$119,IF(12<=5,'Rate Card'!$AE$119,IF(12<=10,'Rate Card'!$AF$119,IF(12<=15,'Rate Card'!$AG$119,IF(12<=20,'Rate Card'!$AH$119,IF(12<=35,'Rate Card'!$AH$119+(12-20)*'Rate Card'!$AI$119,'Rate Card'!$AK$119+(12-35)*'Rate Card'!$AJ$119)))))) | O16: =ROUND((IF(12<=2,'Rate Card'!$AD$119,IF(12<=5,'Rate Card'!$AE$119,IF(12<=10,'Rate Card'!$AF$119,IF(12<=15,'Rate Card'!$AG$119,IF(12<=20,'Rate Card'!$AH$119,IF(12<=35,'Rate Card'!$AH$119+(12-20)*'Rate Card'!$AI$119,'Rate Card'!$AK$119+(12-35)*'Rate Card'!$AJ$119)))))))*(1+'Rate Card'!$C$6),2)+ROUND(ROUND((IF(12<=2,'Rate Card'!$AD$119,IF(12<=5,'Rate Card'!$AE$119,IF(12<=10,'Rate Card'!$AF$119,IF(12<=15,'Rate Card'!$AG$119,IF(12<=20,'Rate Card'!$AH$119,IF(12<=35,'Rate Card'!$AH$119+(12-20)*'Rate Card'!$AI$119,'Rate Card'!$AK$119+(12-35)*'Rate Card'!$AJ$119)))))))*(1+'Rate Card'!$C$6),2)*(IF('Rate Card'!$G$6="YES",'Rate Card'!$E$6,0)+IF('Rate Card'!$K$6="YES",'Rate Card'!$I$6,0)),2) | P16: =IF(12<=2,'Rate Card'!$AD$120,IF(12<=5,'Rate Card'!$AE$120,IF(12<=10,'Rate Card'!$AF$120,IF(12<=15,'Rate Card'!$AG$120,IF(12<=20,'Rate Card'!$AH$120,IF(12<=35,'Rate Card'!$AH$120+(12-20)*'Rate Card'!$AI$120,'Rate Card'!$AK$120+(12-35)*'Rate Card'!$AJ$120)))))) | Q16: =ROUND((IF(12<=2,'Rate Card'!$AD$120,IF(12<=5,'Rate Card'!$AE$120,IF(12<=10,'Rate Card'!$AF$120,IF(12<=15,'Rate Card'!$AG$120,IF(12<=20,'Rate Card'!$AH$120,IF(12<=35,'Rate Card'!$AH$120+(12-20)*'Rate Card'!$AI$120,'Rate Card'!$AK$120+(12-35)*'Rate Card'!$AJ$120)))))))*(1+'Rate Card'!$C$6),2)+ROUND(ROUND((IF(12<=2,'Rate Card'!$AD$120,IF(12<=5,'Rate Card'!$AE$120,IF(12<=10,'Rate Card'!$AF$120,IF(12<=15,'Rate Card'!$AG$120,IF(12<=20,'Rate Card'!$AH$120,IF(12<=35,'Rate Card'!$AH$120+(12-20)*'Rate Card'!$AI$120,'Rate Card'!$AK$120+(12-35)*'Rate Card'!$AJ$120)))))))*(1+'Rate Card'!$C$6),2)*(IF('Rate Card'!$G$6="YES",'Rate Card'!$E$6,0)+IF('Rate Card'!$K$6="YES",'Rate Card'!$I$6,0)),2)
A17: 13 | B17: =IF(13<=5,'Rate Card'!$AD$20,'Rate Card'!$AD$20+(13-5)*'Rate Card'!$AE$20) | C17: =ROUND((IF(13<=5,'Rate Card'!$AD$20,'Rate Card'!$AD$20+(13-5)*'Rate Card'!$AE$20))*(1+'Rate Card'!$C$6),2)+ROUND(ROUND((IF(13<=5,'Rate Card'!$AD$20,'Rate Card'!$AD$20+(13-5)*'Rate Card'!$AE$20))*(1+'Rate Card'!$C$6),2)*(IF('Rate Card'!$G$6="YES",'Rate Card'!$E$6,0)+IF('Rate Card'!$K$6="YES",'Rate Card'!$I$6,0)),2) | D17: =IF(13<=15,'Rate Card'!$AD$21,'Rate Card'!$AD$21+(13-15)*'Rate Card'!$AE$21) | E17: =ROUND((IF(13<=15,'Rate Card'!$AD$21,'Rate Card'!$AD$21+(13-15)*'Rate Card'!$AE$21))*(1+'Rate Card'!$C$6),2)+ROUND(ROUND((IF(13<=15,'Rate Card'!$AD$21,'Rate Card'!$AD$21+(13-15)*'Rate Card'!$AE$21))*(1+'Rate Card'!$C$6),2)*(IF('Rate Card'!$G$6="YES",'Rate Card'!$E$6,0)+IF('Rate Card'!$K$6="YES",'Rate Card'!$I$6,0)),2) | F17: =IF(13<=2,'Rate Card'!$AD$22,IF(13<=5,'Rate Card'!$AE$22,IF(13<=10,'Rate Card'!$AF$22,IF(13<=15,'Rate Card'!$AG$22,IF(13<=20,'Rate Card'!$AH$22,IF(13<=35,'Rate Card'!$AH$22+(13-20)*'Rate Card'!$AI$22,'Rate Card'!$AK$22+(13-35)*'Rate Card'!$AJ$22)))))) | G17: =ROUND((IF(13<=2,'Rate Card'!$AD$22,IF(13<=5,'Rate Card'!$AE$22,IF(13<=10,'Rate Card'!$AF$22,IF(13<=15,'Rate Card'!$AG$22,IF(13<=20,'Rate Card'!$AH$22,IF(13<=35,'Rate Card'!$AH$22+(13-20)*'Rate Card'!$AI$22,'Rate Card'!$AK$22+(13-35)*'Rate Card'!$AJ$22)))))))*(1+'Rate Card'!$C$6),2)+ROUND(ROUND((IF(13<=2,'Rate Card'!$AD$22,IF(13<=5,'Rate Card'!$AE$22,IF(13<=10,'Rate Card'!$AF$22,IF(13<=15,'Rate Card'!$AG$22,IF(13<=20,'Rate Card'!$AH$22,IF(13<=35,'Rate Card'!$AH$22+(13-20)*'Rate Card'!$AI$22,'Rate Card'!$AK$22+(13-35)*'Rate Card'!$AJ$22)))))))*(1+'Rate Card'!$C$6),2)*(IF('Rate Card'!$G$6="YES",'Rate Card'!$E$6,0)+IF('Rate Card'!$K$6="YES",'Rate Card'!$I$6,0)),2) | H17: =IF(13<=2,'Rate Card'!$AD$23,IF(13<=5,'Rate Card'!$AE$23,IF(13<=10,'Rate Card'!$AF$23,IF(13<=15,'Rate Card'!$AG$23,IF(13<=20,'Rate Card'!$AH$23,IF(13<=35,'Rate Card'!$AH$23+(13-20)*'Rate Card'!$AI$23,'Rate Card'!$AK$23+(13-35)*'Rate Card'!$AJ$23)))))) | I17: =ROUND((IF(13<=2,'Rate Card'!$AD$23,IF(13<=5,'Rate Card'!$AE$23,IF(13<=10,'Rate Card'!$AF$23,IF(13<=15,'Rate Card'!$AG$23,IF(13<=20,'Rate Card'!$AH$23,IF(13<=35,'Rate Card'!$AH$23+(13-20)*'Rate Card'!$AI$23,'Rate Card'!$AK$23+(13-35)*'Rate Card'!$AJ$23)))))))*(1+'Rate Card'!$C$6),2)+ROUND(ROUND((IF(13<=2,'Rate Card'!$AD$23,IF(13<=5,'Rate Card'!$AE$23,IF(13<=10,'Rate Card'!$AF$23,IF(13<=15,'Rate Card'!$AG$23,IF(13<=20,'Rate Card'!$AH$23,IF(13<=35,'Rate Card'!$AH$23+(13-20)*'Rate Card'!$AI$23,'Rate Card'!$AK$23+(13-35)*'Rate Card'!$AJ$23)))))))*(1+'Rate Card'!$C$6),2)*(IF('Rate Card'!$G$6="YES",'Rate Card'!$E$6,0)+IF('Rate Card'!$K$6="YES",'Rate Card'!$I$6,0)),2) | J17: =IF(13<=5,'Rate Card'!$AD$117,'Rate Card'!$AD$117+(13-5)*'Rate Card'!$AE$117) | K17: =ROUND((IF(13<=5,'Rate Card'!$AD$117,'Rate Card'!$AD$117+(13-5)*'Rate Card'!$AE$117))*(1+'Rate Card'!$C$6),2)+ROUND(ROUND((IF(13<=5,'Rate Card'!$AD$117,'Rate Card'!$AD$117+(13-5)*'Rate Card'!$AE$117))*(1+'Rate Card'!$C$6),2)*(IF('Rate Card'!$G$6="YES",'Rate Card'!$E$6,0)+IF('Rate Card'!$K$6="YES",'Rate Card'!$I$6,0)),2) | L17: =IF(13<=15,'Rate Card'!$AD$118,'Rate Card'!$AD$118+(13-15)*'Rate Card'!$AE$118) | M17: =ROUND((IF(13<=15,'Rate Card'!$AD$118,'Rate Card'!$AD$118+(13-15)*'Rate Card'!$AE$118))*(1+'Rate Card'!$C$6),2)+ROUND(ROUND((IF(13<=15,'Rate Card'!$AD$118,'Rate Card'!$AD$118+(13-15)*'Rate Card'!$AE$118))*(1+'Rate Card'!$C$6),2)*(IF('Rate Card'!$G$6="YES",'Rate Card'!$E$6,0)+IF('Rate Card'!$K$6="YES",'Rate Card'!$I$6,0)),2) | N17: =IF(13<=2,'Rate Card'!$AD$119,IF(13<=5,'Rate Card'!$AE$119,IF(13<=10,'Rate Card'!$AF$119,IF(13<=15,'Rate Card'!$AG$119,IF(13<=20,'Rate Card'!$AH$119,IF(13<=35,'Rate Card'!$AH$119+(13-20)*'Rate Card'!$AI$119,'Rate Card'!$AK$119+(13-35)*'Rate Card'!$AJ$119)))))) | O17: =ROUND((IF(13<=2,'Rate Card'!$AD$119,IF(13<=5,'Rate Card'!$AE$119,IF(13<=10,'Rate Card'!$AF$119,IF(13<=15,'Rate Card'!$AG$119,IF(13<=20,'Rate Card'!$AH$119,IF(13<=35,'Rate Card'!$AH$119+(13-20)*'Rate Card'!$AI$119,'Rate Card'!$AK$119+(13-35)*'Rate Card'!$AJ$119)))))))*(1+'Rate Card'!$C$6),2)+ROUND(ROUND((IF(13<=2,'Rate Card'!$AD$119,IF(13<=5,'Rate Card'!$AE$119,IF(13<=10,'Rate Card'!$AF$119,IF(13<=15,'Rate Card'!$AG$119,IF(13<=20,'Rate Card'!$AH$119,IF(13<=35,'Rate Card'!$AH$119+(13-20)*'Rate Card'!$AI$119,'Rate Card'!$AK$119+(13-35)*'Rate Card'!$AJ$119)))))))*(1+'Rate Card'!$C$6),2)*(IF('Rate Card'!$G$6="YES",'Rate Card'!$E$6,0)+IF('Rate Card'!$K$6="YES",'Rate Card'!$I$6,0)),2) | P17: =IF(13<=2,'Rate Card'!$AD$120,IF(13<=5,'Rate Card'!$AE$120,IF(13<=10,'Rate Card'!$AF$120,IF(13<=15,'Rate Card'!$AG$120,IF(13<=20,'Rate Card'!$AH$120,IF(13<=35,'Rate Card'!$AH$120+(13-20)*'Rate Card'!$AI$120,'Rate Card'!$AK$120+(13-35)*'Rate Card'!$AJ$120)))))) | Q17: =ROUND((IF(13<=2,'Rate Card'!$AD$120,IF(13<=5,'Rate Card'!$AE$120,IF(13<=10,'Rate Card'!$AF$120,IF(13<=15,'Rate Card'!$AG$120,IF(13<=20,'Rate Card'!$AH$120,IF(13<=35,'Rate Card'!$AH$120+(13-20)*'Rate Card'!$AI$120,'Rate Card'!$AK$120+(13-35)*'Rate Card'!$AJ$120)))))))*(1+'Rate Card'!$C$6),2)+ROUND(ROUND((IF(13<=2,'Rate Card'!$AD$120,IF(13<=5,'Rate Card'!$AE$120,IF(13<=10,'Rate Card'!$AF$120,IF(13<=15,'Rate Card'!$AG$120,IF(13<=20,'Rate Card'!$AH$120,IF(13<=35,'Rate Card'!$AH$120+(13-20)*'Rate Card'!$AI$120,'Rate Card'!$AK$120+(13-35)*'Rate Card'!$AJ$120)))))))*(1+'Rate Card'!$C$6),2)*(IF('Rate Card'!$G$6="YES",'Rate Card'!$E$6,0)+IF('Rate Card'!$K$6="YES",'Rate Card'!$I$6,0)),2)
A18: 14 | B18: =IF(14<=5,'Rate Card'!$AD$20,'Rate Card'!$AD$20+(14-5)*'Rate Card'!$AE$20) | C18: =ROUND((IF(14<=5,'Rate Card'!$AD$20,'Rate Card'!$AD$20+(14-5)*'Rate Card'!$AE$20))*(1+'Rate Card'!$C$6),2)+ROUND(ROUND((IF(14<=5,'Rate Card'!$AD$20,'Rate Card'!$AD$20+(14-5)*'Rate Card'!$AE$20))*(1+'Rate Card'!$C$6),2)*(IF('Rate Card'!$G$6="YES",'Rate Card'!$E$6,0)+IF('Rate Card'!$K$6="YES",'Rate Card'!$I$6,0)),2) | D18: =IF(14<=15,'Rate Card'!$AD$21,'Rate Card'!$AD$21+(14-15)*'Rate Card'!$AE$21) | E18: =ROUND((IF(14<=15,'Rate Card'!$AD$21,'Rate Card'!$AD$21+(14-15)*'Rate Card'!$AE$21))*(1+'Rate Card'!$C$6),2)+ROUND(ROUND((IF(14<=15,'Rate Card'!$AD$21,'Rate Card'!$AD$21+(14-15)*'Rate Card'!$AE$21))*(1+'Rate Card'!$C$6),2)*(IF('Rate Card'!$G$6="YES",'Rate Card'!$E$6,0)+IF('Rate Card'!$K$6="YES",'Rate Card'!$I$6,0)),2) | F18: =IF(14<=2,'Rate Card'!$AD$22,IF(14<=5,'Rate Card'!$AE$22,IF(14<=10,'Rate Card'!$AF$22,IF(14<=15,'Rate Card'!$AG$22,IF(14<=20,'Rate Card'!$AH$22,IF(14<=35,'Rate Card'!$AH$22+(14-20)*'Rate Card'!$AI$22,'Rate Card'!$AK$22+(14-35)*'Rate Card'!$AJ$22)))))) | G18: =ROUND((IF(14<=2,'Rate Card'!$AD$22,IF(14<=5,'Rate Card'!$AE$22,IF(14<=10,'Rate Card'!$AF$22,IF(14<=15,'Rate Card'!$AG$22,IF(14<=20,'Rate Card'!$AH$22,IF(14<=35,'Rate Card'!$AH$22+(14-20)*'Rate Card'!$AI$22,'Rate Card'!$AK$22+(14-35)*'Rate Card'!$AJ$22)))))))*(1+'Rate Card'!$C$6),2)+ROUND(ROUND((IF(14<=2,'Rate Card'!$AD$22,IF(14<=5,'Rate Card'!$AE$22,IF(14<=10,'Rate Card'!$AF$22,IF(14<=15,'Rate Card'!$AG$22,IF(14<=20,'Rate Card'!$AH$22,IF(14<=35,'Rate Card'!$AH$22+(14-20)*'Rate Card'!$AI$22,'Rate Card'!$AK$22+(14-35)*'Rate Card'!$AJ$22)))))))*(1+'Rate Card'!$C$6),2)*(IF('Rate Card'!$G$6="YES",'Rate Card'!$E$6,0)+IF('Rate Card'!$K$6="YES",'Rate Card'!$I$6,0)),2) | H18: =IF(14<=2,'Rate Card'!$AD$23,IF(14<=5,'Rate Card'!$AE$23,IF(14<=10,'Rate Card'!$AF$23,IF(14<=15,'Rate Card'!$AG$23,IF(14<=20,'Rate Card'!$AH$23,IF(14<=35,'Rate Card'!$AH$23+(14-20)*'Rate Card'!$AI$23,'Rate Card'!$AK$23+(14-35)*'Rate Card'!$AJ$23)))))) | I18: =ROUND((IF(14<=2,'Rate Card'!$AD$23,IF(14<=5,'Rate Card'!$AE$23,IF(14<=10,'Rate Card'!$AF$23,IF(14<=15,'Rate Card'!$AG$23,IF(14<=20,'Rate Card'!$AH$23,IF(14<=35,'Rate Card'!$AH$23+(14-20)*'Rate Card'!$AI$23,'Rate Card'!$AK$23+(14-35)*'Rate Card'!$AJ$23)))))))*(1+'Rate Card'!$C$6),2)+ROUND(ROUND((IF(14<=2,'Rate Card'!$AD$23,IF(14<=5,'Rate Card'!$AE$23,IF(14<=10,'Rate Card'!$AF$23,IF(14<=15,'Rate Card'!$AG$23,IF(14<=20,'Rate Card'!$AH$23,IF(14<=35,'Rate Card'!$AH$23+(14-20)*'Rate Card'!$AI$23,'Rate Card'!$AK$23+(14-35)*'Rate Card'!$AJ$23)))))))*(1+'Rate Card'!$C$6),2)*(IF('Rate Card'!$G$6="YES",'Rate Card'!$E$6,0)+IF('Rate Card'!$K$6="YES",'Rate Card'!$I$6,0)),2) | J18: =IF(14<=5,'Rate Card'!$AD$117,'Rate Card'!$AD$117+(14-5)*'Rate Card'!$AE$117) | K18: =ROUND((IF(14<=5,'Rate Card'!$AD$117,'Rate Card'!$AD$117+(14-5)*'Rate Card'!$AE$117))*(1+'Rate Card'!$C$6),2)+ROUND(ROUND((IF(14<=5,'Rate Card'!$AD$117,'Rate Card'!$AD$117+(14-5)*'Rate Card'!$AE$117))*(1+'Rate Card'!$C$6),2)*(IF('Rate Card'!$G$6="YES",'Rate Card'!$E$6,0)+IF('Rate Card'!$K$6="YES",'Rate Card'!$I$6,0)),2) | L18: =IF(14<=15,'Rate Card'!$AD$118,'Rate Card'!$AD$118+(14-15)*'Rate Card'!$AE$118) | M18: =ROUND((IF(14<=15,'Rate Card'!$AD$118,'Rate Card'!$AD$118+(14-15)*'Rate Card'!$AE$118))*(1+'Rate Card'!$C$6),2)+ROUND(ROUND((IF(14<=15,'Rate Card'!$AD$118,'Rate Card'!$AD$118+(14-15)*'Rate Card'!$AE$118))*(1+'Rate Card'!$C$6),2)*(IF('Rate Card'!$G$6="YES",'Rate Card'!$E$6,0)+IF('Rate Card'!$K$6="YES",'Rate Card'!$I$6,0)),2) | N18: =IF(14<=2,'Rate Card'!$AD$119,IF(14<=5,'Rate Card'!$AE$119,IF(14<=10,'Rate Card'!$AF$119,IF(14<=15,'Rate Card'!$AG$119,IF(14<=20,'Rate Card'!$AH$119,IF(14<=35,'Rate Card'!$AH$119+(14-20)*'Rate Card'!$AI$119,'Rate Card'!$AK$119+(14-35)*'Rate Card'!$AJ$119)))))) | O18: =ROUND((IF(14<=2,'Rate Card'!$AD$119,IF(14<=5,'Rate Card'!$AE$119,IF(14<=10,'Rate Card'!$AF$119,IF(14<=15,'Rate Card'!$AG$119,IF(14<=20,'Rate Card'!$AH$119,IF(14<=35,'Rate Card'!$AH$119+(14-20)*'Rate Card'!$AI$119,'Rate Card'!$AK$119+(14-35)*'Rate Card'!$AJ$119)))))))*(1+'Rate Card'!$C$6),2)+ROUND(ROUND((IF(14<=2,'Rate Card'!$AD$119,IF(14<=5,'Rate Card'!$AE$119,IF(14<=10,'Rate Card'!$AF$119,IF(14<=15,'Rate Card'!$AG$119,IF(14<=20,'Rate Card'!$AH$119,IF(14<=35,'Rate Card'!$AH$119+(14-20)*'Rate Card'!$AI$119,'Rate Card'!$AK$119+(14-35)*'Rate Card'!$AJ$119)))))))*(1+'Rate Card'!$C$6),2)*(IF('Rate Card'!$G$6="YES",'Rate Card'!$E$6,0)+IF('Rate Card'!$K$6="YES",'Rate Card'!$I$6,0)),2) | P18: =IF(14<=2,'Rate Card'!$AD$120,IF(14<=5,'Rate Card'!$AE$120,IF(14<=10,'Rate Card'!$AF$120,IF(14<=15,'Rate Card'!$AG$120,IF(14<=20,'Rate Card'!$AH$120,IF(14<=35,'Rate Card'!$AH$120+(14-20)*'Rate Card'!$AI$120,'Rate Card'!$AK$120+(14-35)*'Rate Card'!$AJ$120)))))) | Q18: =ROUND((IF(14<=2,'Rate Card'!$AD$120,IF(14<=5,'Rate Card'!$AE$120,IF(14<=10,'Rate Card'!$AF$120,IF(14<=15,'Rate Card'!$AG$120,IF(14<=20,'Rate Card'!$AH$120,IF(14<=35,'Rate Card'!$AH$120+(14-20)*'Rate Card'!$AI$120,'Rate Card'!$AK$120+(14-35)*'Rate Card'!$AJ$120)))))))*(1+'Rate Card'!$C$6),2)+ROUND(ROUND((IF(14<=2,'Rate Card'!$AD$120,IF(14<=5,'Rate Card'!$AE$120,IF(14<=10,'Rate Card'!$AF$120,IF(14<=15,'Rate Card'!$AG$120,IF(14<=20,'Rate Card'!$AH$120,IF(14<=35,'Rate Card'!$AH$120+(14-20)*'Rate Card'!$AI$120,'Rate Card'!$AK$120+(14-35)*'Rate Card'!$AJ$120)))))))*(1+'Rate Card'!$C$6),2)*(IF('Rate Card'!$G$6="YES",'Rate Card'!$E$6,0)+IF('Rate Card'!$K$6="YES",'Rate Card'!$I$6,0)),2)
A19: 15 | B19: =IF(15<=5,'Rate Card'!$AD$20,'Rate Card'!$AD$20+(15-5)*'Rate Card'!$AE$20) | C19: =ROUND((IF(15<=5,'Rate Card'!$AD$20,'Rate Card'!$AD$20+(15-5)*'Rate Card'!$AE$20))*(1+'Rate Card'!$C$6),2)+ROUND(ROUND((IF(15<=5,'Rate Card'!$AD$20,'Rate Card'!$AD$20+(15-5)*'Rate Card'!$AE$20))*(1+'Rate Card'!$C$6),2)*(IF('Rate Card'!$G$6="YES",'Rate Card'!$E$6,0)+IF('Rate Card'!$K$6="YES",'Rate Card'!$I$6,0)),2) | D19: =IF(15<=15,'Rate Card'!$AD$21,'Rate Card'!$AD$21+(15-15)*'Rate Card'!$AE$21) | E19: =ROUND((IF(15<=15,'Rate Card'!$AD$21,'Rate Card'!$AD$21+(15-15)*'Rate Card'!$AE$21))*(1+'Rate Card'!$C$6),2)+ROUND(ROUND((IF(15<=15,'Rate Card'!$AD$21,'Rate Card'!$AD$21+(15-15)*'Rate Card'!$AE$21))*(1+'Rate Card'!$C$6),2)*(IF('Rate Card'!$G$6="YES",'Rate Card'!$E$6,0)+IF('Rate Card'!$K$6="YES",'Rate Card'!$I$6,0)),2) | F19: =IF(15<=2,'Rate Card'!$AD$22,IF(15<=5,'Rate Card'!$AE$22,IF(15<=10,'Rate Card'!$AF$22,IF(15<=15,'Rate Card'!$AG$22,IF(15<=20,'Rate Card'!$AH$22,IF(15<=35,'Rate Card'!$AH$22+(15-20)*'Rate Card'!$AI$22,'Rate Card'!$AK$22+(15-35)*'Rate Card'!$AJ$22)))))) | G19: =ROUND((IF(15<=2,'Rate Card'!$AD$22,IF(15<=5,'Rate Card'!$AE$22,IF(15<=10,'Rate Card'!$AF$22,IF(15<=15,'Rate Card'!$AG$22,IF(15<=20,'Rate Card'!$AH$22,IF(15<=35,'Rate Card'!$AH$22+(15-20)*'Rate Card'!$AI$22,'Rate Card'!$AK$22+(15-35)*'Rate Card'!$AJ$22)))))))*(1+'Rate Card'!$C$6),2)+ROUND(ROUND((IF(15<=2,'Rate Card'!$AD$22,IF(15<=5,'Rate Card'!$AE$22,IF(15<=10,'Rate Card'!$AF$22,IF(15<=15,'Rate Card'!$AG$22,IF(15<=20,'Rate Card'!$AH$22,IF(15<=35,'Rate Card'!$AH$22+(15-20)*'Rate Card'!$AI$22,'Rate Card'!$AK$22+(15-35)*'Rate Card'!$AJ$22)))))))*(1+'Rate Card'!$C$6),2)*(IF('Rate Card'!$G$6="YES",'Rate Card'!$E$6,0)+IF('Rate Card'!$K$6="YES",'Rate Card'!$I$6,0)),2) | H19: =IF(15<=2,'Rate Card'!$AD$23,IF(15<=5,'Rate Card'!$AE$23,IF(15<=10,'Rate Card'!$AF$23,IF(15<=15,'Rate Card'!$AG$23,IF(15<=20,'Rate Card'!$AH$23,IF(15<=35,'Rate Card'!$AH$23+(15-20)*'Rate Card'!$AI$23,'Rate Card'!$AK$23+(15-35)*'Rate Card'!$AJ$23)))))) | I19: =ROUND((IF(15<=2,'Rate Card'!$AD$23,IF(15<=5,'Rate Card'!$AE$23,IF(15<=10,'Rate Card'!$AF$23,IF(15<=15,'Rate Card'!$AG$23,IF(15<=20,'Rate Card'!$AH$23,IF(15<=35,'Rate Card'!$AH$23+(15-20)*'Rate Card'!$AI$23,'Rate Card'!$AK$23+(15-35)*'Rate Card'!$AJ$23)))))))*(1+'Rate Card'!$C$6),2)+ROUND(ROUND((IF(15<=2,'Rate Card'!$AD$23,IF(15<=5,'Rate Card'!$AE$23,IF(15<=10,'Rate Card'!$AF$23,IF(15<=15,'Rate Card'!$AG$23,IF(15<=20,'Rate Card'!$AH$23,IF(15<=35,'Rate Card'!$AH$23+(15-20)*'Rate Card'!$AI$23,'Rate Card'!$AK$23+(15-35)*'Rate Card'!$AJ$23)))))))*(1+'Rate Card'!$C$6),2)*(IF('Rate Card'!$G$6="YES",'Rate Card'!$E$6,0)+IF('Rate Card'!$K$6="YES",'Rate Card'!$I$6,0)),2) | J19: =IF(15<=5,'Rate Card'!$AD$117,'Rate Card'!$AD$117+(15-5)*'Rate Card'!$AE$117) | K19: =ROUND((IF(15<=5,'Rate Card'!$AD$117,'Rate Card'!$AD$117+(15-5)*'Rate Card'!$AE$117))*(1+'Rate Card'!$C$6),2)+ROUND(ROUND((IF(15<=5,'Rate Card'!$AD$117,'Rate Card'!$AD$117+(15-5)*'Rate Card'!$AE$117))*(1+'Rate Card'!$C$6),2)*(IF('Rate Card'!$G$6="YES",'Rate Card'!$E$6,0)+IF('Rate Card'!$K$6="YES",'Rate Card'!$I$6,0)),2) | L19: =IF(15<=15,'Rate Card'!$AD$118,'Rate Card'!$AD$118+(15-15)*'Rate Card'!$AE$118) | M19: =ROUND((IF(15<=15,'Rate Card'!$AD$118,'Rate Card'!$AD$118+(15-15)*'Rate Card'!$AE$118))*(1+'Rate Card'!$C$6),2)+ROUND(ROUND((IF(15<=15,'Rate Card'!$AD$118,'Rate Card'!$AD$118+(15-15)*'Rate Card'!$AE$118))*(1+'Rate Card'!$C$6),2)*(IF('Rate Card'!$G$6="YES",'Rate Card'!$E$6,0)+IF('Rate Card'!$K$6="YES",'Rate Card'!$I$6,0)),2) | N19: =IF(15<=2,'Rate Card'!$AD$119,IF(15<=5,'Rate Card'!$AE$119,IF(15<=10,'Rate Card'!$AF$119,IF(15<=15,'Rate Card'!$AG$119,IF(15<=20,'Rate Card'!$AH$119,IF(15<=35,'Rate Card'!$AH$119+(15-20)*'Rate Card'!$AI$119,'Rate Card'!$AK$119+(15-35)*'Rate Card'!$AJ$119)))))) | O19: =ROUND((IF(15<=2,'Rate Card'!$AD$119,IF(15<=5,'Rate Card'!$AE$119,IF(15<=10,'Rate Card'!$AF$119,IF(15<=15,'Rate Card'!$AG$119,IF(15<=20,'Rate Card'!$AH$119,IF(15<=35,'Rate Card'!$AH$119+(15-20)*'Rate Card'!$AI$119,'Rate Card'!$AK$119+(15-35)*'Rate Card'!$AJ$119)))))))*(1+'Rate Card'!$C$6),2)+ROUND(ROUND((IF(15<=2,'Rate Card'!$AD$119,IF(15<=5,'Rate Card'!$AE$119,IF(15<=10,'Rate Card'!$AF$119,IF(15<=15,'Rate Card'!$AG$119,IF(15<=20,'Rate Card'!$AH$119,IF(15<=35,'Rate Card'!$AH$119+(15-20)*'Rate Card'!$AI$119,'Rate Card'!$AK$119+(15-35)*'Rate Card'!$AJ$119)))))))*(1+'Rate Card'!$C$6),2)*(IF('Rate Card'!$G$6="YES",'Rate Card'!$E$6,0)+IF('Rate Card'!$K$6="YES",'Rate Card'!$I$6,0)),2) | P19: =IF(15<=2,'Rate Card'!$AD$120,IF(15<=5,'Rate Card'!$AE$120,IF(15<=10,'Rate Card'!$AF$120,IF(15<=15,'Rate Card'!$AG$120,IF(15<=20,'Rate Card'!$AH$120,IF(15<=35,'Rate Card'!$AH$120+(15-20)*'Rate Card'!$AI$120,'Rate Card'!$AK$120+(15-35)*'Rate Card'!$AJ$120)))))) | Q19: =ROUND((IF(15<=2,'Rate Card'!$AD$120,IF(15<=5,'Rate Card'!$AE$120,IF(15<=10,'Rate Card'!$AF$120,IF(15<=15,'Rate Card'!$AG$120,IF(15<=20,'Rate Card'!$AH$120,IF(15<=35,'Rate Card'!$AH$120+(15-20)*'Rate Card'!$AI$120,'Rate Card'!$AK$120+(15-35)*'Rate Card'!$AJ$120)))))))*(1+'Rate Card'!$C$6),2)+ROUND(ROUND((IF(15<=2,'Rate Card'!$AD$120,IF(15<=5,'Rate Card'!$AE$120,IF(15<=10,'Rate Card'!$AF$120,IF(15<=15,'Rate Card'!$AG$120,IF(15<=20,'Rate Card'!$AH$120,IF(15<=35,'Rate Card'!$AH$120+(15-20)*'Rate Card'!$AI$120,'Rate Card'!$AK$120+(15-35)*'Rate Card'!$AJ$120)))))))*(1+'Rate Card'!$C$6),2)*(IF('Rate Card'!$G$6="YES",'Rate Card'!$E$6,0)+IF('Rate Card'!$K$6="YES",'Rate Card'!$I$6,0)),2)
A20: 16 | B20: =IF(16<=5,'Rate Card'!$AD$20,'Rate Card'!$AD$20+(16-5)*'Rate Card'!$AE$20) | C20: =ROUND((IF(16<=5,'Rate Card'!$AD$20,'Rate Card'!$AD$20+(16-5)*'Rate Card'!$AE$20))*(1+'Rate Card'!$C$6),2)+ROUND(ROUND((IF(16<=5,'Rate Card'!$AD$20,'Rate Card'!$AD$20+(16-5)*'Rate Card'!$AE$20))*(1+'Rate Card'!$C$6),2)*(IF('Rate Card'!$G$6="YES",'Rate Card'!$E$6,0)+IF('Rate Card'!$K$6="YES",'Rate Card'!$I$6,0)),2) | D20: =IF(16<=15,'Rate Card'!$AD$21,'Rate Card'!$AD$21+(16-15)*'Rate Card'!$AE$21) | E20: =ROUND((IF(16<=15,'Rate Card'!$AD$21,'Rate Card'!$AD$21+(16-15)*'Rate Card'!$AE$21))*(1+'Rate Card'!$C$6),2)+ROUND(ROUND((IF(16<=15,'Rate Card'!$AD$21,'Rate Card'!$AD$21+(16-15)*'Rate Card'!$AE$21))*(1+'Rate Card'!$C$6),2)*(IF('Rate Card'!$G$6="YES",'Rate Card'!$E$6,0)+IF('Rate Card'!$K$6="YES",'Rate Card'!$I$6,0)),2) | F20: =IF(16<=2,'Rate Card'!$AD$22,IF(16<=5,'Rate Card'!$AE$22,IF(16<=10,'Rate Card'!$AF$22,IF(16<=15,'Rate Card'!$AG$22,IF(16<=20,'Rate Card'!$AH$22,IF(16<=35,'Rate Card'!$AH$22+(16-20)*'Rate Card'!$AI$22,'Rate Card'!$AK$22+(16-35)*'Rate Card'!$AJ$22)))))) | G20: =ROUND((IF(16<=2,'Rate Card'!$AD$22,IF(16<=5,'Rate Card'!$AE$22,IF(16<=10,'Rate Card'!$AF$22,IF(16<=15,'Rate Card'!$AG$22,IF(16<=20,'Rate Card'!$AH$22,IF(16<=35,'Rate Card'!$AH$22+(16-20)*'Rate Card'!$AI$22,'Rate Card'!$AK$22+(16-35)*'Rate Card'!$AJ$22)))))))*(1+'Rate Card'!$C$6),2)+ROUND(ROUND((IF(16<=2,'Rate Card'!$AD$22,IF(16<=5,'Rate Card'!$AE$22,IF(16<=10,'Rate Card'!$AF$22,IF(16<=15,'Rate Card'!$AG$22,IF(16<=20,'Rate Card'!$AH$22,IF(16<=35,'Rate Card'!$AH$22+(16-20)*'Rate Card'!$AI$22,'Rate Card'!$AK$22+(16-35)*'Rate Card'!$AJ$22)))))))*(1+'Rate Card'!$C$6),2)*(IF('Rate Card'!$G$6="YES",'Rate Card'!$E$6,0)+IF('Rate Card'!$K$6="YES",'Rate Card'!$I$6,0)),2) | H20: =IF(16<=2,'Rate Card'!$AD$23,IF(16<=5,'Rate Card'!$AE$23,IF(16<=10,'Rate Card'!$AF$23,IF(16<=15,'Rate Card'!$AG$23,IF(16<=20,'Rate Card'!$AH$23,IF(16<=35,'Rate Card'!$AH$23+(16-20)*'Rate Card'!$AI$23,'Rate Card'!$AK$23+(16-35)*'Rate Card'!$AJ$23)))))) | I20: =ROUND((IF(16<=2,'Rate Card'!$AD$23,IF(16<=5,'Rate Card'!$AE$23,IF(16<=10,'Rate Card'!$AF$23,IF(16<=15,'Rate Card'!$AG$23,IF(16<=20,'Rate Card'!$AH$23,IF(16<=35,'Rate Card'!$AH$23+(16-20)*'Rate Card'!$AI$23,'Rate Card'!$AK$23+(16-35)*'Rate Card'!$AJ$23)))))))*(1+'Rate Card'!$C$6),2)+ROUND(ROUND((IF(16<=2,'Rate Card'!$AD$23,IF(16<=5,'Rate Card'!$AE$23,IF(16<=10,'Rate Card'!$AF$23,IF(16<=15,'Rate Card'!$AG$23,IF(16<=20,'Rate Card'!$AH$23,IF(16<=35,'Rate Card'!$AH$23+(16-20)*'Rate Card'!$AI$23,'Rate Card'!$AK$23+(16-35)*'Rate Card'!$AJ$23)))))))*(1+'Rate Card'!$C$6),2)*(IF('Rate Card'!$G$6="YES",'Rate Card'!$E$6,0)+IF('Rate Card'!$K$6="YES",'Rate Card'!$I$6,0)),2) | J20: =IF(16<=5,'Rate Card'!$AD$117,'Rate Card'!$AD$117+(16-5)*'Rate Card'!$AE$117) | K20: =ROUND((IF(16<=5,'Rate Card'!$AD$117,'Rate Card'!$AD$117+(16-5)*'Rate Card'!$AE$117))*(1+'Rate Card'!$C$6),2)+ROUND(ROUND((IF(16<=5,'Rate Card'!$AD$117,'Rate Card'!$AD$117+(16-5)*'Rate Card'!$AE$117))*(1+'Rate Card'!$C$6),2)*(IF('Rate Card'!$G$6="YES",'Rate Card'!$E$6,0)+IF('Rate Card'!$K$6="YES",'Rate Card'!$I$6,0)),2) | L20: =IF(16<=15,'Rate Card'!$AD$118,'Rate Card'!$AD$118+(16-15)*'Rate Card'!$AE$118) | M20: =ROUND((IF(16<=15,'Rate Card'!$AD$118,'Rate Card'!$AD$118+(16-15)*'Rate Card'!$AE$118))*(1+'Rate Card'!$C$6),2)+ROUND(ROUND((IF(16<=15,'Rate Card'!$AD$118,'Rate Card'!$AD$118+(16-15)*'Rate Card'!$AE$118))*(1+'Rate Card'!$C$6),2)*(IF('Rate Card'!$G$6="YES",'Rate Card'!$E$6,0)+IF('Rate Card'!$K$6="YES",'Rate Card'!$I$6,0)),2) | N20: =IF(16<=2,'Rate Card'!$AD$119,IF(16<=5,'Rate Card'!$AE$119,IF(16<=10,'Rate Card'!$AF$119,IF(16<=15,'Rate Card'!$AG$119,IF(16<=20,'Rate Card'!$AH$119,IF(16<=35,'Rate Card'!$AH$119+(16-20)*'Rate Card'!$AI$119,'Rate Card'!$AK$119+(16-35)*'Rate Card'!$AJ$119)))))) | O20: =ROUND((IF(16<=2,'Rate Card'!$AD$119,IF(16<=5,'Rate Card'!$AE$119,IF(16<=10,'Rate Card'!$AF$119,IF(16<=15,'Rate Card'!$AG$119,IF(16<=20,'Rate Card'!$AH$119,IF(16<=35,'Rate Card'!$AH$119+(16-20)*'Rate Card'!$AI$119,'Rate Card'!$AK$119+(16-35)*'Rate Card'!$AJ$119)))))))*(1+'Rate Card'!$C$6),2)+ROUND(ROUND((IF(16<=2,'Rate Card'!$AD$119,IF(16<=5,'Rate Card'!$AE$119,IF(16<=10,'Rate Card'!$AF$119,IF(16<=15,'Rate Card'!$AG$119,IF(16<=20,'Rate Card'!$AH$119,IF(16<=35,'Rate Card'!$AH$119+(16-20)*'Rate Card'!$AI$119,'Rate Card'!$AK$119+(16-35)*'Rate Card'!$AJ$119)))))))*(1+'Rate Card'!$C$6),2)*(IF('Rate Card'!$G$6="YES",'Rate Card'!$E$6,0)+IF('Rate Card'!$K$6="YES",'Rate Card'!$I$6,0)),2) | P20: =IF(16<=2,'Rate Card'!$AD$120,IF(16<=5,'Rate Card'!$AE$120,IF(16<=10,'Rate Card'!$AF$120,IF(16<=15,'Rate Card'!$AG$120,IF(16<=20,'Rate Card'!$AH$120,IF(16<=35,'Rate Card'!$AH$120+(16-20)*'Rate Card'!$AI$120,'Rate Card'!$AK$120+(16-35)*'Rate Card'!$AJ$120)))))) | Q20: =ROUND((IF(16<=2,'Rate Card'!$AD$120,IF(16<=5,'Rate Card'!$AE$120,IF(16<=10,'Rate Card'!$AF$120,IF(16<=15,'Rate Card'!$AG$120,IF(16<=20,'Rate Card'!$AH$120,IF(16<=35,'Rate Card'!$AH$120+(16-20)*'Rate Card'!$AI$120,'Rate Card'!$AK$120+(16-35)*'Rate Card'!$AJ$120)))))))*(1+'Rate Card'!$C$6),2)+ROUND(ROUND((IF(16<=2,'Rate Card'!$AD$120,IF(16<=5,'Rate Card'!$AE$120,IF(16<=10,'Rate Card'!$AF$120,IF(16<=15,'Rate Card'!$AG$120,IF(16<=20,'Rate Card'!$AH$120,IF(16<=35,'Rate Card'!$AH$120+(16-20)*'Rate Card'!$AI$120,'Rate Card'!$AK$120+(16-35)*'Rate Card'!$AJ$120)))))))*(1+'Rate Card'!$C$6),2)*(IF('Rate Card'!$G$6="YES",'Rate Card'!$E$6,0)+IF('Rate Card'!$K$6="YES",'Rate Card'!$I$6,0)),2)
